Workbook

Sheet Start Here
A1: Topic | B1: Details
A2: Project | B2: Multirotor Recovery Dynamics — calculations and simulation archive
A3: Source snapshot | B3: fbc4c878a99f68650c70670e7ee3721a6a24e67d
A4: Imported on | B4: 2026-09-28
A5: Scope | B5: All six committed simulation JSON files; engineering CSVs; component studies; equations, model source, plot sources and a reproduced release time series.
A6: Evidence | B6: Simulation outputs describe the historical design profile. They are not measurements of the Veeniix V995.
A7: V995 | B7: Owner-estimated mass around 50 g. Do not substitute the historical 135.66 g design budget for a measured V995 mass.
A8: Raw data | B8: Original JSON fields and CSV values are preserved. Nested objects become dotted columns. JSON arrays in metadata remain JSON text. Blank values remain unavailable, not zero.
A9: Live calculations | B9: Sizing, guard, mixer, statistics and research workbook formulas recalculate in Sheets. Imported simulation outputs are snapshots; editing inputs does not rerun Python dynamics.
A10: Scenarios | B10: Study A and A2 are release_startup. Scenario Trials holds the newer three-arm exploratory diagnostic. Do not pool these as equivalent experiments.
A11: Statistics | B11: Bounds describe Monte Carlo sampling uncertainty conditional on the model. Zero successes does not establish equivalence or physical impossibility.
A12: Historical policy | B12: Package Rankings preserves the source policy key as a historical package/configuration ranking, not a verified runtime switching policy.
... A16: Refresh | B16: Refresh source tables from a new pinned commit, then rebuild charts and recalculate. This workbook is a snapshot, not a live GitHub sync.

Sheet Charts
A1: Chart | B1: Meaning
A2: Release plots | B2: Reproduced nominal release trace; historical design and placeholder torque authority.
A3: Study plots | B3: Frozen touchdown proxy, not physical flight qualification.
A4: Diagnostic plots | B4: Limited exploratory prescribed-upset cohort; three scenario arms, 12 paired draws per cell/package/class.

Sheet Study Charts
A1: Exploratory survivable-set maps — release_startup | B1: One-sided 95% lower bounds by state cell. Frozen assumed touchdown proxy. Simulation only; not measured V995 performance.

Sheet Source Index
A1: Tab | B1: Source path | C1: Source URL | D1: Rows excluding header | E1: Notes
A2: Start Here | D2: 15
A3: Charts | D3: 3
A4: Mass Budget | B4: Engineering Data/mass_budget.csv | C4: https://github.com/500ft/multirotor-recovery-dynamics/blob/fbc4c878a99f68650c70670e7ee3721a6a24e67d/Engineering%20Data/mass_budget.csv | D4: 11 | E4: Imported without changing source evidence status.
A5: Power Budget | B5: Engineering Data/power_budget.csv | C5: https://github.com/500ft/multirotor-recovery-dynamics/blob/fbc4c878a99f68650c70670e7ee3721a6a24e67d/Engineering%20Data/power_budget.csv | D5: 4 | E5: Imported without changing source evidence status.
A6: Estimates | B6: Engineering Data/estimates.csv | C6: https://github.com/500ft/multirotor-recovery-dynamics/blob/fbc4c878a99f68650c70670e7ee3721a6a24e67d/Engineering%20Data/estimates.csv | D6: 23 | E6: Imported without changing source evidence status.
A7: Component Verification | B7: Engineering Data/component_verification.csv | C7: https://github.com/500ft/multirotor-recovery-dynamics/blob/fbc4c878a99f68650c70670e7ee3721a6a24e67d/Engineering%20Data/component_verification.csv | D7: 24 | E7: Imported without changing source evidence status.
A8: Hardware Interfaces | B8: Engineering Data/hardware_interfaces.csv | C8: https://github.com/500ft/multirotor-recovery-dynamics/blob/fbc4c878a99f68650c70670e7ee3721a6a24e67d/Engineering%20Data/hardware_interfaces.csv | D8: 13 | E8: Imported without changing source evidence status.
A9: Instrumentation | B9: Engineering Data/instrumentation.csv | C9: https://github.com/500ft/multirotor-recovery-dynamics/blob/fbc4c878a99f68650c70670e7ee3721a6a24e67d/Engineering%20Data/instrumentation.csv | D9: 11 | E9: Imported without changing source evidence status.
A10: Requirements | B10: Engineering Data/requirements.csv | C10: https://github.com/500ft/multirotor-recovery-dynamics/blob/fbc4c878a99f68650c70670e7ee3721a6a24e67d/Engineering%20Data/requirements.csv | D10: 17 | E10: Imported without changing source evidence status.
A11: BOM | B11: Design Report/BOM.csv | C11: https://github.com/500ft/multirotor-recovery-dynamics/blob/fbc4c878a99f68650c70670e7ee3721a6a24e67d/Design%20Report/BOM.csv | D11: 16 | E11: Imported without changing source evidence status.
A12: Purchase Checklist | B12: Engineering Data/purchase_checklist.csv | C12: https://github.com/500ft/multirotor-recovery-dynamics/blob/fbc4c878a99f68650c70670e7ee3721a6a24e67d/Engineering%20Data/purchase_checklist.csv | D12: 12 | E12: Imported without changing source evidence status.
A13: FMEA | B13: Engineering Data/fmea.csv | C13: https://github.com/500ft/multirotor-recovery-dynamics/blob/fbc4c878a99f68650c70670e7ee3721a6a24e67d/Engineering%20Data/fmea.csv | D13: 10 | E13: Imported without changing source evidence status.
A14: CAD Parameters | B14: cad/bench/parameters.csv | C14: https://github.com/500ft/multirotor-recovery-dynamics/blob/fbc4c878a99f68650c70670e7ee3721a6a24e67d/cad/bench/parameters.csv | D14: 26 | E14: Imported without changing source evidence status.
A15: CAD Input Requests | B15: cad/bench/input-requests.csv | C15: https://github.com/500ft/multirotor-recovery-dynamics/blob/fbc4c878a99f68650c70670e7ee3721a6a24e67d/cad/bench/input-requests.csv | D15: 12 | E15: Imported without changing source evidence status.
... A24: Paired A2 | B24: Data/survivable_set_results_a2.json | C24: https://github.com/500ft/multirotor-recovery-dynamics/blob/fbc4c878a99f68650c70670e7ee3721a6a24e67d/Data/survivable_set_results_a2.json | D24: 96 | E24: Paired mechanism versus reallocation. Null interval bounds remain blank.
A25: Package Rankings | B25: Data/survivable_set_results*.json | D25: 192 | E25: Source policy records; configuration ranking only.
A26: Primary Comparisons | B26: Data/survivable_set_results*.json | D26: 8 | E26: Historical kill-criterion outputs, not a non-inferiority test.
A27: Scenario Trials | B27: Data/scenario-diagnostic/scenario_diagnostic.json | C27: https://github.com/500ft/multirotor-recovery-dynamics/blob/fbc4c878a99f68650c70670e7ee3721a6a24e67d/Data/scenario-diagnostic/scenario_diagnostic.json | D27: 288 | E27: 288 exploratory trial endpoints; source pair indices are preserved. No measured V995 performance.
A28: Scenario Contrasts | B28: Data/scenario-diagnostic/scenario_diagnostic.json | C28: https://github.com/500ft/multirotor-recovery-dynamics/blob/fbc4c878a99f68650c70670e7ee3721a6a24e67d/Data/scenario-diagnostic/scenario_diagnostic.json | D28: 12 | E28: Conditional paired binary comparisons.
A29: Continuous Contrasts | B29: Data/scenario-diagnostic/scenario_diagnostic.json | C29: https://github.com/500ft/multirotor-recovery-dynamics/blob/fbc4c878a99f68650c70670e7ee3721a6a24e67d/Data/scenario-diagnostic/scenario_diagnostic.json | D29: 12 | E29: Paired differences; min/max are not confidence bounds.
A30: Convergence | B30: Data/survivable_set_convergence.json | C30: https://github.com/500ft/multirotor-recovery-dynamics/blob/fbc4c878a99f68650c70670e7ee3721a6a24e67d/Data/survivable_set_convergence.json | D30: 12 | E30: Historical dt diagnostic; does not establish model validity.
A31: Monte Carlo | B31: Data/monte_carlo_results.json | C31: https://github.com/500ft/multirotor-recovery-dynamics/blob/fbc4c878a99f68650c70670e7ee3721a6a24e67d/Data/monte_carlo_results.json | D31: 9 | E31: Committed summaries. Individual draws were not saved.
A32: Release Envelope | B32: Data/release_recovery_results.json | C32: https://github.com/500ft/multirotor-recovery-dynamics/blob/fbc4c878a99f68650c70670e7ee3721a6a24e67d/Data/release_recovery_results.json | D32: 3 | E32: Best-tier bound is sensor-limited, not a demonstrated dynamic failure boundary.
A33: Simulation Metadata | B33: Data/*.json | D33: 125 | E33: Source registration, assumptions, seeds, reported verdicts and runtime metadata.
A34: Recovery Envelope Model | B34: Analysis/recovery.py | C34: https://github.com/500ft/multirotor-recovery-dynamics/blob/fbc4c878a99f68650c70670e7ee3721a6a24e67d/Analysis/recovery.py | D34: 3 | E34: Recomputed first-order envelope. Historical defaults differ from current mass budget and 6-DoF model; intentionally preserved.
A35: Simulation Parameters | B35: Analysis/sim_release_recovery.py | C35: https://github.com/500ft/multirotor-recovery-dynamics/blob/fbc4c878a99f68650c70670e7ee3721a6a24e67d/Analysis/sim_release_recovery.py | D35: 3 | E35: Historical modeled parameters; not V995 measurements.
A36: Release Trace | B36: Analysis/sim_release_recovery.py | C36: https://github.com/500ft/multirotor-recovery-dynamics/blob/fbc4c878a99f68650c70670e7ee3721a6a24e67d/Analysis/sim_release_recovery.py | D36: 12000 | E36: REPRODUCED 2026-09-28. Full 12000 logged samples, dt=0.0005 s. World z positive upward; ground at -3 m. No downsampling.
A37: Sizing Calculations | B37: Analysis/budget.py; Design Report/calculations.md | D37: 23 | E37: Live formulas. Historical design only.
A38: Guard Calculations | B38: Analysis/guard.py | C38: https://github.com/500ft/multirotor-recovery-dynamics/blob/fbc4c878a99f68650c70670e7ee3721a6a24e67d/Analysis/guard.py | D38: 3 | E38: Assumed linear-elastic inputs. Does not establish fracture survival.
A39: Mixer Authority | B39: Analysis/sim_release_recovery.py | C39: https://github.com/500ft/multirotor-recovery-dynamics/blob/fbc4c878a99f68650c70670e7ee3721a6a24e67d/Analysis/sim_release_recovery.py | D39: 101 | E39: Four healthy symmetric rotors; assumed 60 mm arm. Not the rotor-out allocation solution.
A40: Statistics Calculations | B40: Analysis/classifier_stats.py; Analysis/monte_carlo_recovery.py | D40: 7 | E40: Illustrative live formulas. No Tango interval or non-inferiority claim added.
A41: CS Component Candidates | B41: Research/Component Study/Drone_Component_and_Propulsion_Study.xlsx#Component Candidates | D41: 45 | E41: Original component workbook; all 157 formulas retained with translated sheet references. Historical catalog assumptions.
A42: CS Reference Drones | B42: Research/Component Study/Drone_Component_and_Propulsion_Study.xlsx#Reference Drones | D42: 11 | E42: Original component workbook; all 157 formulas retained with translated sheet references. Historical catalog assumptions.
A43: CS Battery Architectures | B43: Research/Component Study/Drone_Component_and_Propulsion_Study.xlsx#Battery Architectures | D43: 10 | E43: Original component workbook; all 157 formulas retained with translated sheet references. Historical catalog assumptions.
A44: CS Propulsion Study | B44: Research/Component Study/Drone_Component_and_Propulsion_Study.xlsx#Propulsion Study | D44: 16 | E44: Original component workbook; all 157 formulas retained with translated sheet references. Historical catalog assumptions.
A45: CS Sources | B45: Research/Component Study/Drone_Component_and_Propulsion_Study.xlsx#Assumptions & Sources | D45: 20 | E45: Original component workbook; all 157 formulas retained with translated sheet references. Historical catalog assumptions.
A46: CS Dashboard | B46: Research/Component Study/Drone_Component_and_Propulsion_Study.xlsx#Dashboard | D46: 30 | E46: Original component workbook; all 157 formulas retained with translated sheet references. Historical catalog assumptions.
A47: CS Checks | B47: Research/Component Study/Drone_Component_and_Propulsion_Study.xlsx#Checks | D47: 10 | E47: Original component workbook; all 157 formulas retained with translated sheet references. Historical catalog assumptions.
A48: Component Selection | B48: Research/Component Study/component-selection-2026/Component_Selection_2026.xlsx | C48: https://github.com/500ft/multirotor-recovery-dynamics/blob/fbc4c878a99f68650c70670e7ee3721a6a24e67d/Research/Component%20Study/component-selection-2026/Component_Selection_2026.xlsx | D48: 209 | E48: Lossless nonempty-row archive of all 22 original tabs. Original headings retained as rows; source column letters map back to workbook.
A49: Tier Research | B49: Research/Component Study/unrestricted-tier-study-2026/results/ | C49: https://github.com/500ft/multirotor-recovery-dynamics/blob/fbc4c878a99f68650c70670e7ee3721a6a24e67d/Research/Component%20Study/unrestricted-tier-study-2026/results/ | D49: 153 | E49: Catalog/research snapshot; nested candidate lists retained as JSON.
A50: Model Functions | B50: Analysis/*.py | D50: 114 | E50: Exact pinned implementation, including controllers, allocator, event handling, statistics and plotting. Source text is not executed by Sheets.
A51: Model Constants | B51: Analysis/*.py | D51: 98 | E51: Complete module-level declarations; expressions preserved as source text.
A52: Equation Register | B52: Analysis/*.py; Design Report/calculations.md | D52: 26 | E52: Readable equation map; full exact implementation retained in Model Functions and Model Constants.
A53: Calculation Notes | B53: Design and evidence documentation | C53: https://github.com/500ft/multirotor-recovery-dynamics/blob/fbc4c878a99f68650c70670e7ee3721a6a24e67d/Design%20and%20evidence%20documentation | D53: 433 | E53: Complete selected calculation/methodology documents. Original prose retained, including uncertainty and unresolved decisions.
A54: Figure Index | B54: Figures/ | C54: https://github.com/500ft/multirotor-recovery-dynamics/blob/fbc4c878a99f68650c70670e7ee3721a6a24e67d/Figures/ | D54: 11 | E54: Original figures linked alongside native workbook charts. No image values were digitized.
A55: Scenario Summary | B55: Data/scenario-diagnostic/scenario_diagnostic.json | C55: https://github.com/500ft/multirotor-recovery-dynamics/blob/fbc4c878a99f68650c70670e7ee3721a6a24e67d/Data/scenario-diagnostic/scenario_diagnostic.json | D55: 24 | E55: Derived descriptive means by exact cohort. No pooled success inference.
A56: Plot Data | B56: Derived from source tabs | D56: 223 | E56: Live linked source ranges for all comparison charts.
A57: Study Charts | B57: Plot Data | D57: 8 | E57: Eight native charts: two studies × four failure topologies.

Sheet Equation Register
A1: Calculation | B1: Equation or method | C1: Units | D1: Workbook location | E1: Implementation | F1: Limitations
A2: Mass freeze | B2: m_frozen = 5 ceil((sum(m_worst)+5)/5) | C2: g | D2: Sizing Calculations | E2: Analysis/budget.py | F2: 5 g allowance is selected, not measured
A3: Thrust requirement | B3: T_motor = (T/W) m / 4 | C3: gf with mass in g | D3: Sizing Calculations | E3: Analysis/gates.py | F3: Historical quadrotor sizing
A4: Flight time | B4: t_min = 60 C_Ah f_usable / I_A | C4: min | D4: Sizing Calculations | E4: Design Report/calculations.md | F4: Constant average current approximation
A5: Guard geometry | B5: D_inner=D_prop+2c; D_outer=D_inner+2t | C5: mm | D5: Sizing Calculations | E5: Design Report/calculations.md | F5: Clearance and wall are targets
A6: Angular arrest | B6: t = I |omega| / tau | C6: s | D6: Recovery Envelope Model | E6: Analysis/recovery.py | F6: Constant opposing torque
A7: Rest-to-rest rotation | B7: t = 2 sqrt(|theta| I / tau) | C7: s | D7: Recovery Envelope Model | E7: Analysis/recovery.py | F7: Bang-bang single-axis model
A8: Vertical envelope | B8: a_down = g - (T_up + 0.5 rho Cd A v_down^2)/m | C8: m/s² | D8: Recovery Envelope Model | E8: Analysis/recovery.py | F8: Downward-positive convention
A9: Rigid-body dynamics | B9: omega_dot = I^-1 (tau - omega cross (I omega)) | C9: rad/s² | D9: Model Functions | E9: Analysis/rigid_body.py | F9: Body angular rates, diagonal inertia
A10: Attitude kinematics | B10: q_dot = 0.5 q tensor (0,omega); normalize(q_next) | C10: 1/s | D10: Model Functions | E10: Analysis/rigid_body.py | F10: Quaternion w,x,y,z; body to world
A11: 6-DoF translation | B11: m v_dot = R(q)[0,0,T] + F_drag - [0,0,mg] | C11: N | D11: Model Functions | E11: Analysis/sim_release_recovery.py | F11: World z positive upward; see exact integrator
A12: Mixer differential | B12: d=max(0,min(T/4,T_max/4-T/4)) | C12: N | D12: Mixer Authority | E12: Analysis/sim_release_recovery.py | F12: Four healthy motors
... A27: Free fall | B27: d=0.5 g t^2; v=g t | C27: m, m/s | D27: Calculation Notes | E27: Design Report/calculations.md | F27: From rest, no drag

Sheet Sizing Calculations
A1: Quantity | B1: Value | C1: Unit | D1: Basis
A2: Best mass | B2: =SUM('Mass Budget'!C2:C12) -> 123.86 | C2: g | D2: Historical design budget
A3: Nominal mass | B3: =SUM('Mass Budget'!D2:D12) -> 135.66 | C3: g | D3: Historical design budget
A4: Worst mass | B4: =SUM('Mass Budget'!E2:E12) -> 156 | C4: g | D4: Historical design budget
A5: Unmodeled hardware | B5: 5 | C5: g | D5: Selected allowance; not itemized
A6: Proposed frozen maximum | B6: =CEILING(B4+B5,5) -> 165 | C6: g | D6: Analysis/budget.py
A7: Nominal margin | B7: =B6-B3 -> 29.34 | C7: g | D7: Frozen maximum minus nominal
A8: Abort threshold | B8: 225 | C8: g | D8: Selected design threshold; not a V995 limit
A9: Required thrust-to-weight | B9: 2 | C9: ratio | D9: REQ-PROP-001
A10: Number of motors | B10: 4 | C10: count | D10: Quadrotor
A11: Required per-motor thrust | B11: =B9*B6/B10 -> 82.5 | C11: gf | D11: At proposed frozen maximum
A12: Required total thrust | B12: =B9*B6/1000*9.81 -> 3.2373 | C12: N | D12: g=9.81 m/s²
A13: 5 V nominal sensor current | B13: =SUM('Power Budget'!C2:C5) -> 315 | C13: mA | D13: Listed 5 V loads only
A14: 5 V worst sensor current | B14: =SUM('Power Budget'!D2:D5) -> 620 | C14: mA | D14: Listed 5 V loads only
A15: 5 V nominal sensor power | B15: =5*B13/1000 -> 1.575 | C15: W | D15: Excludes motors and unlisted loads
A16: Battery capacity | B16: 0.55 | C16: Ah | D16: Historical 2S pack example
A17: Usable capacity fraction | B17: 0.8 | C17: fraction | D17: Sizing assumption
A18: Average flight current | B18: 9 | C18: A | D18: Illustrative assumption, not measured
A19: Estimated flight duration | B19: =60*B16*B17/B18 -> 2.9333333 | C19: min | D19: Capacity/current approximation
A20: Propeller diameter | B20: 50.8 | C20: mm | D20: Historical 2 inch example
A21: Radial clearance | B21: 2.5 | C21: mm | D21: Preliminary target
A22: Wall thickness | B22: 2 | C22: mm | D22: Preliminary target
A23: Guard inner diameter | B23: =B20+2*B21 -> 55.8 | C23: mm | D23: Geometry example
A24: Guard outer diameter | B24: =B23+2*B22 -> 59.8 | C24: mm | D24: Geometry example

Sheet Guard Calculations
A1: Case | B1: Impact energy J | C1: Stiffness N/m | D1: Stress per force Pa/N | E1: Clearance m | F1: Allowable stress Pa | G1: Deflection m | H1: Equivalent force N | I1: Impact stress Pa | J1: Clearance SF | K1: Stress SF | L1: Functional pass
A2: best | B2: 0.02 | C2: 1400 | D2: 150000 | E2: 0.003 | F2: 20000000 | G2: =SQRT(2*B2/C2) -> 0.0053452248 | H2: =SQRT(2*B2*C2) -> 7.4833148 | I2: =D2*H2 -> 1122497.2 | J2: =E2/G2 -> 0.56124861 | K2: =F2/I2 -> 17.817416 | L2: =AND(J2>=2,K2>=3) -> FALSE
A3: nominal | B3: 0.05 | C3: 900 | D3: 225000 | E3: 0.0025 | F3: 16000000 | G3: =SQRT(2*B3/C3) -> 0.010540926 | H3: =SQRT(2*B3*C3) -> 9.486833 | I3: =D3*H3 -> 2134537.4 | J3: =E3/G3 -> 0.23717082 | K3: =F3/I3 -> 7.4957693 | L3: =AND(J3>=2,K3>=3) -> FALSE
A4: worst | B4: 0.1 | C4: 500 | D4: 300000 | E4: 0.002 | F4: 12000000 | G4: =SQRT(2*B4/C4) -> 0.02 | H4: =SQRT(2*B4*C4) -> 10 | I4: =D4*H4 -> 3000000 | J4: =E4/G4 -> 0.1 | K4: =F4/I4 -> 4 | L4: =AND(J4>=2,K4>=3) -> FALSE

Sheet Mixer Authority
A1: Collective fraction | B1: Max total thrust N | C1: Arm m | D1: Collective thrust N | E1: Differential per motor N | F1: Roll-pitch authority Nm
A2: 0 | B2: 4.2 | C2: 0.06 | D2: =A2*B2 -> 0 | E2: =MAX(0,MIN(D2/4,B2/4-D2/4)) -> 0 | F2: =2*SQRT(2)*C2*E2 -> 0
A3: 0.01 | B3: 4.2 | C3: 0.06 | D3: =A3*B3 -> 0.042 | E3: =MAX(0,MIN(D3/4,B3/4-D3/4)) -> 0.0105 | F3: =2*SQRT(2)*C3*E3 -> 0.0017819091
A4: 0.02 | B4: 4.2 | C4: 0.06 | D4: =A4*B4 -> 0.084 | E4: =MAX(0,MIN(D4/4,B4/4-D4/4)) -> 0.021 | F4: =2*SQRT(2)*C4*E4 -> 0.0035638182
A5: 0.03 | B5: 4.2 | C5: 0.06 | D5: =A5*B5 -> 0.126 | E5: =MAX(0,MIN(D5/4,B5/4-D5/4)) -> 0.0315 | F5: =2*SQRT(2)*C5*E5 -> 0.0053457273
A6: 0.04 | B6: 4.2 | C6: 0.06 | D6: =A6*B6 -> 0.168 | E6: =MAX(0,MIN(D6/4,B6/4-D6/4)) -> 0.042 | F6: =2*SQRT(2)*C6*E6 -> 0.0071276364
A7: 0.05 | B7: 4.2 | C7: 0.06 | D7: =A7*B7 -> 0.21 | E7: =MAX(0,MIN(D7/4,B7/4-D7/4)) -> 0.0525 | F7: =2*SQRT(2)*C7*E7 -> 0.0089095454
A8: 0.06 | B8: 4.2 | C8: 0.06 | D8: =A8*B8 -> 0.252 | E8: =MAX(0,MIN(D8/4,B8/4-D8/4)) -> 0.063 | F8: =2*SQRT(2)*C8*E8 -> 0.010691455
A9: 0.07 | B9: 4.2 | C9: 0.06 | D9: =A9*B9 -> 0.294 | E9: =MAX(0,MIN(D9/4,B9/4-D9/4)) -> 0.0735 | F9: =2*SQRT(2)*C9*E9 -> 0.012473364
A10: 0.08 | B10: 4.2 | C10: 0.06 | D10: =A10*B10 -> 0.336 | E10: =MAX(0,MIN(D10/4,B10/4-D10/4)) -> 0.084 | F10: =2*SQRT(2)*C10*E10 -> 0.014255273
A11: 0.09 | B11: 4.2 | C11: 0.06 | D11: =A11*B11 -> 0.378 | E11: =MAX(0,MIN(D11/4,B11/4-D11/4)) -> 0.0945 | F11: =2*SQRT(2)*C11*E11 -> 0.016037182
A12: 0.1 | B12: 4.2 | C12: 0.06 | D12: =A12*B12 -> 0.42 | E12: =MAX(0,MIN(D12/4,B12/4-D12/4)) -> 0.105 | F12: =2*SQRT(2)*C12*E12 -> 0.017819091
A13: 0.11 | B13: 4.2 | C13: 0.06 | D13: =A13*B13 -> 0.462 | E13: =MAX(0,MIN(D13/4,B13/4-D13/4)) -> 0.1155 | F13: =2*SQRT(2)*C13*E13 -> 0.019601
... A102: 1 | B102: 4.2 | C102: 0.06 | D102: =A102*B102 -> 4.2 | E102: =MAX(0,MIN(D102/4,B102/4-D102/4)) -> 0 | F102: =2*SQRT(2)*C102*E102 -> 0

Sheet Statistics Calculations
A1: Calculation | B1: n | C1: Events or successes | D1: Confidence | E1: Result | F1: Interpretation
A2: Zero-event upper bound | B2: 300 | C2: 0 | D2: 0.95 | E2: =1-(1-D2)^(1/B2) -> 0.0099360819 | F2: Exact one-sided upper event-rate bound
A3: Zero-event upper bound | B3: 1000 | C3: 0 | D3: 0.95 | E3: =1-(1-D3)^(1/B3) -> 0.0029912495 | F3: Exact one-sided upper event-rate bound
A4: Required n at max rate 0.01 | C4: 0.01 | D4: 0.95 | E4: =CEILING(LN(1-D4)/LN(1-C4),1) -> 299 | F4: Zero observed events required
A5: Required n at max rate 0.003 | C5: 0.003 | D5: 0.95 | E5: =CEILING(LN(1-D5)/LN(1-C5),1) -> 998 | F5: Zero observed events required
A6: Success fraction | B6: 300 | C6: 0 | D6: 0.95 | E6: =C6/B6 -> 0 | F6: Example matching zero-success primary cells
A7: One-sided success lower | B7: 300 | C7: 0 | D7: 0.95 | E7: =IF(C7=0,0,_xlfn.BETA.INV(1-D7,C7,B7-C7+1)) -> 0 | F7: Clopper-Pearson; sampling uncertainty only
A8: One-sided success upper | B8: 300 | C8: 0 | D8: 0.95 | E8: =IF(C8=B8,1,_xlfn.BETA.INV(D8,C8+1,B8-C8)) -> 0.0099360819 | F8: Clopper-Pearson; each endpoint is one-sided 95%

Sheet Release Envelope
A1: tier | B1: max_recoverable_rate_rad_s | C1: max_recoverable_rate_deg_s | D1: envelope_edge | E1: max_torque_n_m | F1: max_thrust_n | G1: available_height_m
A2: best | B2: 34.5 | C2: 1976.7044 | D2: gyro_limit | E2: 0.006 | F2: 5 | G2: 3
A3: nominal | B3: 3.5 | C3: 200.53523 | D3: failure | E3: 0.004 | F3: 4.2 | G3: 3
A4: worst | B4: 1 | C4: 57.29578 | D4: failure | E4: 0.0025 | F4: 3.5 | G4: 3

Sheet Release Trace
A1: time_s | B1: tilt_rad | C1: body_rate_rad_s | D1: altitude_z_m | E1: vertical_velocity_m_s | F1: collective_thrust_N
A2: 0 | B2: 1.0471976 | C2: 2 | D2: 0 | E2: 0 | F2: 0
A3: 0.0005 | B3: 1.0479048 | C3: 2 | D3: -2.4525e-06 | E3: -0.004905 | F3: 0
A4: 0.001 | B4: 1.0486123 | C4: 2 | D4: -7.3574997e-06 | E4: -0.0098099993 | F4: 0
A5: 0.0015 | B5: 1.0493202 | C5: 2 | D5: -1.4714998e-05 | E5: -0.014714997 | F5: 0
A6: 0.002 | B6: 1.0500283 | C6: 2 | D6: -2.4524993e-05 | E6: -0.01961999 | F6: 0
A7: 0.0025 | B7: 1.0507367 | C7: 2 | D7: -3.6787483e-05 | E7: -0.02452498 | F7: 0
A8: 0.003 | B8: 1.0514454 | C8: 2 | D8: -5.1502464e-05 | E8: -0.029429963 | F8: 0
A9: 0.0035 | B9: 1.0521543 | C9: 2 | D9: -6.8669933e-05 | E9: -0.034334938 | F9: 0
A10: 0.004 | B10: 1.0528636 | C10: 2 | D10: -8.8289886e-05 | E10: -0.039239905 | F10: 0
A11: 0.0045 | B11: 1.0535731 | C11: 2 | D11: -0.00011036232 | E11: -0.044144861 | F11: 0
A12: 0.005 | B12: 1.0542829 | C12: 2 | D12: -0.00013488722 | E12: -0.049049806 | F12: 0
A13: 0.0055 | B13: 1.054993 | C13: 2 | D13: -0.00016186459 | E13: -0.053954738 | F13: 0
... A12001: 5.9995 | B12001: 0 | C12001: 1.6717092e-09 | D12001: -0.0015475137 | E12001: 0.0016352113 | F12001: 1.2727527

Sheet Monte Carlo
A1: scenario | B1: initial_rate_rad_s | C1: n | D1: successes | E1: success_rate | F1: success_rate_95_lower | G1: descent_p50_m | H1: descent_max_m
A2: as-toleranced_cg5mm | B2: 1 | C2: 75 | D2: 3 | E2: 0.04 | F2: 0.01098986 | G2: 0.56441365 | H2: 0.82285271
A3: as-toleranced_cg5mm | B3: 2 | C3: 150 | D3: 6 | E3: 0.04 | F3: 0.017560962 | G3: 1.1210407 | H3: 2.2155016
A4: as-toleranced_cg5mm | B4: 3 | C4: 75 | D4: 1 | E4: 0.013333333 | F4: 0.00068367678 | G4: 1.8372977 | H4: 1.8372977
A5: balance-controlled_cg1mm | B5: 1 | C5: 75 | D5: 45 | E5: 0.6 | F5: 0.49853621 | G5: 0.3544341 | H5: 1.0117193
A6: balance-controlled_cg1mm | B6: 2 | C6: 150 | D6: 115 | E6: 0.76666667 | F6: 0.702805 | G6: 0.8373164 | H6: 2.4058195
A7: balance-controlled_cg1mm | B7: 3 | C7: 75 | D7: 32 | E7: 0.42666667 | F7: 0.32962637 | G7: 2.2428553 | H7: 2.9710038
A8: as-toleranced_cg5mm_mixer-authority | B8: 1 | C8: 75 | D8: 75 | E8: 1 | F8: 0.96084411 | G8: 0.32101097 | H8: 0.54106116
A9: as-toleranced_cg5mm_mixer-authority | B9: 2 | C9: 150 | D9: 150 | E9: 1 | F9: 0.98022656 | G9: 0.38518251 | H9: 0.81609106
A10: as-toleranced_cg5mm_mixer-authority | B10: 3 | C10: 75 | D10: 75 | E10: 1 | F10: 0.96084411 | G10: 0.51810024 | H10: 1.0129521

Sheet Study A
A1: stage | B1: class | C1: cell | D1: action | E1: variant | F1: n | G1: successes | H1: p_safe | I1: p_safe_95_lower | J1: p_safe_95_upper | K1: sensitivity_successes.strict | L1: sensitivity_successes.lenient
A2: exploratory | B2: one_out | C2: h1.5_vz-1.5_w2_d0.11 | D2: mechanism | E2: a | F2: 30 | G2: 2 | H2: 0.066666667 | I2: 0.011975801 | J2: 0.19532604 | K2: 1 | L2: 2
A3: exploratory | B3: one_out | C3: h1.5_vz-1.5_w2_d0.11 | D3: parachute | E3: a | F3: 2000 | G3: 0 | H3: 0 | I3: 0 | J3: 0.0014967449 | K3: 0 | L3: 0
A4: exploratory | B4: one_out | C4: h1.5_vz-1.5_w2_d0.11 | D4: realloc_only | E4: a | F4: 30 | G4: 2 | H4: 0.066666667 | I4: 0.011975801 | J4: 0.19532604 | K4: 2 | L4: 5
A5: exploratory | B5: one_out | C5: h1.5_vz-1.5_w2_d0.3 | D5: mechanism | E5: a | F5: 300 | G5: 0 | H5: 0 | I5: 0 | J5: 0.0099360819 | K5: 0 | L5: 0
A6: exploratory | B6: one_out | C6: h1.5_vz-1.5_w2_d0.3 | D6: parachute | E6: a | F6: 2000 | G6: 0 | H6: 0 | I6: 0 | J6: 0.0014967449 | K6: 0 | L6: 0
A7: exploratory | B7: one_out | C7: h1.5_vz-1.5_w2_d0.3 | D7: realloc_only | E7: a | F7: 300 | G7: 0 | H7: 0 | I7: 0 | J7: 0.0099360819 | K7: 0 | L7: 0
A8: exploratory | B8: one_out | C8: h1.5_vz-1.5_w6_d0.11 | D8: mechanism | E8: a | F8: 30 | G8: 0 | H8: 0 | I8: 0 | J8: 0.095033853 | K8: 0 | L8: 0
A9: exploratory | B9: one_out | C9: h1.5_vz-1.5_w6_d0.11 | D9: parachute | E9: a | F9: 2000 | G9: 0 | H9: 0 | I9: 0 | J9: 0.0014967449 | K9: 0 | L9: 0
A10: exploratory | B10: one_out | C10: h1.5_vz-1.5_w6_d0.11 | D10: realloc_only | E10: a | F10: 30 | G10: 0 | H10: 0 | I10: 0 | J10: 0.095033853 | K10: 0 | L10: 0
A11: exploratory | B11: one_out | C11: h1.5_vz-1.5_w6_d0.3 | D11: mechanism | E11: a | F11: 30 | G11: 0 | H11: 0 | I11: 0 | J11: 0.095033853 | K11: 0 | L11: 0
A12: exploratory | B12: one_out | C12: h1.5_vz-1.5_w6_d0.3 | D12: parachute | E12: a | F12: 2000 | G12: 0 | H12: 0 | I12: 0 | J12: 0.0014967449 | K12: 0 | L12: 0
A13: exploratory | B13: one_out | C13: h1.5_vz-1.5_w6_d0.3 | D13: realloc_only | E13: a | F13: 30 | G13: 0 | H13: 0 | I13: 0 | J13: 0.095033853 | K13: 0 | L13: 0
... A297: primary | B297: two_adjacent | C297: h3_vz0_w6_d0.11 | D297: realloc_only | E297: a | F297: 300 | G297: 0 | H297: 0 | I297: 0 | J297: 0.0099360819 | K297: 0 | L297: 0

Sheet Study A2
A1: stage | B1: class | C1: cell | D1: action | E1: variant | F1: n | G1: successes | H1: p_safe | I1: p_safe_95_lower | J1: p_safe_95_upper | K1: sensitivity_successes.strict | L1: sensitivity_successes.lenient
A2: exploratory | B2: one_out | C2: h1.5_vz-1.5_w2_d0.11 | D2: mechanism | E2: a2 | F2: 30 | G2: 2 | H2: 0.066666667 | I2: 0.011975801 | J2: 0.19532604 | K2: 1 | L2: 2
A3: exploratory | B3: one_out | C3: h1.5_vz-1.5_w2_d0.11 | D3: parachute | E3: a2 | F3: 2000 | G3: 0 | H3: 0 | I3: 0 | J3: 0.0014967449 | K3: 0 | L3: 0
A4: exploratory | B4: one_out | C4: h1.5_vz-1.5_w2_d0.11 | D4: realloc_only | E4: a2 | F4: 30 | G4: 2 | H4: 0.066666667 | I4: 0.011975801 | J4: 0.19532604 | K4: 2 | L4: 5
A5: exploratory | B5: one_out | C5: h1.5_vz-1.5_w2_d0.3 | D5: mechanism | E5: a2 | F5: 300 | G5: 0 | H5: 0 | I5: 0 | J5: 0.0099360819 | K5: 0 | L5: 0
A6: exploratory | B6: one_out | C6: h1.5_vz-1.5_w2_d0.3 | D6: parachute | E6: a2 | F6: 2000 | G6: 0 | H6: 0 | I6: 0 | J6: 0.0014967449 | K6: 0 | L6: 0
A7: exploratory | B7: one_out | C7: h1.5_vz-1.5_w2_d0.3 | D7: realloc_only | E7: a2 | F7: 300 | G7: 0 | H7: 0 | I7: 0 | J7: 0.0099360819 | K7: 0 | L7: 0
A8: exploratory | B8: one_out | C8: h1.5_vz-1.5_w6_d0.11 | D8: mechanism | E8: a2 | F8: 30 | G8: 0 | H8: 0 | I8: 0 | J8: 0.095033853 | K8: 0 | L8: 0
A9: exploratory | B9: one_out | C9: h1.5_vz-1.5_w6_d0.11 | D9: parachute | E9: a2 | F9: 2000 | G9: 0 | H9: 0 | I9: 0 | J9: 0.0014967449 | K9: 0 | L9: 0
A10: exploratory | B10: one_out | C10: h1.5_vz-1.5_w6_d0.11 | D10: realloc_only | E10: a2 | F10: 30 | G10: 0 | H10: 0 | I10: 0 | J10: 0.095033853 | K10: 0 | L10: 0
A11: exploratory | B11: one_out | C11: h1.5_vz-1.5_w6_d0.3 | D11: mechanism | E11: a2 | F11: 30 | G11: 0 | H11: 0 | I11: 0 | J11: 0.095033853 | K11: 0 | L11: 0
A12: exploratory | B12: one_out | C12: h1.5_vz-1.5_w6_d0.3 | D12: parachute | E12: a2 | F12: 2000 | G12: 0 | H12: 0 | I12: 0 | J12: 0.0014967449 | K12: 0 | L12: 0
A13: exploratory | B13: one_out | C13: h1.5_vz-1.5_w6_d0.3 | D13: realloc_only | E13: a2 | F13: 30 | G13: 0 | H13: 0 | I13: 0 | J13: 0.095033853 | K13: 0 | L13: 0
... A297: primary | B297: two_adjacent | C297: h3_vz0_w6_d0.11 | D297: realloc_only | E297: a2 | F297: 300 | G297: 0 | H297: 0 | I297: 0 | J297: 0.0099360819 | K297: 0 | L297: 0

Sheet Scenario Trials
A1: status | B1: safe | C1: impact_speed_m_s | D1: impact_tilt_rad | E1: t_contact_s | F1: t_switch_s | G1: max_descent_m | H1: class | I1: cell | J1: package | K1: arm | L1: pair
A2: contact | B2: FALSE | C2: 7.3989937 | D2: 1.0658969 | E2: 0.7795 | F2: 0.162 | G2: 2.9997407 | H2: one_out | I2: h3_vz0_w6_d0.11 | J2: mechanism | K2: release_startup | L2: 0
A3: contact | B3: FALSE | C3: 7.5884774 | D3: 0.74591488 | E3: 0.792 | F3: 0.162 | G3: 2.9993612 | H3: one_out | I3: h3_vz0_w6_d0.11 | J3: mechanism | K3: in_flight_hold_matched | L3: 0
A4: contact | B4: FALSE | C4: 7.8708608 | D4: 1.7693926 | E4: 0.8155 | F4: 0.11 | G4: 2.9985799 | H4: one_out | I4: h3_vz0_w6_d0.11 | J4: mechanism | K4: in_flight_hold_immediate | L4: 0
A5: contact | B5: FALSE | C5: 8.0215939 | D5: 2.5404958 | E5: 0.7795 | F5: 0.1665 | G5: 2.9980874 | H5: one_out | I5: h3_vz0_w6_d0.11 | J5: mechanism | K5: release_startup | L5: 1
A6: contact | B6: FALSE | C6: 6.1030075 | D6: 2.3949693 | E6: 0.8665 | F6: 0.1665 | G6: 2.9977588 | H6: one_out | I6: h3_vz0_w6_d0.11 | J6: mechanism | K6: in_flight_hold_matched | L6: 1
A7: contact | B7: FALSE | C7: 4.9194318 | D7: 0.63416922 | E7: 0.85 | F7: 0.11 | G7: 2.9983909 | H7: one_out | I7: h3_vz0_w6_d0.11 | J7: mechanism | K7: in_flight_hold_immediate | L7: 1
A8: contact | B8: FALSE | C8: 6.839334 | D8: 0.53276808 | E8: 0.7645 | F8: 0.1655 | G8: 2.9995193 | H8: one_out | I8: h3_vz0_w6_d0.11 | J8: mechanism | K8: release_startup | L8: 2
A9: contact | B9: FALSE | C9: 6.8633035 | D9: 0.23304644 | E9: 0.787 | F9: 0.1655 | G9: 2.9986026 | H9: one_out | I9: h3_vz0_w6_d0.11 | J9: mechanism | K9: in_flight_hold_matched | L9: 2
A10: contact | B10: FALSE | C10: 7.6740837 | D10: 1.2996089 | E10: 0.7975 | F10: 0.11 | G10: 2.9976761 | H10: one_out | I10: h3_vz0_w6_d0.11 | J10: mechanism | K10: in_flight_hold_immediate | L10: 2
A11: contact | B11: FALSE | C11: 7.9782295 | D11: 2.750325 | E11: 0.779 | F11: 0.192 | G11: 2.9991177 | H11: one_out | I11: h3_vz0_w6_d0.11 | J11: mechanism | K11: release_startup | L11: 3
A12: contact | B12: FALSE | C12: 4.5542475 | D12: 1.1173716 | E12: 0.8875 | F12: 0.192 | G12: 2.9986853 | H12: one_out | I12: h3_vz0_w6_d0.11 | J12: mechanism | K12: in_flight_hold_matched | L12: 3
A13: contact | B13: FALSE | C13: 7.3635372 | D13: 1.1262083 | E13: 0.816 | F13: 0.11 | G13: 2.9994363 | H13: one_out | I13: h3_vz0_w6_d0.11 | J13: mechanism | K13: in_flight_hold_immediate | L13: 3
... A289: contact | B289: FALSE | C289: 5.1848215 | D289: 2.5595009 | E289: 0.457 | F289: 0.3 | G289: 1.4977236 | H289: two_adjacent | I289: h1.5_vz-1.5_w2_d0.3 | J289: realloc_only | K289: in_flight_hold_immediate | L289: 11

Sheet Scenario Summary
A1: failure_class | B1: cell | C1: package | D1: arm | E1: n | F1: safe_count | G1: mean_impact_speed_m_s | H1: mean_contact_time_s
A2: one_out | B2: h1.5_vz-1.5_w2_d0.3 | C2: mechanism | D2: in_flight_hold_immediate | E2: =COUNTIFS('Scenario Trials'!$H$2:$H$289,$A2,'Scenario Trials'!$I$2:$I$289,$B2,'Scenario Trials'!$J$2:$J$289,$C2,'Scenario Trials'!$K$2:$K$289,$D2) -> 12 | F2: =COUNTIFS('Scenario Trials'!$H$2:$H$289,$A2,'Scenario Trials'!$I$2:$I$289,$B2,'Scenario Trials'!$J$2:$J$289,$C2,'Scenario Trials'!$K$2:$K$289,$D2,'Scenario Trials'!$B$2:$B$289,TRUE) -> 0 | G2: =AVERAGEIFS('Scenario Trials'!$C$2:$C$289,'Scenario Trials'!$H$2:$H$289,$A2,'Scenario Trials'!$I$2:$I$289,$B2,'Scenario Trials'!$J$2:$J$289,$C2,'Scenario Trials'!$K$2:$K$289,$D2) -> 5.4080845 | H2: =AVERAGEIFS('Scenario Trials'!$E$2:$E$289,'Scenario Trials'!$H$2:$H$289,$A2,'Scenario Trials'!$I$2:$I$289,$B2,'Scenario Trials'!$J$2:$J$289,$C2,'Scenario Trials'!$K$2:$K$289,$D2) -> 0.46416667
A3: one_out | B3: h1.5_vz-1.5_w2_d0.3 | C3: mechanism | D3: in_flight_hold_matched | E3: =COUNTIFS('Scenario Trials'!$H$2:$H$289,$A3,'Scenario Trials'!$I$2:$I$289,$B3,'Scenario Trials'!$J$2:$J$289,$C3,'Scenario Trials'!$K$2:$K$289,$D3) -> 12 | F3: =COUNTIFS('Scenario Trials'!$H$2:$H$289,$A3,'Scenario Trials'!$I$2:$I$289,$B3,'Scenario Trials'!$J$2:$J$289,$C3,'Scenario Trials'!$K$2:$K$289,$D3,'Scenario Trials'!$B$2:$B$289,TRUE) -> 0 | G3: =AVERAGEIFS('Scenario Trials'!$C$2:$C$289,'Scenario Trials'!$H$2:$H$289,$A3,'Scenario Trials'!$I$2:$I$289,$B3,'Scenario Trials'!$J$2:$J$289,$C3,'Scenario Trials'!$K$2:$K$289,$D3) -> 4.9681307 | H3: =AVERAGEIFS('Scenario Trials'!$E$2:$E$289,'Scenario Trials'!$H$2:$H$289,$A3,'Scenario Trials'!$I$2:$I$289,$B3,'Scenario Trials'!$J$2:$J$289,$C3,'Scenario Trials'!$K$2:$K$289,$D3) -> 0.473125
A4: one_out | B4: h1.5_vz-1.5_w2_d0.3 | C4: mechanism | D4: release_startup | E4: =COUNTIFS('Scenario Trials'!$H$2:$H$289,$A4,'Scenario Trials'!$I$2:$I$289,$B4,'Scenario Trials'!$J$2:$J$289,$C4,'Scenario Trials'!$K$2:$K$289,$D4) -> 12 | F4: =COUNTIFS('Scenario Trials'!$H$2:$H$289,$A4,'Scenario Trials'!$I$2:$I$289,$B4,'Scenario Trials'!$J$2:$J$289,$C4,'Scenario Trials'!$K$2:$K$289,$D4,'Scenario Trials'!$B$2:$B$289,TRUE) -> 0 | G4: =AVERAGEIFS('Scenario Trials'!$C$2:$C$289,'Scenario Trials'!$H$2:$H$289,$A4,'Scenario Trials'!$I$2:$I$289,$B4,'Scenario Trials'!$J$2:$J$289,$C4,'Scenario Trials'!$K$2:$K$289,$D4) -> 4.9162082 | H4: =AVERAGEIFS('Scenario Trials'!$E$2:$E$289,'Scenario Trials'!$H$2:$H$289,$A4,'Scenario Trials'!$I$2:$I$289,$B4,'Scenario Trials'!$J$2:$J$289,$C4,'Scenario Trials'!$K$2:$K$289,$D4) -> 0.43175
A5: one_out | B5: h1.5_vz-1.5_w2_d0.3 | C5: realloc_only | D5: in_flight_hold_immediate | E5: =COUNTIFS('Scenario Trials'!$H$2:$H$289,$A5,'Scenario Trials'!$I$2:$I$289,$B5,'Scenario Trials'!$J$2:$J$289,$C5,'Scenario Trials'!$K$2:$K$289,$D5) -> 12 | F5: =COUNTIFS('Scenario Trials'!$H$2:$H$289,$A5,'Scenario Trials'!$I$2:$I$289,$B5,'Scenario Trials'!$J$2:$J$289,$C5,'Scenario Trials'!$K$2:$K$289,$D5,'Scenario Trials'!$B$2:$B$289,TRUE) -> 0 | G5: =AVERAGEIFS('Scenario Trials'!$C$2:$C$289,'Scenario Trials'!$H$2:$H$289,$A5,'Scenario Trials'!$I$2:$I$289,$B5,'Scenario Trials'!$J$2:$J$289,$C5,'Scenario Trials'!$K$2:$K$289,$D5) -> 4.7608316 | H5: =AVERAGEIFS('Scenario Trials'!$E$2:$E$289,'Scenario Trials'!$H$2:$H$289,$A5,'Scenario Trials'!$I$2:$I$289,$B5,'Scenario Trials'!$J$2:$J$289,$C5,'Scenario Trials'!$K$2:$K$289,$D5) -> 0.47183333
A6: one_out | B6: h1.5_vz-1.5_w2_d0.3 | C6: realloc_only | D6: in_flight_hold_matched | E6: =COUNTIFS('Scenario Trials'!$H$2:$H$289,$A6,'Scenario Trials'!$I$2:$I$289,$B6,'Scenario Trials'!$J$2:$J$289,$C6,'Scenario Trials'!$K$2:$K$289,$D6) -> 12 | F6: =COUNTIFS('Scenario Trials'!$H$2:$H$289,$A6,'Scenario Trials'!$I$2:$I$289,$B6,'Scenario Trials'!$J$2:$J$289,$C6,'Scenario Trials'!$K$2:$K$289,$D6,'Scenario Trials'!$B$2:$B$289,TRUE) -> 0 | G6: =AVERAGEIFS('Scenario Trials'!$C$2:$C$289,'Scenario Trials'!$H$2:$H$289,$A6,'Scenario Trials'!$I$2:$I$289,$B6,'Scenario Trials'!$J$2:$J$289,$C6,'Scenario Trials'!$K$2:$K$289,$D6) -> 4.8807339 | H6: =AVERAGEIFS('Scenario Trials'!$E$2:$E$289,'Scenario Trials'!$H$2:$H$289,$A6,'Scenario Trials'!$I$2:$I$289,$B6,'Scenario Trials'!$J$2:$J$289,$C6,'Scenario Trials'!$K$2:$K$289,$D6) -> 0.47383333
A7: one_out | B7: h1.5_vz-1.5_w2_d0.3 | C7: realloc_only | D7: release_startup | E7: =COUNTIFS('Scenario Trials'!$H$2:$H$289,$A7,'Scenario Trials'!$I$2:$I$289,$B7,'Scenario Trials'!$J$2:$J$289,$C7,'Scenario Trials'!$K$2:$K$289,$D7) -> 12 | F7: =COUNTIFS('Scenario Trials'!$H$2:$H$289,$A7,'Scenario Trials'!$I$2:$I$289,$B7,'Scenario Trials'!$J$2:$J$289,$C7,'Scenario Trials'!$K$2:$K$289,$D7,'Scenario Trials'!$B$2:$B$289,TRUE) -> 0 | G7: =AVERAGEIFS('Scenario Trials'!$C$2:$C$289,'Scenario Trials'!$H$2:$H$289,$A7,'Scenario Trials'!$I$2:$I$289,$B7,'Scenario Trials'!$J$2:$J$289,$C7,'Scenario Trials'!$K$2:$K$289,$D7) -> 4.8251283 | H7: =AVERAGEIFS('Scenario Trials'!$E$2:$E$289,'Scenario Trials'!$H$2:$H$289,$A7,'Scenario Trials'!$I$2:$I$289,$B7,'Scenario Trials'!$J$2:$J$289,$C7,'Scenario Trials'!$K$2:$K$289,$D7) -> 0.433375
A8: one_out | B8: h3_vz0_w6_d0.11 | C8: mechanism | D8: in_flight_hold_immediate | E8: =COUNTIFS('Scenario Trials'!$H$2:$H$289,$A8,'Scenario Trials'!$I$2:$I$289,$B8,'Scenario Trials'!$J$2:$J$289,$C8,'Scenario Trials'!$K$2:$K$289,$D8) -> 12 | F8: =COUNTIFS('Scenario Trials'!$H$2:$H$289,$A8,'Scenario Trials'!$I$2:$I$289,$B8,'Scenario Trials'!$J$2:$J$289,$C8,'Scenario Trials'!$K$2:$K$289,$D8,'Scenario Trials'!$B$2:$B$289,TRUE) -> 0 | G8: =AVERAGEIFS('Scenario Trials'!$C$2:$C$289,'Scenario Trials'!$H$2:$H$289,$A8,'Scenario Trials'!$I$2:$I$289,$B8,'Scenario Trials'!$J$2:$J$289,$C8,'Scenario Trials'!$K$2:$K$289,$D8) -> 7.0259008 | H8: =AVERAGEIFS('Scenario Trials'!$E$2:$E$289,'Scenario Trials'!$H$2:$H$289,$A8,'Scenario Trials'!$I$2:$I$289,$B8,'Scenario Trials'!$J$2:$J$289,$C8,'Scenario Trials'!$K$2:$K$289,$D8) -> 0.81345833
A9: one_out | B9: h3_vz0_w6_d0.11 | C9: mechanism | D9: in_flight_hold_matched | E9: =COUNTIFS('Scenario Trials'!$H$2:$H$289,$A9,'Scenario Trials'!$I$2:$I$289,$B9,'Scenario Trials'!$J$2:$J$289,$C9,'Scenario Trials'!$K$2:$K$289,$D9) -> 12 | F9: =COUNTIFS('Scenario Trials'!$H$2:$H$289,$A9,'Scenario Trials'!$I$2:$I$289,$B9,'Scenario Trials'!$J$2:$J$289,$C9,'Scenario Trials'!$K$2:$K$289,$D9,'Scenario Trials'!$B$2:$B$289,TRUE) -> 0 | G9: =AVERAGEIFS('Scenario Trials'!$C$2:$C$289,'Scenario Trials'!$H$2:$H$289,$A9,'Scenario Trials'!$I$2:$I$289,$B9,'Scenario Trials'!$J$2:$J$289,$C9,'Scenario Trials'!$K$2:$K$289,$D9) -> 6.8009062 | H9: =AVERAGEIFS('Scenario Trials'!$E$2:$E$289,'Scenario Trials'!$H$2:$H$289,$A9,'Scenario Trials'!$I$2:$I$289,$B9,'Scenario Trials'!$J$2:$J$289,$C9,'Scenario Trials'!$K$2:$K$289,$D9) -> 0.81716667
A10: one_out | B10: h3_vz0_w6_d0.11 | C10: mechanism | D10: release_startup | E10: =COUNTIFS('Scenario Trials'!$H$2:$H$289,$A10,'Scenario Trials'!$I$2:$I$289,$B10,'Scenario Trials'!$J$2:$J$289,$C10,'Scenario Trials'!$K$2:$K$289,$D10) -> 12 | F10: =COUNTIFS('Scenario Trials'!$H$2:$H$289,$A10,'Scenario Trials'!$I$2:$I$289,$B10,'Scenario Trials'!$J$2:$J$289,$C10,'Scenario Trials'!$K$2:$K$289,$D10,'Scenario Trials'!$B$2:$B$289,TRUE) -> 0 | G10: =AVERAGEIFS('Scenario Trials'!$C$2:$C$289,'Scenario Trials'!$H$2:$H$289,$A10,'Scenario Trials'!$I$2:$I$289,$B10,'Scenario Trials'!$J$2:$J$289,$C10,'Scenario Trials'!$K$2:$K$289,$D10) -> 7.345775 | H10: =AVERAGEIFS('Scenario Trials'!$E$2:$E$289,'Scenario Trials'!$H$2:$H$289,$A10,'Scenario Trials'!$I$2:$I$289,$B10,'Scenario Trials'!$J$2:$J$289,$C10,'Scenario Trials'!$K$2:$K$289,$D10) -> 0.7645
A11: one_out | B11: h3_vz0_w6_d0.11 | C11: realloc_only | D11: in_flight_hold_immediate | E11: =COUNTIFS('Scenario Trials'!$H$2:$H$289,$A11,'Scenario Trials'!$I$2:$I$289,$B11,'Scenario Trials'!$J$2:$J$289,$C11,'Scenario Trials'!$K$2:$K$289,$D11) -> 12 | F11: =COUNTIFS('Scenario Trials'!$H$2:$H$289,$A11,'Scenario Trials'!$I$2:$I$289,$B11,'Scenario Trials'!$J$2:$J$289,$C11,'Scenario Trials'!$K$2:$K$289,$D11,'Scenario Trials'!$B$2:$B$289,TRUE) -> 0 | G11: =AVERAGEIFS('Scenario Trials'!$C$2:$C$289,'Scenario Trials'!$H$2:$H$289,$A11,'Scenario Trials'!$I$2:$I$289,$B11,'Scenario Trials'!$J$2:$J$289,$C11,'Scenario Trials'!$K$2:$K$289,$D11) -> 6.1661669 | H11: =AVERAGEIFS('Scenario Trials'!$E$2:$E$289,'Scenario Trials'!$H$2:$H$289,$A11,'Scenario Trials'!$I$2:$I$289,$B11,'Scenario Trials'!$J$2:$J$289,$C11,'Scenario Trials'!$K$2:$K$289,$D11) -> 0.90283333
A12: one_out | B12: h3_vz0_w6_d0.11 | C12: realloc_only | D12: in_flight_hold_matched | E12: =COUNTIFS('Scenario Trials'!$H$2:$H$289,$A12,'Scenario Trials'!$I$2:$I$289,$B12,'Scenario Trials'!$J$2:$J$289,$C12,'Scenario Trials'!$K$2:$K$289,$D12) -> 12 | F12: =COUNTIFS('Scenario Trials'!$H$2:$H$289,$A12,'Scenario Trials'!$I$2:$I$289,$B12,'Scenario Trials'!$J$2:$J$289,$C12,'Scenario Trials'!$K$2:$K$289,$D12,'Scenario Trials'!$B$2:$B$289,TRUE) -> 0 | G12: =AVERAGEIFS('Scenario Trials'!$C$2:$C$289,'Scenario Trials'!$H$2:$H$289,$A12,'Scenario Trials'!$I$2:$I$289,$B12,'Scenario Trials'!$J$2:$J$289,$C12,'Scenario Trials'!$K$2:$K$289,$D12) -> 6.5653095 | H12: =AVERAGEIFS('Scenario Trials'!$E$2:$E$289,'Scenario Trials'!$H$2:$H$289,$A12,'Scenario Trials'!$I$2:$I$289,$B12,'Scenario Trials'!$J$2:$J$289,$C12,'Scenario Trials'!$K$2:$K$289,$D12) -> 0.84483333
A13: one_out | B13: h3_vz0_w6_d0.11 | C13: realloc_only | D13: release_startup | E13: =COUNTIFS('Scenario Trials'!$H$2:$H$289,$A13,'Scenario Trials'!$I$2:$I$289,$B13,'Scenario Trials'!$J$2:$J$289,$C13,'Scenario Trials'!$K$2:$K$289,$D13) -> 12 | F13: =COUNTIFS('Scenario Trials'!$H$2:$H$289,$A13,'Scenario Trials'!$I$2:$I$289,$B13,'Scenario Trials'!$J$2:$J$289,$C13,'Scenario Trials'!$K$2:$K$289,$D13,'Scenario Trials'!$B$2:$B$289,TRUE) -> 0 | G13: =AVERAGEIFS('Scenario Trials'!$C$2:$C$289,'Scenario Trials'!$H$2:$H$289,$A13,'Scenario Trials'!$I$2:$I$289,$B13,'Scenario Trials'!$J$2:$J$289,$C13,'Scenario Trials'!$K$2:$K$289,$D13) -> 6.6142245 | H13: =AVERAGEIFS('Scenario Trials'!$E$2:$E$289,'Scenario Trials'!$H$2:$H$289,$A13,'Scenario Trials'!$I$2:$I$289,$B13,'Scenario Trials'!$J$2:$J$289,$C13,'Scenario Trials'!$K$2:$K$289,$D13) -> 0.81283333
... A25: two_adjacent | B25: h3_vz0_w6_d0.11 | C25: realloc_only | D25: release_startup | E25: =COUNTIFS('Scenario Trials'!$H$2:$H$289,$A25,'Scenario Trials'!$I$2:$I$289,$B25,'Scenario Trials'!$J$2:$J$289,$C25,'Scenario Trials'!$K$2:$K$289,$D25) -> 12 | F25: =COUNTIFS('Scenario Trials'!$H$2:$H$289,$A25,'Scenario Trials'!$I$2:$I$289,$B25,'Scenario Trials'!$J$2:$J$289,$C25,'Scenario Trials'!$K$2:$K$289,$D25,'Scenario Trials'!$B$2:$B$289,TRUE) -> 0 | G25: =AVERAGEIFS('Scenario Trials'!$C$2:$C$289,'Scenario Trials'!$H$2:$H$289,$A25,'Scenario Trials'!$I$2:$I$289,$B25,'Scenario Trials'!$J$2:$J$289,$C25,'Scenario Trials'!$K$2:$K$289,$D25) -> 6.5871316 | H25: =AVERAGEIFS('Scenario Trials'!$E$2:$E$289,'Scenario Trials'!$H$2:$H$289,$A25,'Scenario Trials'!$I$2:$I$289,$B25,'Scenario Trials'!$J$2:$J$289,$C25,'Scenario Trials'!$K$2:$K$289,$D25) -> 0.81825

Sheet Scenario Contrasts
A1: contrast | B1: class | C1: package | D1: n | E1: only_a | F1: only_b | G1: both | H1: neither | I1: delta | J1: midp
A2: H-L | B2: one_out | C2: mechanism | D2: 24 | E2: 0 | F2: 0 | G2: 0 | H2: 24 | I2: 0 | J2: 1
A3: H-L | B3: one_out | C3: realloc_only | D3: 24 | E3: 0 | F3: 0 | G3: 0 | H3: 24 | I3: 0 | J3: 1
A4: H-L | B4: two_adjacent | C4: mechanism | D4: 24 | E4: 0 | F4: 0 | G4: 0 | H4: 24 | I4: 0 | J4: 1
A5: H-L | B5: two_adjacent | C5: realloc_only | D5: 24 | E5: 0 | F5: 0 | G5: 0 | H5: 24 | I5: 0 | J5: 1
A6: I-H | B6: one_out | C6: mechanism | D6: 24 | E6: 0 | F6: 0 | G6: 0 | H6: 24 | I6: 0 | J6: 1
A7: I-H | B7: one_out | C7: realloc_only | D7: 24 | E7: 0 | F7: 0 | G7: 0 | H7: 24 | I7: 0 | J7: 1
A8: I-H | B8: two_adjacent | C8: mechanism | D8: 24 | E8: 0 | F8: 0 | G8: 0 | H8: 24 | I8: 0 | J8: 1
A9: I-H | B9: two_adjacent | C9: realloc_only | D9: 24 | E9: 0 | F9: 0 | G9: 0 | H9: 24 | I9: 0 | J9: 1
A10: I-L | B10: one_out | C10: mechanism | D10: 24 | E10: 0 | F10: 0 | G10: 0 | H10: 24 | I10: 0 | J10: 1
A11: I-L | B11: one_out | C11: realloc_only | D11: 24 | E11: 0 | F11: 0 | G11: 0 | H11: 24 | I11: 0 | J11: 1
A12: I-L | B12: two_adjacent | C12: mechanism | D12: 24 | E12: 0 | F12: 0 | G12: 0 | H12: 24 | I12: 0 | J12: 1
A13: I-L | B13: two_adjacent | C13: realloc_only | D13: 24 | E13: 0 | F13: 0 | G13: 0 | H13: 24 | I13: 0 | J13: 1

Sheet Continuous Contrasts
A1: contrast | B1: class | C1: cell | D1: n | E1: mean_d_impact_speed_m_s | F1: min_d_impact_speed_m_s | G1: max_d_impact_speed_m_s | H1: mean_d_time_to_contact_s
A2: H-L | B2: one_out | C2: h1.5_vz-1.5_w2_d0.3 | D2: 24 | E2: 0.053764071 | F2: -0.50322085 | G2: 1.0280412 | H2: 0.040916667
A3: H-L | B3: one_out | C3: h3_vz0_w6_d0.11 | D3: 24 | E3: -0.29689195 | F3: -3.423982 | G3: 0.7952798 | H3: 0.042333333
A4: H-L | B4: two_adjacent | C4: h1.5_vz-1.5_w2_d0.3 | D4: 24 | E4: 0.11515798 | F4: 0.010331756 | G4: 0.24143768 | H4: 0.0285625
A5: H-L | B5: two_adjacent | C5: h3_vz0_w6_d0.11 | D5: 24 | E5: -0.17358605 | F5: -0.43004072 | G5: 0.14193006 | H5: 0.065166667
A6: I-H | B6: one_out | C6: h1.5_vz-1.5_w2_d0.3 | D6: 24 | E6: 0.16002573 | F6: -0.63734265 | G6: 0.7495851 | H6: -0.0054791667
A7: I-H | B7: one_out | C7: h3_vz0_w6_d0.11 | D7: 24 | E7: -0.087073995 | F7: -3.2903984 | G7: 2.8092897 | H7: 0.027145833
A8: I-H | B8: two_adjacent | C8: h1.5_vz-1.5_w2_d0.3 | D8: 24 | E8: -0.025966148 | F8: -0.19318146 | G8: 0.096328962 | H8: 0.000625
A9: I-H | B9: two_adjacent | C9: h3_vz0_w6_d0.11 | D9: 24 | E9: -0.0094449705 | F9: -0.15050655 | G9: 0.12054117 | H9: 0.0048125
A10: I-L | B10: one_out | C10: h1.5_vz-1.5_w2_d0.3 | D10: 24 | E10: 0.2137898 | F10: -0.52874947 | G10: 1.1876589 | H10: 0.0354375
A11: I-L | B11: one_out | C11: h3_vz0_w6_d0.11 | D11: 24 | E11: -0.38396594 | F11: -3.6925433 | G11: 1.2630865 | H11: 0.069479167
A12: I-L | B12: two_adjacent | C12: h1.5_vz-1.5_w2_d0.3 | D12: 24 | E12: 0.089191834 | F12: -0.14580902 | G12: 0.25753059 | H12: 0.0291875
A13: I-L | B13: two_adjacent | C13: h3_vz0_w6_d0.11 | D13: 24 | E13: -0.18303103 | F13: -0.39185548 | G13: 0.025087771 | H13: 0.069979167

Sheet Convergence
A1: class | B1: cell | C1: trial | D1: impact_speed_dt5e-4 | E1: impact_speed_dt2.5e-4 | F1: impact_tilt_rad_dt5e-4 | G1: impact_tilt_rad_dt2.5e-4 | H1: speed_delta | I1: landed_agrees
A2: one_out | B2: h3_vz0_w6_d0.11 | C2: 0 | D2: 7.3686958 | E2: 7.364343 | F2: 1.081137 | G2: 1.0777597 | H2: 0.0043528248 | I2: TRUE
A3: one_out | B3: h3_vz0_w6_d0.11 | C3: 1 | D3: 7.681894 | E3: 7.6850454 | F3: 1.3265024 | G3: 1.3220976 | H3: 0.0031513778 | I3: TRUE
A4: one_out | B4: h3_vz0_w6_d0.11 | C4: 2 | D4: 7.7638328 | E4: 7.76673 | F4: 1.4884582 | G4: 1.4940764 | H4: 0.0028971841 | I4: TRUE
A5: one_out | B5: h1.5_vz-1.5_w2_d0.3 | C5: 0 | D5: 5.1673964 | E5: 5.1669857 | F5: 1.2480047 | G5: 1.2483568 | H5: 0.00041071535 | I5: TRUE
A6: one_out | B6: h1.5_vz-1.5_w2_d0.3 | C6: 1 | D6: 4.8018392 | E6: 4.8021455 | F6: 1.0596707 | G6: 1.0601796 | H6: 0.00030627303 | I6: TRUE
A7: one_out | B7: h1.5_vz-1.5_w2_d0.3 | C7: 2 | D7: 4.8736807 | E7: 4.8743827 | F7: 1.154657 | G7: 1.155028 | H7: 0.00070191448 | I7: TRUE
A8: partial_authority | B8: h3_vz0_w6_d0.11 | C8: 0 | D8: 0.98970585 | E8: 0.98972598 | F8: 0.069270373 | G8: 0.068704148 | H8: 2.0129764e-05 | I8: TRUE
A9: partial_authority | B9: h3_vz0_w6_d0.11 | C9: 1 | D9: 0.98899679 | E9: 0.98895585 | F9: 0.021154467 | G9: 0.02162794 | H9: 4.0941656e-05 | I9: TRUE
A10: partial_authority | B10: h3_vz0_w6_d0.11 | C10: 2 | D10: 0.9914055 | E10: 0.99135474 | F10: 0.06288969 | G10: 0.061979313 | H10: 5.0757824e-05 | I10: TRUE
A11: partial_authority | B11: h1.5_vz-1.5_w2_d0.3 | C11: 0 | D11: 5.1473539 | E11: 5.1464778 | F11: 1.1845288 | G11: 1.1839817 | H11: 0.00087613519 | I11: TRUE
A12: partial_authority | B12: h1.5_vz-1.5_w2_d0.3 | C12: 1 | D12: 4.7344414 | E12: 4.7330678 | F12: 0.89277743 | G12: 0.89362822 | H12: 0.0013736742 | I12: TRUE
A13: partial_authority | B13: h1.5_vz-1.5_w2_d0.3 | C13: 2 | D13: 4.7690708 | E13: 4.7689353 | F13: 0.95587716 | G13: 0.95563822 | H13: 0.00013552869 | I13: TRUE

Sheet Paired A
A1: class | B1: cell | C1: a | D1: b | E1: n | F1: both_safe | G1: only_a | H1: only_b | I1: neither | J1: discordant | K1: delta | L1: pi_lower | M1: pi_upper | N1: midp | O1: verdict
A2: one_out | B2: h1.5_vz-1.5_w2_d0.11 | C2: mechanism | D2: realloc_only | E2: 30 | F2: 2 | G2: 0 | H2: 0 | I2: 28 | J2: 0 | K2: 0 | N2: 1 | O2: no_discordant_pairs
A3: one_out | B3: h1.5_vz-1.5_w2_d0.3 | C3: mechanism | D3: realloc_only | E3: 300 | F3: 0 | G3: 0 | H3: 0 | I3: 300 | J3: 0 | K3: 0 | N3: 1 | O3: no_discordant_pairs
A4: one_out | B4: h1.5_vz-1.5_w6_d0.11 | C4: mechanism | D4: realloc_only | E4: 30 | F4: 0 | G4: 0 | H4: 0 | I4: 30 | J4: 0 | K4: 0 | N4: 1 | O4: no_discordant_pairs
A5: one_out | B5: h1.5_vz-1.5_w6_d0.3 | C5: mechanism | D5: realloc_only | E5: 30 | F5: 0 | G5: 0 | H5: 0 | I5: 30 | J5: 0 | K5: 0 | N5: 1 | O5: no_discordant_pairs
A6: one_out | B6: h1.5_vz0_w2_d0.11 | C6: mechanism | D6: realloc_only | E6: 30 | F6: 10 | G6: 0 | H6: 1 | I6: 19 | J6: 1 | K6: -0.033333333 | L6: 0 | M6: 0.975 | N6: 0.5 | O6: not_distinguished
A7: one_out | B7: h1.5_vz0_w2_d0.3 | C7: mechanism | D7: realloc_only | E7: 30 | F7: 0 | G7: 0 | H7: 0 | I7: 30 | J7: 0 | K7: 0 | N7: 1 | O7: no_discordant_pairs
A8: one_out | B8: h1.5_vz0_w6_d0.11 | C8: mechanism | D8: realloc_only | E8: 30 | F8: 0 | G8: 0 | H8: 0 | I8: 30 | J8: 0 | K8: 0 | N8: 1 | O8: no_discordant_pairs
A9: one_out | B9: h1.5_vz0_w6_d0.3 | C9: mechanism | D9: realloc_only | E9: 30 | F9: 0 | G9: 0 | H9: 0 | I9: 30 | J9: 0 | K9: 0 | N9: 1 | O9: no_discordant_pairs
A10: one_out | B10: h3_vz-1.5_w2_d0.11 | C10: mechanism | D10: realloc_only | E10: 30 | F10: 6 | G10: 0 | H10: 3 | I10: 21 | J10: 3 | K10: -0.1 | L10: 0 | M10: 0.70759823 | N10: 0.125 | O10: not_distinguished
A11: one_out | B11: h3_vz-1.5_w2_d0.3 | C11: mechanism | D11: realloc_only | E11: 30 | F11: 0 | G11: 0 | H11: 0 | I11: 30 | J11: 0 | K11: 0 | N11: 1 | O11: no_discordant_pairs
A12: one_out | B12: h3_vz-1.5_w6_d0.11 | C12: mechanism | D12: realloc_only | E12: 30 | F12: 0 | G12: 0 | H12: 0 | I12: 30 | J12: 0 | K12: 0 | N12: 1 | O12: no_discordant_pairs
A13: one_out | B13: h3_vz-1.5_w6_d0.3 | C13: mechanism | D13: realloc_only | E13: 30 | F13: 0 | G13: 0 | H13: 0 | I13: 30 | J13: 0 | K13: 0 | N13: 1 | O13: no_discordant_pairs
A14: one_out | B14: h3_vz0_w2_d0.11 | C14: mechanism | D14: realloc_only | E14: 30 | F14: 9 | G14: 0 | H14: 2 | I14: 19 | J14: 2 | K14: -0.066666667 | L14: 0 | M14: 0.84188612 | N14: 0.25 | O14: not_distinguished
A15: one_out | B15: h3_vz0_w2_d0.3 | C15: mechanism | D15: realloc_only | E15: 30 | F15: 3 | G15: 0 | H15: 4 | I15: 23 | J15: 4 | K15: -0.13333333 | L15: 0 | M15: 0.60236464 | N15: 0.0625 | O15: not_distinguished
A16: one_out | B16: h3_vz0_w6_d0.11 | C16: mechanism | D16: realloc_only | E16: 300 | F16: 0 | G16: 0 | H16: 0 | I16: 300 | J16: 0 | K16: 0 | N16: 1 | O16: no_discordant_pairs
A17: one_out | B17: h3_vz0_w6_d0.3 | C17: mechanism | D17: realloc_only | E17: 30 | F17: 0 | G17: 0 | H17: 0 | I17: 30 | J17: 0 | K17: 0 | N17: 1 | O17: no_discordant_pairs
A18: one_out | B18: h6_vz-1.5_w2_d0.11 | C18: mechanism | D18: realloc_only | E18: 30 | F18: 11 | G18: 0 | H18: 4 | I18: 15 | J18: 4 | K18: -0.13333333 | L18: 0 | M18: 0.60236464 | N18: 0.0625 | O18: not_distinguished
A19: one_out | B19: h6_vz-1.5_w2_d0.3 | C19: mechanism | D19: realloc_only | E19: 30 | F19: 11 | G19: 0 | H19: 5 | I19: 14 | J19: 5 | K19: -0.16666667 | L19: 0 | M19: 0.52182375 | N19: 0.03125 | O19: not_distinguished
A20: one_out | B20: h6_vz-1.5_w6_d0.11 | C20: mechanism | D20: realloc_only | E20: 30 | F20: 0 | G20: 0 | H20: 0 | I20: 30 | J20: 0 | K20: 0 | N20: 1 | O20: no_discordant_pairs
A21: one_out | B21: h6_vz-1.5_w6_d0.3 | C21: mechanism | D21: realloc_only | E21: 30 | F21: 0 | G21: 0 | H21: 0 | I21: 30 | J21: 0 | K21: 0 | N21: 1 | O21: no_discordant_pairs
A22: one_out | B22: h6_vz0_w2_d0.11 | C22: mechanism | D22: realloc_only | E22: 30 | F22: 14 | G22: 0 | H22: 1 | I22: 15 | J22: 1 | K22: -0.033333333 | L22: 0 | M22: 0.975 | N22: 0.5 | O22: not_distinguished
A23: one_out | B23: h6_vz0_w2_d0.3 | C23: mechanism | D23: realloc_only | E23: 30 | F23: 10 | G23: 0 | H23: 3 | I23: 17 | J23: 3 | K23: -0.1 | L23: 0 | M23: 0.70759823 | N23: 0.125 | O23: not_distinguished
A24: one_out | B24: h6_vz0_w6_d0.11 | C24: mechanism | D24: realloc_only | E24: 30 | F24: 0 | G24: 0 | H24: 0 | I24: 30 | J24: 0 | K24: 0 | N24: 1 | O24: no_discordant_pairs
A25: one_out | B25: h6_vz0_w6_d0.3 | C25: mechanism | D25: realloc_only | E25: 30 | F25: 0 | G25: 0 | H25: 1 | I25: 29 | J25: 1 | K25: -0.033333333 | L25: 0 | M25: 0.975 | N25: 0.5 | O25: not_distinguished
A26: partial_authority | B26: h1.5_vz-1.5_w2_d0.11 | C26: mechanism | D26: realloc_only | E26: 30 | F26: 29 | G26: 0 | H26: 1 | I26: 0 | J26: 1 | K26: -0.033333333 | L26: 0 | M26: 0.975 | N26: 0.5 | O26: not_distinguished
A27: partial_authority | B27: h1.5_vz-1.5_w2_d0.3 | C27: mechanism | D27: realloc_only | E27: 30 | F27: 0 | G27: 0 | H27: 0 | I27: 30 | J27: 0 | K27: 0 | N27: 1 | O27: no_discordant_pairs
A28: partial_authority | B28: h1.5_vz-1.5_w6_d0.11 | C28: mechanism | D28: realloc_only | E28: 30 | F28: 0 | G28: 0 | H28: 4 | I28: 26 | J28: 4 | K28: -0.13333333 | L28: 0 | M28: 0.60236464 | N28: 0.0625 | O28: not_distinguished
A29: partial_authority | B29: h1.5_vz-1.5_w6_d0.3 | C29: mechanism | D29: realloc_only | E29: 30 | F29: 0 | G29: 0 | H29: 0 | I29: 30 | J29: 0 | K29: 0 | N29: 1 | O29: no_discordant_pairs
A30: partial_authority | B30: h1.5_vz0_w2_d0.11 | C30: mechanism | D30: realloc_only | E30: 30 | F30: 30 | G30: 0 | H30: 0 | I30: 0 | J30: 0 | K30: 0 | N30: 1 | O30: no_discordant_pairs
A31: partial_authority | B31: h1.5_vz0_w2_d0.3 | C31: mechanism | D31: realloc_only | E31: 30 | F31: 5 | G31: 0 | H31: 3 | I31: 22 | J31: 3 | K31: -0.1 | L31: 0 | M31: 0.70759823 | N31: 0.125 | O31: not_distinguished
A32: partial_authority | B32: h1.5_vz0_w6_d0.11 | C32: mechanism | D32: realloc_only | E32: 30 | F32: 14 | G32: 1 | H32: 3 | I32: 12 | J32: 4 | K32: -0.066666667 | L32: 0.0063094632 | M32: 0.80587955 | N32: 0.375 | O32: not_distinguished
A33: partial_authority | B33: h1.5_vz0_w6_d0.3 | C33: mechanism | D33: realloc_only | E33: 30 | F33: 0 | G33: 0 | H33: 0 | I33: 30 | J33: 0 | K33: 0 | N33: 1 | O33: no_discordant_pairs
A34: partial_authority | B34: h3_vz-1.5_w2_d0.11 | C34: mechanism | D34: realloc_only | E34: 30 | F34: 30 | G34: 0 | H34: 0 | I34: 0 | J34: 0 | K34: 0 | N34: 1 | O34: no_discordant_pairs
A35: partial_authority | B35: h3_vz-1.5_w2_d0.3 | C35: mechanism | D35: realloc_only | E35: 30 | F35: 8 | G35: 0 | H35: 6 | I35: 16 | J35: 6 | K35: -0.2 | L35: 0 | M35: 0.45925813 | N35: 0.015625 | O35: b_superior
A36: partial_authority | B36: h3_vz-1.5_w6_d0.11 | C36: mechanism | D36: realloc_only | E36: 30 | F36: 16 | G36: 1 | H36: 7 | I36: 6 | J36: 8 | K36: -0.2 | L36: 0.0031597235 | M36: 0.52650967 | N36: 0.0390625 | O36: not_distinguished
A37: partial_authority | B37: h3_vz-1.5_w6_d0.3 | C37: mechanism | D37: realloc_only | E37: 30 | F37: 0 | G37: 0 | H37: 0 | I37: 30 | J37: 0 | K37: 0 | N37: 1 | O37: no_discordant_pairs
A38: partial_authority | B38: h3_vz0_w2_d0.11 | C38: mechanism | D38: realloc_only | E38: 30 | F38: 30 | G38: 0 | H38: 0 | I38: 0 | J38: 0 | K38: 0 | N38: 1 | O38: no_discordant_pairs
A39: partial_authority | B39: h3_vz0_w2_d0.3 | C39: mechanism | D39: realloc_only | E39: 30 | F39: 28 | G39: 0 | H39: 2 | I39: 0 | J39: 2 | K39: -0.066666667 | L39: 0 | M39: 0.84188612 | N39: 0.25 | O39: not_distinguished
A40: partial_authority | B40: h3_vz0_w6_d0.11 | C40: mechanism | D40: realloc_only | E40: 30 | F40: 30 | G40: 0 | H40: 0 | I40: 0 | J40: 0 | K40: 0 | N40: 1 | O40: no_discordant_pairs
A41: partial_authority | B41: h3_vz0_w6_d0.3 | C41: mechanism | D41: realloc_only | E41: 30 | F41: 0 | G41: 0 | H41: 0 | I41: 30 | J41: 0 | K41: 0 | N41: 1 | O41: no_discordant_pairs
A42: partial_authority | B42: h6_vz-1.5_w2_d0.11 | C42: mechanism | D42: realloc_only | E42: 30 | F42: 30 | G42: 0 | H42: 0 | I42: 0 | J42: 0 | K42: 0 | N42: 1 | O42: no_discordant_pairs
A43: partial_authority | B43: h6_vz-1.5_w2_d0.3 | C43: mechanism | D43: realloc_only | E43: 30 | F43: 30 | G43: 0 | H43: 0 | I43: 0 | J43: 0 | K43: 0 | N43: 1 | O43: no_discordant_pairs
A44: partial_authority | B44: h6_vz-1.5_w6_d0.11 | C44: mechanism | D44: realloc_only | E44: 30 | F44: 30 | G44: 0 | H44: 0 | I44: 0 | J44: 0 | K44: 0 | N44: 1 | O44: no_discordant_pairs
A45: partial_authority | B45: h6_vz-1.5_w6_d0.3 | C45: mechanism | D45: realloc_only | E45: 30 | F45: 0 | G45: 0 | H45: 0 | I45: 30 | J45: 0 | K45: 0 | N45: 1 | O45: no_discordant_pairs
A46: partial_authority | B46: h6_vz0_w2_d0.11 | C46: mechanism | D46: realloc_only | E46: 30 | F46: 30 | G46: 0 | H46: 0 | I46: 0 | J46: 0 | K46: 0 | N46: 1 | O46: no_discordant_pairs
A47: partial_authority | B47: h6_vz0_w2_d0.3 | C47: mechanism | D47: realloc_only | E47: 30 | F47: 30 | G47: 0 | H47: 0 | I47: 0 | J47: 0 | K47: 0 | N47: 1 | O47: no_discordant_pairs
A48: partial_authority | B48: h6_vz0_w6_d0.11 | C48: mechanism | D48: realloc_only | E48: 30 | F48: 30 | G48: 0 | H48: 0 | I48: 0 | J48: 0 | K48: 0 | N48: 1 | O48: no_discordant_pairs
A49: partial_authority | B49: h6_vz0_w6_d0.3 | C49: mechanism | D49: realloc_only | E49: 30 | F49: 0 | G49: 0 | H49: 1 | I49: 29 | J49: 1 | K49: -0.033333333 | L49: 0 | M49: 0.975 | N49: 0.5 | O49: not_distinguished
A50: two_adjacent | B50: h1.5_vz-1.5_w2_d0.11 | C50: mechanism | D50: realloc_only | E50: 30 | F50: 0 | G50: 0 | H50: 0 | I50: 30 | J50: 0 | K50: 0 | N50: 1 | O50: no_discordant_pairs
A51: two_adjacent | B51: h1.5_vz-1.5_w2_d0.3 | C51: mechanism | D51: realloc_only | E51: 300 | F51: 0 | G51: 0 | H51: 0 | I51: 300 | J51: 0 | K51: 0 | N51: 1 | O51: no_discordant_pairs
A52: two_adjacent | B52: h1.5_vz-1.5_w6_d0.11 | C52: mechanism | D52: realloc_only | E52: 30 | F52: 0 | G52: 0 | H52: 0 | I52: 30 | J52: 0 | K52: 0 | N52: 1 | O52: no_discordant_pairs
A53: two_adjacent | B53: h1.5_vz-1.5_w6_d0.3 | C53: mechanism | D53: realloc_only | E53: 30 | F53: 0 | G53: 0 | H53: 0 | I53: 30 | J53: 0 | K53: 0 | N53: 1 | O53: no_discordant_pairs
A54: two_adjacent | B54: h1.5_vz0_w2_d0.11 | C54: mechanism | D54: realloc_only | E54: 30 | F54: 0 | G54: 0 | H54: 0 | I54: 30 | J54: 0 | K54: 0 | N54: 1 | O54: no_discordant_pairs
A55: two_adjacent | B55: h1.5_vz0_w2_d0.3 | C55: mechanism | D55: realloc_only | E55: 30 | F55: 0 | G55: 0 | H55: 0 | I55: 30 | J55: 0 | K55: 0 | N55: 1 | O55: no_discordant_pairs
A56: two_adjacent | B56: h1.5_vz0_w6_d0.11 | C56: mechanism | D56: realloc_only | E56: 30 | F56: 0 | G56: 0 | H56: 0 | I56: 30 | J56: 0 | K56: 0 | N56: 1 | O56: no_discordant_pairs
A57: two_adjacent | B57: h1.5_vz0_w6_d0.3 | C57: mechanism | D57: realloc_only | E57: 30 | F57: 0 | G57: 0 | H57: 0 | I57: 30 | J57: 0 | K57: 0 | N57: 1 | O57: no_discordant_pairs
A58: two_adjacent | B58: h3_vz-1.5_w2_d0.11 | C58: mechanism | D58: realloc_only | E58: 30 | F58: 0 | G58: 0 | H58: 0 | I58: 30 | J58: 0 | K58: 0 | N58: 1 | O58: no_discordant_pairs
A59: two_adjacent | B59: h3_vz-1.5_w2_d0.3 | C59: mechanism | D59: realloc_only | E59: 30 | F59: 0 | G59: 0 | H59: 0 | I59: 30 | J59: 0 | K59: 0 | N59: 1 | O59: no_discordant_pairs
A60: two_adjacent | B60: h3_vz-1.5_w6_d0.11 | C60: mechanism | D60: realloc_only | E60: 30 | F60: 0 | G60: 0 | H60: 0 | I60: 30 | J60: 0 | K60: 0 | N60: 1 | O60: no_discordant_pairs
A61: two_adjacent | B61: h3_vz-1.5_w6_d0.3 | C61: mechanism | D61: realloc_only | E61: 30 | F61: 0 | G61: 0 | H61: 0 | I61: 30 | J61: 0 | K61: 0 | N61: 1 | O61: no_discordant_pairs
... A73: two_adjacent | B73: h6_vz0_w6_d0.3 | C73: mechanism | D73: realloc_only | E73: 30 | F73: 0 | G73: 0 | H73: 0 | I73: 30 | J73: 0 | K73: 0 | N73: 1 | O73: no_discordant_pairs
A74: two_opposite | B74: h1.5_vz-1.5_w2_d0.11 | C74: mechanism | D74: realloc_only | E74: 30 | F74: 0 | G74: 4 | H74: 0 | I74: 26 | J74: 4 | K74: 0.13333333 | L74: 0.39763536 | M74: 1 | N74: 0.0625 | O74: not_distinguished
A75: two_opposite | B75: h1.5_vz-1.5_w2_d0.3 | C75: mechanism | D75: realloc_only | E75: 30 | F75: 0 | G75: 0 | H75: 0 | I75: 30 | J75: 0 | K75: 0 | N75: 1 | O75: no_discordant_pairs
A76: two_opposite | B76: h1.5_vz-1.5_w6_d0.11 | C76: mechanism | D76: realloc_only | E76: 30 | F76: 0 | G76: 0 | H76: 0 | I76: 30 | J76: 0 | K76: 0 | N76: 1 | O76: no_discordant_pairs
A77: two_opposite | B77: h1.5_vz-1.5_w6_d0.3 | C77: mechanism | D77: realloc_only | E77: 30 | F77: 0 | G77: 0 | H77: 0 | I77: 30 | J77: 0 | K77: 0 | N77: 1 | O77: no_discordant_pairs
A78: two_opposite | B78: h1.5_vz0_w2_d0.11 | C78: mechanism | D78: realloc_only | E78: 30 | F78: 0 | G78: 1 | H78: 1 | I78: 28 | J78: 2 | K78: 0 | L78: 0.012579117 | M78: 0.98742088 | N78: 1 | O78: not_distinguished
A79: two_opposite | B79: h1.5_vz0_w2_d0.3 | C79: mechanism | D79: realloc_only | E79: 30 | F79: 0 | G79: 0 | H79: 0 | I79: 30 | J79: 0 | K79: 0 | N79: 1 | O79: no_discordant_pairs
A80: two_opposite | B80: h1.5_vz0_w6_d0.11 | C80: mechanism | D80: realloc_only | E80: 30 | F80: 0 | G80: 0 | H80: 0 | I80: 30 | J80: 0 | K80: 0 | N80: 1 | O80: no_discordant_pairs
A81: two_opposite | B81: h1.5_vz0_w6_d0.3 | C81: mechanism | D81: realloc_only | E81: 30 | F81: 0 | G81: 0 | H81: 0 | I81: 30 | J81: 0 | K81: 0 | N81: 1 | O81: no_discordant_pairs
A82: two_opposite | B82: h3_vz-1.5_w2_d0.11 | C82: mechanism | D82: realloc_only | E82: 30 | F82: 1 | G82: 0 | H82: 2 | I82: 27 | J82: 2 | K82: -0.066666667 | L82: 0 | M82: 0.84188612 | N82: 0.25 | O82: not_distinguished
A83: two_opposite | B83: h3_vz-1.5_w2_d0.3 | C83: mechanism | D83: realloc_only | E83: 30 | F83: 0 | G83: 0 | H83: 0 | I83: 30 | J83: 0 | K83: 0 | N83: 1 | O83: no_discordant_pairs
A84: two_opposite | B84: h3_vz-1.5_w6_d0.11 | C84: mechanism | D84: realloc_only | E84: 30 | F84: 0 | G84: 0 | H84: 0 | I84: 30 | J84: 0 | K84: 0 | N84: 1 | O84: no_discordant_pairs
A85: two_opposite | B85: h3_vz-1.5_w6_d0.3 | C85: mechanism | D85: realloc_only | E85: 30 | F85: 0 | G85: 0 | H85: 0 | I85: 30 | J85: 0 | K85: 0 | N85: 1 | O85: no_discordant_pairs
A86: two_opposite | B86: h3_vz0_w2_d0.11 | C86: mechanism | D86: realloc_only | E86: 30 | F86: 4 | G86: 0 | H86: 2 | I86: 24 | J86: 2 | K86: -0.066666667 | L86: 0 | M86: 0.84188612 | N86: 0.25 | O86: not_distinguished
A87: two_opposite | B87: h3_vz0_w2_d0.3 | C87: mechanism | D87: realloc_only | E87: 30 | F87: 0 | G87: 0 | H87: 0 | I87: 30 | J87: 0 | K87: 0 | N87: 1 | O87: no_discordant_pairs
A88: two_opposite | B88: h3_vz0_w6_d0.11 | C88: mechanism | D88: realloc_only | E88: 30 | F88: 0 | G88: 0 | H88: 0 | I88: 30 | J88: 0 | K88: 0 | N88: 1 | O88: no_discordant_pairs
A89: two_opposite | B89: h3_vz0_w6_d0.3 | C89: mechanism | D89: realloc_only | E89: 30 | F89: 0 | G89: 0 | H89: 0 | I89: 30 | J89: 0 | K89: 0 | N89: 1 | O89: no_discordant_pairs
A90: two_opposite | B90: h6_vz-1.5_w2_d0.11 | C90: mechanism | D90: realloc_only | E90: 30 | F90: 6 | G90: 0 | H90: 4 | I90: 20 | J90: 4 | K90: -0.13333333 | L90: 0 | M90: 0.60236464 | N90: 0.0625 | O90: not_distinguished
A91: two_opposite | B91: h6_vz-1.5_w2_d0.3 | C91: mechanism | D91: realloc_only | E91: 30 | F91: 0 | G91: 0 | H91: 0 | I91: 30 | J91: 0 | K91: 0 | N91: 1 | O91: no_discordant_pairs
A92: two_opposite | B92: h6_vz-1.5_w6_d0.11 | C92: mechanism | D92: realloc_only | E92: 30 | F92: 0 | G92: 0 | H92: 0 | I92: 30 | J92: 0 | K92: 0 | N92: 1 | O92: no_discordant_pairs
A93: two_opposite | B93: h6_vz-1.5_w6_d0.3 | C93: mechanism | D93: realloc_only | E93: 30 | F93: 0 | G93: 0 | H93: 0 | I93: 30 | J93: 0 | K93: 0 | N93: 1 | O93: no_discordant_pairs
A94: two_opposite | B94: h6_vz0_w2_d0.11 | C94: mechanism | D94: realloc_only | E94: 30 | F94: 8 | G94: 0 | H94: 7 | I94: 15 | J94: 7 | K94: -0.23333333 | L94: 0 | M94: 0.4096164 | N94: 0.0078125 | O94: b_superior
A95: two_opposite | B95: h6_vz0_w2_d0.3 | C95: mechanism | D95: realloc_only | E95: 30 | F95: 0 | G95: 0 | H95: 2 | I95: 28 | J95: 2 | K95: -0.066666667 | L95: 0 | M95: 0.84188612 | N95: 0.25 | O95: not_distinguished
A96: two_opposite | B96: h6_vz0_w6_d0.11 | C96: mechanism | D96: realloc_only | E96: 30 | F96: 0 | G96: 0 | H96: 0 | I96: 30 | J96: 0 | K96: 0 | N96: 1 | O96: no_discordant_pairs
A97: two_opposite | B97: h6_vz0_w6_d0.3 | C97: mechanism | D97: realloc_only | E97: 30 | F97: 0 | G97: 0 | H97: 0 | I97: 30 | J97: 0 | K97: 0 | N97: 1 | O97: no_discordant_pairs

Sheet Paired A2
A1: class | B1: cell | C1: a | D1: b | E1: n | F1: both_safe | G1: only_a | H1: only_b | I1: neither | J1: discordant | K1: delta | L1: pi_lower | M1: pi_upper | N1: midp | O1: verdict
A2: one_out | B2: h1.5_vz-1.5_w2_d0.11 | C2: mechanism | D2: realloc_only | E2: 30 | F2: 2 | G2: 0 | H2: 0 | I2: 28 | J2: 0 | K2: 0 | N2: 1 | O2: no_discordant_pairs
A3: one_out | B3: h1.5_vz-1.5_w2_d0.3 | C3: mechanism | D3: realloc_only | E3: 300 | F3: 0 | G3: 0 | H3: 0 | I3: 300 | J3: 0 | K3: 0 | N3: 1 | O3: no_discordant_pairs
A4: one_out | B4: h1.5_vz-1.5_w6_d0.11 | C4: mechanism | D4: realloc_only | E4: 30 | F4: 0 | G4: 0 | H4: 0 | I4: 30 | J4: 0 | K4: 0 | N4: 1 | O4: no_discordant_pairs
A5: one_out | B5: h1.5_vz-1.5_w6_d0.3 | C5: mechanism | D5: realloc_only | E5: 30 | F5: 0 | G5: 0 | H5: 0 | I5: 30 | J5: 0 | K5: 0 | N5: 1 | O5: no_discordant_pairs
A6: one_out | B6: h1.5_vz0_w2_d0.11 | C6: mechanism | D6: realloc_only | E6: 30 | F6: 10 | G6: 0 | H6: 1 | I6: 19 | J6: 1 | K6: -0.033333333 | L6: 0 | M6: 0.975 | N6: 0.5 | O6: not_distinguished
A7: one_out | B7: h1.5_vz0_w2_d0.3 | C7: mechanism | D7: realloc_only | E7: 30 | F7: 0 | G7: 0 | H7: 0 | I7: 30 | J7: 0 | K7: 0 | N7: 1 | O7: no_discordant_pairs
A8: one_out | B8: h1.5_vz0_w6_d0.11 | C8: mechanism | D8: realloc_only | E8: 30 | F8: 0 | G8: 0 | H8: 0 | I8: 30 | J8: 0 | K8: 0 | N8: 1 | O8: no_discordant_pairs
A9: one_out | B9: h1.5_vz0_w6_d0.3 | C9: mechanism | D9: realloc_only | E9: 30 | F9: 0 | G9: 0 | H9: 0 | I9: 30 | J9: 0 | K9: 0 | N9: 1 | O9: no_discordant_pairs
A10: one_out | B10: h3_vz-1.5_w2_d0.11 | C10: mechanism | D10: realloc_only | E10: 30 | F10: 6 | G10: 0 | H10: 3 | I10: 21 | J10: 3 | K10: -0.1 | L10: 0 | M10: 0.70759823 | N10: 0.125 | O10: not_distinguished
A11: one_out | B11: h3_vz-1.5_w2_d0.3 | C11: mechanism | D11: realloc_only | E11: 30 | F11: 0 | G11: 0 | H11: 0 | I11: 30 | J11: 0 | K11: 0 | N11: 1 | O11: no_discordant_pairs
A12: one_out | B12: h3_vz-1.5_w6_d0.11 | C12: mechanism | D12: realloc_only | E12: 30 | F12: 0 | G12: 0 | H12: 0 | I12: 30 | J12: 0 | K12: 0 | N12: 1 | O12: no_discordant_pairs
A13: one_out | B13: h3_vz-1.5_w6_d0.3 | C13: mechanism | D13: realloc_only | E13: 30 | F13: 0 | G13: 0 | H13: 0 | I13: 30 | J13: 0 | K13: 0 | N13: 1 | O13: no_discordant_pairs
A14: one_out | B14: h3_vz0_w2_d0.11 | C14: mechanism | D14: realloc_only | E14: 30 | F14: 9 | G14: 0 | H14: 1 | I14: 20 | J14: 1 | K14: -0.033333333 | L14: 0 | M14: 0.975 | N14: 0.5 | O14: not_distinguished
A15: one_out | B15: h3_vz0_w2_d0.3 | C15: mechanism | D15: realloc_only | E15: 30 | F15: 3 | G15: 0 | H15: 4 | I15: 23 | J15: 4 | K15: -0.13333333 | L15: 0 | M15: 0.60236464 | N15: 0.0625 | O15: not_distinguished
A16: one_out | B16: h3_vz0_w6_d0.11 | C16: mechanism | D16: realloc_only | E16: 300 | F16: 0 | G16: 0 | H16: 0 | I16: 300 | J16: 0 | K16: 0 | N16: 1 | O16: no_discordant_pairs
A17: one_out | B17: h3_vz0_w6_d0.3 | C17: mechanism | D17: realloc_only | E17: 30 | F17: 0 | G17: 0 | H17: 0 | I17: 30 | J17: 0 | K17: 0 | N17: 1 | O17: no_discordant_pairs
A18: one_out | B18: h6_vz-1.5_w2_d0.11 | C18: mechanism | D18: realloc_only | E18: 30 | F18: 11 | G18: 0 | H18: 4 | I18: 15 | J18: 4 | K18: -0.13333333 | L18: 0 | M18: 0.60236464 | N18: 0.0625 | O18: not_distinguished
A19: one_out | B19: h6_vz-1.5_w2_d0.3 | C19: mechanism | D19: realloc_only | E19: 30 | F19: 11 | G19: 0 | H19: 5 | I19: 14 | J19: 5 | K19: -0.16666667 | L19: 0 | M19: 0.52182375 | N19: 0.03125 | O19: not_distinguished
A20: one_out | B20: h6_vz-1.5_w6_d0.11 | C20: mechanism | D20: realloc_only | E20: 30 | F20: 0 | G20: 0 | H20: 0 | I20: 30 | J20: 0 | K20: 0 | N20: 1 | O20: no_discordant_pairs
A21: one_out | B21: h6_vz-1.5_w6_d0.3 | C21: mechanism | D21: realloc_only | E21: 30 | F21: 0 | G21: 0 | H21: 0 | I21: 30 | J21: 0 | K21: 0 | N21: 1 | O21: no_discordant_pairs
A22: one_out | B22: h6_vz0_w2_d0.11 | C22: mechanism | D22: realloc_only | E22: 30 | F22: 14 | G22: 0 | H22: 1 | I22: 15 | J22: 1 | K22: -0.033333333 | L22: 0 | M22: 0.975 | N22: 0.5 | O22: not_distinguished
A23: one_out | B23: h6_vz0_w2_d0.3 | C23: mechanism | D23: realloc_only | E23: 30 | F23: 10 | G23: 0 | H23: 3 | I23: 17 | J23: 3 | K23: -0.1 | L23: 0 | M23: 0.70759823 | N23: 0.125 | O23: not_distinguished
A24: one_out | B24: h6_vz0_w6_d0.11 | C24: mechanism | D24: realloc_only | E24: 30 | F24: 0 | G24: 0 | H24: 0 | I24: 30 | J24: 0 | K24: 0 | N24: 1 | O24: no_discordant_pairs
A25: one_out | B25: h6_vz0_w6_d0.3 | C25: mechanism | D25: realloc_only | E25: 30 | F25: 0 | G25: 0 | H25: 1 | I25: 29 | J25: 1 | K25: -0.033333333 | L25: 0 | M25: 0.975 | N25: 0.5 | O25: not_distinguished
A26: partial_authority | B26: h1.5_vz-1.5_w2_d0.11 | C26: mechanism | D26: realloc_only | E26: 30 | F26: 29 | G26: 0 | H26: 1 | I26: 0 | J26: 1 | K26: -0.033333333 | L26: 0 | M26: 0.975 | N26: 0.5 | O26: not_distinguished
A27: partial_authority | B27: h1.5_vz-1.5_w2_d0.3 | C27: mechanism | D27: realloc_only | E27: 30 | F27: 0 | G27: 0 | H27: 0 | I27: 30 | J27: 0 | K27: 0 | N27: 1 | O27: no_discordant_pairs
A28: partial_authority | B28: h1.5_vz-1.5_w6_d0.11 | C28: mechanism | D28: realloc_only | E28: 30 | F28: 0 | G28: 0 | H28: 4 | I28: 26 | J28: 4 | K28: -0.13333333 | L28: 0 | M28: 0.60236464 | N28: 0.0625 | O28: not_distinguished
A29: partial_authority | B29: h1.5_vz-1.5_w6_d0.3 | C29: mechanism | D29: realloc_only | E29: 30 | F29: 0 | G29: 0 | H29: 0 | I29: 30 | J29: 0 | K29: 0 | N29: 1 | O29: no_discordant_pairs
A30: partial_authority | B30: h1.5_vz0_w2_d0.11 | C30: mechanism | D30: realloc_only | E30: 30 | F30: 30 | G30: 0 | H30: 0 | I30: 0 | J30: 0 | K30: 0 | N30: 1 | O30: no_discordant_pairs
A31: partial_authority | B31: h1.5_vz0_w2_d0.3 | C31: mechanism | D31: realloc_only | E31: 30 | F31: 5 | G31: 0 | H31: 3 | I31: 22 | J31: 3 | K31: -0.1 | L31: 0 | M31: 0.70759823 | N31: 0.125 | O31: not_distinguished
A32: partial_authority | B32: h1.5_vz0_w6_d0.11 | C32: mechanism | D32: realloc_only | E32: 30 | F32: 14 | G32: 1 | H32: 3 | I32: 12 | J32: 4 | K32: -0.066666667 | L32: 0.0063094632 | M32: 0.80587955 | N32: 0.375 | O32: not_distinguished
A33: partial_authority | B33: h1.5_vz0_w6_d0.3 | C33: mechanism | D33: realloc_only | E33: 30 | F33: 0 | G33: 0 | H33: 0 | I33: 30 | J33: 0 | K33: 0 | N33: 1 | O33: no_discordant_pairs
A34: partial_authority | B34: h3_vz-1.5_w2_d0.11 | C34: mechanism | D34: realloc_only | E34: 30 | F34: 30 | G34: 0 | H34: 0 | I34: 0 | J34: 0 | K34: 0 | N34: 1 | O34: no_discordant_pairs
A35: partial_authority | B35: h3_vz-1.5_w2_d0.3 | C35: mechanism | D35: realloc_only | E35: 30 | F35: 8 | G35: 0 | H35: 6 | I35: 16 | J35: 6 | K35: -0.2 | L35: 0 | M35: 0.45925813 | N35: 0.015625 | O35: b_superior
A36: partial_authority | B36: h3_vz-1.5_w6_d0.11 | C36: mechanism | D36: realloc_only | E36: 30 | F36: 16 | G36: 1 | H36: 7 | I36: 6 | J36: 8 | K36: -0.2 | L36: 0.0031597235 | M36: 0.52650967 | N36: 0.0390625 | O36: not_distinguished
A37: partial_authority | B37: h3_vz-1.5_w6_d0.3 | C37: mechanism | D37: realloc_only | E37: 30 | F37: 0 | G37: 0 | H37: 0 | I37: 30 | J37: 0 | K37: 0 | N37: 1 | O37: no_discordant_pairs
A38: partial_authority | B38: h3_vz0_w2_d0.11 | C38: mechanism | D38: realloc_only | E38: 30 | F38: 30 | G38: 0 | H38: 0 | I38: 0 | J38: 0 | K38: 0 | N38: 1 | O38: no_discordant_pairs
A39: partial_authority | B39: h3_vz0_w2_d0.3 | C39: mechanism | D39: realloc_only | E39: 30 | F39: 28 | G39: 0 | H39: 2 | I39: 0 | J39: 2 | K39: -0.066666667 | L39: 0 | M39: 0.84188612 | N39: 0.25 | O39: not_distinguished
A40: partial_authority | B40: h3_vz0_w6_d0.11 | C40: mechanism | D40: realloc_only | E40: 30 | F40: 30 | G40: 0 | H40: 0 | I40: 0 | J40: 0 | K40: 0 | N40: 1 | O40: no_discordant_pairs
A41: partial_authority | B41: h3_vz0_w6_d0.3 | C41: mechanism | D41: realloc_only | E41: 30 | F41: 0 | G41: 0 | H41: 0 | I41: 30 | J41: 0 | K41: 0 | N41: 1 | O41: no_discordant_pairs
A42: partial_authority | B42: h6_vz-1.5_w2_d0.11 | C42: mechanism | D42: realloc_only | E42: 30 | F42: 30 | G42: 0 | H42: 0 | I42: 0 | J42: 0 | K42: 0 | N42: 1 | O42: no_discordant_pairs
A43: partial_authority | B43: h6_vz-1.5_w2_d0.3 | C43: mechanism | D43: realloc_only | E43: 30 | F43: 30 | G43: 0 | H43: 0 | I43: 0 | J43: 0 | K43: 0 | N43: 1 | O43: no_discordant_pairs
A44: partial_authority | B44: h6_vz-1.5_w6_d0.11 | C44: mechanism | D44: realloc_only | E44: 30 | F44: 30 | G44: 0 | H44: 0 | I44: 0 | J44: 0 | K44: 0 | N44: 1 | O44: no_discordant_pairs
A45: partial_authority | B45: h6_vz-1.5_w6_d0.3 | C45: mechanism | D45: realloc_only | E45: 30 | F45: 0 | G45: 0 | H45: 0 | I45: 30 | J45: 0 | K45: 0 | N45: 1 | O45: no_discordant_pairs
A46: partial_authority | B46: h6_vz0_w2_d0.11 | C46: mechanism | D46: realloc_only | E46: 30 | F46: 30 | G46: 0 | H46: 0 | I46: 0 | J46: 0 | K46: 0 | N46: 1 | O46: no_discordant_pairs
A47: partial_authority | B47: h6_vz0_w2_d0.3 | C47: mechanism | D47: realloc_only | E47: 30 | F47: 30 | G47: 0 | H47: 0 | I47: 0 | J47: 0 | K47: 0 | N47: 1 | O47: no_discordant_pairs
A48: partial_authority | B48: h6_vz0_w6_d0.11 | C48: mechanism | D48: realloc_only | E48: 30 | F48: 30 | G48: 0 | H48: 0 | I48: 0 | J48: 0 | K48: 0 | N48: 1 | O48: no_discordant_pairs
A49: partial_authority | B49: h6_vz0_w6_d0.3 | C49: mechanism | D49: realloc_only | E49: 30 | F49: 0 | G49: 0 | H49: 1 | I49: 29 | J49: 1 | K49: -0.033333333 | L49: 0 | M49: 0.975 | N49: 0.5 | O49: not_distinguished
A50: two_adjacent | B50: h1.5_vz-1.5_w2_d0.11 | C50: mechanism | D50: realloc_only | E50: 30 | F50: 0 | G50: 0 | H50: 0 | I50: 30 | J50: 0 | K50: 0 | N50: 1 | O50: no_discordant_pairs
A51: two_adjacent | B51: h1.5_vz-1.5_w2_d0.3 | C51: mechanism | D51: realloc_only | E51: 300 | F51: 0 | G51: 0 | H51: 0 | I51: 300 | J51: 0 | K51: 0 | N51: 1 | O51: no_discordant_pairs
A52: two_adjacent | B52: h1.5_vz-1.5_w6_d0.11 | C52: mechanism | D52: realloc_only | E52: 30 | F52: 0 | G52: 0 | H52: 0 | I52: 30 | J52: 0 | K52: 0 | N52: 1 | O52: no_discordant_pairs
A53: two_adjacent | B53: h1.5_vz-1.5_w6_d0.3 | C53: mechanism | D53: realloc_only | E53: 30 | F53: 0 | G53: 0 | H53: 0 | I53: 30 | J53: 0 | K53: 0 | N53: 1 | O53: no_discordant_pairs
A54: two_adjacent | B54: h1.5_vz0_w2_d0.11 | C54: mechanism | D54: realloc_only | E54: 30 | F54: 0 | G54: 0 | H54: 0 | I54: 30 | J54: 0 | K54: 0 | N54: 1 | O54: no_discordant_pairs
A55: two_adjacent | B55: h1.5_vz0_w2_d0.3 | C55: mechanism | D55: realloc_only | E55: 30 | F55: 0 | G55: 0 | H55: 0 | I55: 30 | J55: 0 | K55: 0 | N55: 1 | O55: no_discordant_pairs
A56: two_adjacent | B56: h1.5_vz0_w6_d0.11 | C56: mechanism | D56: realloc_only | E56: 30 | F56: 0 | G56: 0 | H56: 0 | I56: 30 | J56: 0 | K56: 0 | N56: 1 | O56: no_discordant_pairs
A57: two_adjacent | B57: h1.5_vz0_w6_d0.3 | C57: mechanism | D57: realloc_only | E57: 30 | F57: 0 | G57: 0 | H57: 0 | I57: 30 | J57: 0 | K57: 0 | N57: 1 | O57: no_discordant_pairs
A58: two_adjacent | B58: h3_vz-1.5_w2_d0.11 | C58: mechanism | D58: realloc_only | E58: 30 | F58: 0 | G58: 0 | H58: 0 | I58: 30 | J58: 0 | K58: 0 | N58: 1 | O58: no_discordant_pairs
A59: two_adjacent | B59: h3_vz-1.5_w2_d0.3 | C59: mechanism | D59: realloc_only | E59: 30 | F59: 0 | G59: 0 | H59: 0 | I59: 30 | J59: 0 | K59: 0 | N59: 1 | O59: no_discordant_pairs
A60: two_adjacent | B60: h3_vz-1.5_w6_d0.11 | C60: mechanism | D60: realloc_only | E60: 30 | F60: 0 | G60: 0 | H60: 0 | I60: 30 | J60: 0 | K60: 0 | N60: 1 | O60: no_discordant_pairs
A61: two_adjacent | B61: h3_vz-1.5_w6_d0.3 | C61: mechanism | D61: realloc_only | E61: 30 | F61: 0 | G61: 0 | H61: 0 | I61: 30 | J61: 0 | K61: 0 | N61: 1 | O61: no_discordant_pairs
... A73: two_adjacent | B73: h6_vz0_w6_d0.3 | C73: mechanism | D73: realloc_only | E73: 30 | F73: 0 | G73: 0 | H73: 0 | I73: 30 | J73: 0 | K73: 0 | N73: 1 | O73: no_discordant_pairs
A74: two_opposite | B74: h1.5_vz-1.5_w2_d0.11 | C74: mechanism | D74: realloc_only | E74: 30 | F74: 0 | G74: 4 | H74: 0 | I74: 26 | J74: 4 | K74: 0.13333333 | L74: 0.39763536 | M74: 1 | N74: 0.0625 | O74: not_distinguished
A75: two_opposite | B75: h1.5_vz-1.5_w2_d0.3 | C75: mechanism | D75: realloc_only | E75: 30 | F75: 0 | G75: 0 | H75: 0 | I75: 30 | J75: 0 | K75: 0 | N75: 1 | O75: no_discordant_pairs
A76: two_opposite | B76: h1.5_vz-1.5_w6_d0.11 | C76: mechanism | D76: realloc_only | E76: 30 | F76: 0 | G76: 0 | H76: 0 | I76: 30 | J76: 0 | K76: 0 | N76: 1 | O76: no_discordant_pairs
A77: two_opposite | B77: h1.5_vz-1.5_w6_d0.3 | C77: mechanism | D77: realloc_only | E77: 30 | F77: 0 | G77: 0 | H77: 0 | I77: 30 | J77: 0 | K77: 0 | N77: 1 | O77: no_discordant_pairs
A78: two_opposite | B78: h1.5_vz0_w2_d0.11 | C78: mechanism | D78: realloc_only | E78: 30 | F78: 0 | G78: 1 | H78: 1 | I78: 28 | J78: 2 | K78: 0 | L78: 0.012579117 | M78: 0.98742088 | N78: 1 | O78: not_distinguished
A79: two_opposite | B79: h1.5_vz0_w2_d0.3 | C79: mechanism | D79: realloc_only | E79: 30 | F79: 0 | G79: 0 | H79: 0 | I79: 30 | J79: 0 | K79: 0 | N79: 1 | O79: no_discordant_pairs
A80: two_opposite | B80: h1.5_vz0_w6_d0.11 | C80: mechanism | D80: realloc_only | E80: 30 | F80: 0 | G80: 0 | H80: 0 | I80: 30 | J80: 0 | K80: 0 | N80: 1 | O80: no_discordant_pairs
A81: two_opposite | B81: h1.5_vz0_w6_d0.3 | C81: mechanism | D81: realloc_only | E81: 30 | F81: 0 | G81: 0 | H81: 0 | I81: 30 | J81: 0 | K81: 0 | N81: 1 | O81: no_discordant_pairs
A82: two_opposite | B82: h3_vz-1.5_w2_d0.11 | C82: mechanism | D82: realloc_only | E82: 30 | F82: 1 | G82: 0 | H82: 1 | I82: 28 | J82: 1 | K82: -0.033333333 | L82: 0 | M82: 0.975 | N82: 0.5 | O82: not_distinguished
A83: two_opposite | B83: h3_vz-1.5_w2_d0.3 | C83: mechanism | D83: realloc_only | E83: 30 | F83: 0 | G83: 0 | H83: 0 | I83: 30 | J83: 0 | K83: 0 | N83: 1 | O83: no_discordant_pairs
A84: two_opposite | B84: h3_vz-1.5_w6_d0.11 | C84: mechanism | D84: realloc_only | E84: 30 | F84: 0 | G84: 0 | H84: 0 | I84: 30 | J84: 0 | K84: 0 | N84: 1 | O84: no_discordant_pairs
A85: two_opposite | B85: h3_vz-1.5_w6_d0.3 | C85: mechanism | D85: realloc_only | E85: 30 | F85: 0 | G85: 0 | H85: 0 | I85: 30 | J85: 0 | K85: 0 | N85: 1 | O85: no_discordant_pairs
A86: two_opposite | B86: h3_vz0_w2_d0.11 | C86: mechanism | D86: realloc_only | E86: 30 | F86: 4 | G86: 0 | H86: 1 | I86: 25 | J86: 1 | K86: -0.033333333 | L86: 0 | M86: 0.975 | N86: 0.5 | O86: not_distinguished
A87: two_opposite | B87: h3_vz0_w2_d0.3 | C87: mechanism | D87: realloc_only | E87: 30 | F87: 0 | G87: 0 | H87: 0 | I87: 30 | J87: 0 | K87: 0 | N87: 1 | O87: no_discordant_pairs
A88: two_opposite | B88: h3_vz0_w6_d0.11 | C88: mechanism | D88: realloc_only | E88: 30 | F88: 0 | G88: 0 | H88: 0 | I88: 30 | J88: 0 | K88: 0 | N88: 1 | O88: no_discordant_pairs
A89: two_opposite | B89: h3_vz0_w6_d0.3 | C89: mechanism | D89: realloc_only | E89: 30 | F89: 0 | G89: 0 | H89: 0 | I89: 30 | J89: 0 | K89: 0 | N89: 1 | O89: no_discordant_pairs
A90: two_opposite | B90: h6_vz-1.5_w2_d0.11 | C90: mechanism | D90: realloc_only | E90: 30 | F90: 3 | G90: 0 | H90: 4 | I90: 23 | J90: 4 | K90: -0.13333333 | L90: 0 | M90: 0.60236464 | N90: 0.0625 | O90: not_distinguished
A91: two_opposite | B91: h6_vz-1.5_w2_d0.3 | C91: mechanism | D91: realloc_only | E91: 30 | F91: 0 | G91: 0 | H91: 0 | I91: 30 | J91: 0 | K91: 0 | N91: 1 | O91: no_discordant_pairs
A92: two_opposite | B92: h6_vz-1.5_w6_d0.11 | C92: mechanism | D92: realloc_only | E92: 30 | F92: 0 | G92: 0 | H92: 0 | I92: 30 | J92: 0 | K92: 0 | N92: 1 | O92: no_discordant_pairs
A93: two_opposite | B93: h6_vz-1.5_w6_d0.3 | C93: mechanism | D93: realloc_only | E93: 30 | F93: 0 | G93: 0 | H93: 0 | I93: 30 | J93: 0 | K93: 0 | N93: 1 | O93: no_discordant_pairs
A94: two_opposite | B94: h6_vz0_w2_d0.11 | C94: mechanism | D94: realloc_only | E94: 30 | F94: 4 | G94: 0 | H94: 10 | I94: 16 | J94: 10 | K94: -0.33333333 | L94: 0 | M94: 0.30849711 | N94: 0.0009765625 | O94: b_superior
A95: two_opposite | B95: h6_vz0_w2_d0.3 | C95: mechanism | D95: realloc_only | E95: 30 | F95: 0 | G95: 0 | H95: 1 | I95: 29 | J95: 1 | K95: -0.033333333 | L95: 0 | M95: 0.975 | N95: 0.5 | O95: not_distinguished
A96: two_opposite | B96: h6_vz0_w6_d0.11 | C96: mechanism | D96: realloc_only | E96: 30 | F96: 0 | G96: 0 | H96: 0 | I96: 30 | J96: 0 | K96: 0 | N96: 1 | O96: no_discordant_pairs
A97: two_opposite | B97: h6_vz0_w6_d0.3 | C97: mechanism | D97: realloc_only | E97: 30 | F97: 0 | G97: 0 | H97: 0 | I97: 30 | J97: 0 | K97: 0 | N97: 1 | O97: no_discordant_pairs

Sheet A vs A2 Paired
A1: class | B1: cell | C1: action | D1: a | E1: b | F1: n | G1: both_safe | H1: only_a | I1: only_b | J1: neither | K1: discordant | L1: delta | M1: pi_lower | N1: pi_upper | O1: midp | P1: verdict
A2: one_out | B2: h1.5_vz-1.5_w2_d0.11 | C2: mechanism | D2: a | E2: a2 | F2: 30 | G2: 2 | H2: 0 | I2: 0 | J2: 28 | K2: 0 | L2: 0 | O2: 1 | P2: no_discordant_pairs
A3: one_out | B3: h1.5_vz-1.5_w2_d0.11 | C3: realloc_only | D3: a | E3: a2 | F3: 30 | G3: 2 | H3: 0 | I3: 0 | J3: 28 | K3: 0 | L3: 0 | O3: 1 | P3: no_discordant_pairs
A4: one_out | B4: h1.5_vz-1.5_w2_d0.3 | C4: mechanism | D4: a | E4: a2 | F4: 300 | G4: 0 | H4: 0 | I4: 0 | J4: 300 | K4: 0 | L4: 0 | O4: 1 | P4: no_discordant_pairs
A5: one_out | B5: h1.5_vz-1.5_w2_d0.3 | C5: realloc_only | D5: a | E5: a2 | F5: 300 | G5: 0 | H5: 0 | I5: 0 | J5: 300 | K5: 0 | L5: 0 | O5: 1 | P5: no_discordant_pairs
A6: one_out | B6: h1.5_vz-1.5_w6_d0.11 | C6: mechanism | D6: a | E6: a2 | F6: 30 | G6: 0 | H6: 0 | I6: 0 | J6: 30 | K6: 0 | L6: 0 | O6: 1 | P6: no_discordant_pairs
A7: one_out | B7: h1.5_vz-1.5_w6_d0.11 | C7: realloc_only | D7: a | E7: a2 | F7: 30 | G7: 0 | H7: 0 | I7: 0 | J7: 30 | K7: 0 | L7: 0 | O7: 1 | P7: no_discordant_pairs
A8: one_out | B8: h1.5_vz-1.5_w6_d0.3 | C8: mechanism | D8: a | E8: a2 | F8: 30 | G8: 0 | H8: 0 | I8: 0 | J8: 30 | K8: 0 | L8: 0 | O8: 1 | P8: no_discordant_pairs
A9: one_out | B9: h1.5_vz-1.5_w6_d0.3 | C9: realloc_only | D9: a | E9: a2 | F9: 30 | G9: 0 | H9: 0 | I9: 0 | J9: 30 | K9: 0 | L9: 0 | O9: 1 | P9: no_discordant_pairs
A10: one_out | B10: h1.5_vz0_w2_d0.11 | C10: mechanism | D10: a | E10: a2 | F10: 30 | G10: 10 | H10: 0 | I10: 0 | J10: 20 | K10: 0 | L10: 0 | O10: 1 | P10: no_discordant_pairs
A11: one_out | B11: h1.5_vz0_w2_d0.11 | C11: realloc_only | D11: a | E11: a2 | F11: 30 | G11: 11 | H11: 0 | I11: 0 | J11: 19 | K11: 0 | L11: 0 | O11: 1 | P11: no_discordant_pairs
A12: one_out | B12: h1.5_vz0_w2_d0.3 | C12: mechanism | D12: a | E12: a2 | F12: 30 | G12: 0 | H12: 0 | I12: 0 | J12: 30 | K12: 0 | L12: 0 | O12: 1 | P12: no_discordant_pairs
A13: one_out | B13: h1.5_vz0_w2_d0.3 | C13: realloc_only | D13: a | E13: a2 | F13: 30 | G13: 0 | H13: 0 | I13: 0 | J13: 30 | K13: 0 | L13: 0 | O13: 1 | P13: no_discordant_pairs
... A26: one_out | B26: h3_vz0_w2_d0.11 | C26: mechanism | D26: a | E26: a2 | F26: 30 | G26: 9 | H26: 0 | I26: 0 | J26: 21 | K26: 0 | L26: 0 | O26: 1 | P26: no_discordant_pairs
A27: one_out | B27: h3_vz0_w2_d0.11 | C27: realloc_only | D27: a | E27: a2 | F27: 30 | G27: 10 | H27: 1 | I27: 0 | J27: 19 | K27: 1 | L27: 0.033333333 | M27: 0.025 | N27: 1 | O27: 0.5 | P27: not_distinguished
A28: one_out | B28: h3_vz0_w2_d0.3 | C28: mechanism | D28: a | E28: a2 | F28: 30 | G28: 3 | H28: 0 | I28: 0 | J28: 27 | K28: 0 | L28: 0 | O28: 1 | P28: no_discordant_pairs
A29: one_out | B29: h3_vz0_w2_d0.3 | C29: realloc_only | D29: a | E29: a2 | F29: 30 | G29: 7 | H29: 0 | I29: 0 | J29: 23 | K29: 0 | L29: 0 | O29: 1 | P29: no_discordant_pairs
A30: one_out | B30: h3_vz0_w6_d0.11 | C30: mechanism | D30: a | E30: a2 | F30: 300 | G30: 0 | H30: 0 | I30: 0 | J30: 300 | K30: 0 | L30: 0 | O30: 1 | P30: no_discordant_pairs
A31: one_out | B31: h3_vz0_w6_d0.11 | C31: realloc_only | D31: a | E31: a2 | F31: 300 | G31: 0 | H31: 0 | I31: 0 | J31: 300 | K31: 0 | L31: 0 | O31: 1 | P31: no_discordant_pairs
A32: one_out | B32: h3_vz0_w6_d0.3 | C32: mechanism | D32: a | E32: a2 | F32: 30 | G32: 0 | H32: 0 | I32: 0 | J32: 30 | K32: 0 | L32: 0 | O32: 1 | P32: no_discordant_pairs
A33: one_out | B33: h3_vz0_w6_d0.3 | C33: realloc_only | D33: a | E33: a2 | F33: 30 | G33: 0 | H33: 0 | I33: 0 | J33: 30 | K33: 0 | L33: 0 | O33: 1 | P33: no_discordant_pairs
A34: one_out | B34: h6_vz-1.5_w2_d0.11 | C34: mechanism | D34: a | E34: a2 | F34: 30 | G34: 11 | H34: 0 | I34: 0 | J34: 19 | K34: 0 | L34: 0 | O34: 1 | P34: no_discordant_pairs
A35: one_out | B35: h6_vz-1.5_w2_d0.11 | C35: realloc_only | D35: a | E35: a2 | F35: 30 | G35: 15 | H35: 0 | I35: 0 | J35: 15 | K35: 0 | L35: 0 | O35: 1 | P35: no_discordant_pairs
A36: one_out | B36: h6_vz-1.5_w2_d0.3 | C36: mechanism | D36: a | E36: a2 | F36: 30 | G36: 11 | H36: 0 | I36: 0 | J36: 19 | K36: 0 | L36: 0 | O36: 1 | P36: no_discordant_pairs
A37: one_out | B37: h6_vz-1.5_w2_d0.3 | C37: realloc_only | D37: a | E37: a2 | F37: 30 | G37: 16 | H37: 0 | I37: 0 | J37: 14 | K37: 0 | L37: 0 | O37: 1 | P37: no_discordant_pairs
A38: one_out | B38: h6_vz-1.5_w6_d0.11 | C38: mechanism | D38: a | E38: a2 | F38: 30 | G38: 0 | H38: 0 | I38: 0 | J38: 30 | K38: 0 | L38: 0 | O38: 1 | P38: no_discordant_pairs
A39: one_out | B39: h6_vz-1.5_w6_d0.11 | C39: realloc_only | D39: a | E39: a2 | F39: 30 | G39: 0 | H39: 0 | I39: 0 | J39: 30 | K39: 0 | L39: 0 | O39: 1 | P39: no_discordant_pairs
... A162: two_opposite | B162: h3_vz-1.5_w2_d0.11 | C162: mechanism | D162: a | E162: a2 | F162: 30 | G162: 1 | H162: 0 | I162: 0 | J162: 29 | K162: 0 | L162: 0 | O162: 1 | P162: no_discordant_pairs
A163: two_opposite | B163: h3_vz-1.5_w2_d0.11 | C163: realloc_only | D163: a | E163: a2 | F163: 30 | G163: 2 | H163: 1 | I163: 0 | J163: 27 | K163: 1 | L163: 0.033333333 | M163: 0.025 | N163: 1 | O163: 0.5 | P163: not_distinguished
A164: two_opposite | B164: h3_vz-1.5_w2_d0.3 | C164: mechanism | D164: a | E164: a2 | F164: 30 | G164: 0 | H164: 0 | I164: 0 | J164: 30 | K164: 0 | L164: 0 | O164: 1 | P164: no_discordant_pairs
A165: two_opposite | B165: h3_vz-1.5_w2_d0.3 | C165: realloc_only | D165: a | E165: a2 | F165: 30 | G165: 0 | H165: 0 | I165: 0 | J165: 30 | K165: 0 | L165: 0 | O165: 1 | P165: no_discordant_pairs
A166: two_opposite | B166: h3_vz-1.5_w6_d0.11 | C166: mechanism | D166: a | E166: a2 | F166: 30 | G166: 0 | H166: 0 | I166: 0 | J166: 30 | K166: 0 | L166: 0 | O166: 1 | P166: no_discordant_pairs
A167: two_opposite | B167: h3_vz-1.5_w6_d0.11 | C167: realloc_only | D167: a | E167: a2 | F167: 30 | G167: 0 | H167: 0 | I167: 0 | J167: 30 | K167: 0 | L167: 0 | O167: 1 | P167: no_discordant_pairs
A168: two_opposite | B168: h3_vz-1.5_w6_d0.3 | C168: mechanism | D168: a | E168: a2 | F168: 30 | G168: 0 | H168: 0 | I168: 0 | J168: 30 | K168: 0 | L168: 0 | O168: 1 | P168: no_discordant_pairs
A169: two_opposite | B169: h3_vz-1.5_w6_d0.3 | C169: realloc_only | D169: a | E169: a2 | F169: 30 | G169: 0 | H169: 0 | I169: 0 | J169: 30 | K169: 0 | L169: 0 | O169: 1 | P169: no_discordant_pairs
A170: two_opposite | B170: h3_vz0_w2_d0.11 | C170: mechanism | D170: a | E170: a2 | F170: 30 | G170: 4 | H170: 0 | I170: 0 | J170: 26 | K170: 0 | L170: 0 | O170: 1 | P170: no_discordant_pairs
A171: two_opposite | B171: h3_vz0_w2_d0.11 | C171: realloc_only | D171: a | E171: a2 | F171: 30 | G171: 5 | H171: 1 | I171: 0 | J171: 24 | K171: 1 | L171: 0.033333333 | M171: 0.025 | N171: 1 | O171: 0.5 | P171: not_distinguished
A172: two_opposite | B172: h3_vz0_w2_d0.3 | C172: mechanism | D172: a | E172: a2 | F172: 30 | G172: 0 | H172: 0 | I172: 0 | J172: 30 | K172: 0 | L172: 0 | O172: 1 | P172: no_discordant_pairs
A173: two_opposite | B173: h3_vz0_w2_d0.3 | C173: realloc_only | D173: a | E173: a2 | F173: 30 | G173: 0 | H173: 0 | I173: 0 | J173: 30 | K173: 0 | L173: 0 | O173: 1 | P173: no_discordant_pairs
A174: two_opposite | B174: h3_vz0_w6_d0.11 | C174: mechanism | D174: a | E174: a2 | F174: 30 | G174: 0 | H174: 0 | I174: 0 | J174: 30 | K174: 0 | L174: 0 | O174: 1 | P174: no_discordant_pairs
A175: two_opposite | B175: h3_vz0_w6_d0.11 | C175: realloc_only | D175: a | E175: a2 | F175: 30 | G175: 0 | H175: 0 | I175: 0 | J175: 30 | K175: 0 | L175: 0 | O175: 1 | P175: no_discordant_pairs
A176: two_opposite | B176: h3_vz0_w6_d0.3 | C176: mechanism | D176: a | E176: a2 | F176: 30 | G176: 0 | H176: 0 | I176: 0 | J176: 30 | K176: 0 | L176: 0 | O176: 1 | P176: no_discordant_pairs
A177: two_opposite | B177: h3_vz0_w6_d0.3 | C177: realloc_only | D177: a | E177: a2 | F177: 30 | G177: 0 | H177: 0 | I177: 0 | J177: 30 | K177: 0 | L177: 0 | O177: 1 | P177: no_discordant_pairs
A178: two_opposite | B178: h6_vz-1.5_w2_d0.11 | C178: mechanism | D178: a | E178: a2 | F178: 30 | G178: 3 | H178: 3 | I178: 0 | J178: 24 | K178: 3 | L178: 0.1 | M178: 0.29240177 | N178: 1 | O178: 0.125 | P178: not_distinguished
A179: two_opposite | B179: h6_vz-1.5_w2_d0.11 | C179: realloc_only | D179: a | E179: a2 | F179: 30 | G179: 7 | H179: 3 | I179: 0 | J179: 20 | K179: 3 | L179: 0.1 | M179: 0.29240177 | N179: 1 | O179: 0.125 | P179: not_distinguished
A180: two_opposite | B180: h6_vz-1.5_w2_d0.3 | C180: mechanism | D180: a | E180: a2 | F180: 30 | G180: 0 | H180: 0 | I180: 0 | J180: 30 | K180: 0 | L180: 0 | O180: 1 | P180: no_discordant_pairs
A181: two_opposite | B181: h6_vz-1.5_w2_d0.3 | C181: realloc_only | D181: a | E181: a2 | F181: 30 | G181: 0 | H181: 0 | I181: 0 | J181: 30 | K181: 0 | L181: 0 | O181: 1 | P181: no_discordant_pairs
A182: two_opposite | B182: h6_vz-1.5_w6_d0.11 | C182: mechanism | D182: a | E182: a2 | F182: 30 | G182: 0 | H182: 0 | I182: 0 | J182: 30 | K182: 0 | L182: 0 | O182: 1 | P182: no_discordant_pairs
A183: two_opposite | B183: h6_vz-1.5_w6_d0.11 | C183: realloc_only | D183: a | E183: a2 | F183: 30 | G183: 0 | H183: 0 | I183: 0 | J183: 30 | K183: 0 | L183: 0 | O183: 1 | P183: no_discordant_pairs
A184: two_opposite | B184: h6_vz-1.5_w6_d0.3 | C184: mechanism | D184: a | E184: a2 | F184: 30 | G184: 0 | H184: 0 | I184: 0 | J184: 30 | K184: 0 | L184: 0 | O184: 1 | P184: no_discordant_pairs
A185: two_opposite | B185: h6_vz-1.5_w6_d0.3 | C185: realloc_only | D185: a | E185: a2 | F185: 30 | G185: 0 | H185: 0 | I185: 0 | J185: 30 | K185: 0 | L185: 0 | O185: 1 | P185: no_discordant_pairs
A186: two_opposite | B186: h6_vz0_w2_d0.11 | C186: mechanism | D186: a | E186: a2 | F186: 30 | G186: 4 | H186: 4 | I186: 0 | J186: 22 | K186: 4 | L186: 0.13333333 | M186: 0.39763536 | N186: 1 | O186: 0.0625 | P186: not_distinguished
A187: two_opposite | B187: h6_vz0_w2_d0.11 | C187: realloc_only | D187: a | E187: a2 | F187: 30 | G187: 14 | H187: 1 | I187: 0 | J187: 15 | K187: 1 | L187: 0.033333333 | M187: 0.025 | N187: 1 | O187: 0.5 | P187: not_distinguished
A188: two_opposite | B188: h6_vz0_w2_d0.3 | C188: mechanism | D188: a | E188: a2 | F188: 30 | G188: 0 | H188: 0 | I188: 0 | J188: 30 | K188: 0 | L188: 0 | O188: 1 | P188: no_discordant_pairs
A189: two_opposite | B189: h6_vz0_w2_d0.3 | C189: realloc_only | D189: a | E189: a2 | F189: 30 | G189: 1 | H189: 1 | I189: 0 | J189: 28 | K189: 1 | L189: 0.033333333 | M189: 0.025 | N189: 1 | O189: 0.5 | P189: not_distinguished
A190: two_opposite | B190: h6_vz0_w6_d0.11 | C190: mechanism | D190: a | E190: a2 | F190: 30 | G190: 0 | H190: 0 | I190: 0 | J190: 30 | K190: 0 | L190: 0 | O190: 1 | P190: no_discordant_pairs
A191: two_opposite | B191: h6_vz0_w6_d0.11 | C191: realloc_only | D191: a | E191: a2 | F191: 30 | G191: 0 | H191: 0 | I191: 0 | J191: 30 | K191: 0 | L191: 0 | O191: 1 | P191: no_discordant_pairs
A192: two_opposite | B192: h6_vz0_w6_d0.3 | C192: mechanism | D192: a | E192: a2 | F192: 30 | G192: 0 | H192: 0 | I192: 0 | J192: 30 | K192: 0 | L192: 0 | O192: 1 | P192: no_discordant_pairs
A193: two_opposite | B193: h6_vz0_w6_d0.3 | C193: realloc_only | D193: a | E193: a2 | F193: 30 | G193: 0 | H193: 0 | I193: 0 | J193: 30 | K193: 0 | L193: 0 | O193: 1 | P193: no_discordant_pairs

Sheet Package Rankings
A1: study | B1: class | C1: cell | D1: best_action | E1: best_p_safe_95_lower | F1: ambiguous_with
A2: a | B2: one_out | C2: h1.5_vz-1.5_w2_d0.11 | D2: realloc_only | E2: 0.011975801 | F2: ["mechanism"]
A3: a | B3: one_out | C3: h1.5_vz-1.5_w2_d0.3 | D3: realloc_only | E3: 0 | F3: ["mechanism", "parachute"]
A4: a | B4: one_out | C4: h1.5_vz-1.5_w6_d0.11 | D4: realloc_only | E4: 0 | F4: ["mechanism", "parachute"]
A5: a | B5: one_out | C5: h1.5_vz-1.5_w6_d0.3 | D5: realloc_only | E5: 0 | F5: ["mechanism", "parachute"]
A6: a | B6: one_out | C6: h1.5_vz0_w2_d0.11 | D6: realloc_only | E6: 0.22105945 | F6: ["mechanism"]
A7: a | B7: one_out | C7: h1.5_vz0_w2_d0.3 | D7: realloc_only | E7: 0 | F7: ["mechanism", "parachute"]
A8: a | B8: one_out | C8: h1.5_vz0_w6_d0.11 | D8: realloc_only | E8: 0 | F8: ["mechanism", "parachute"]
A9: a | B9: one_out | C9: h1.5_vz0_w6_d0.3 | D9: realloc_only | E9: 0 | F9: ["mechanism", "parachute"]
A10: a | B10: one_out | C10: h3_vz-1.5_w2_d0.11 | D10: realloc_only | E10: 0.16632596 | F10: ["mechanism"]
A11: a | B11: one_out | C11: h3_vz-1.5_w2_d0.3 | D11: realloc_only | E11: 0 | F11: ["mechanism", "parachute"]
A12: a | B12: one_out | C12: h3_vz-1.5_w6_d0.11 | D12: realloc_only | E12: 0 | F12: ["mechanism", "parachute"]
A13: a | B13: one_out | C13: h3_vz-1.5_w6_d0.3 | D13: realloc_only | E13: 0 | F13: ["mechanism", "parachute"]
... A193: a2 | B193: two_opposite | C193: h6_vz0_w6_d0.3 | D193: realloc_only | E193: 0 | F193: ["mechanism", "parachute"]

Sheet Primary Comparisons
A1: study | B1: class | C1: cell | D1: mechanism_lower | E1: realloc_upper | F1: mechanism_dominates | G1: realloc_dominates | H1: both_actions_fail
A2: a | B2: one_out | C2: h1.5_vz-1.5_w2_d0.3 | D2: 0 | E2: 0.0099360819 | F2: FALSE | G2: FALSE | H2: TRUE
A3: a | B3: one_out | C3: h3_vz0_w6_d0.11 | D3: 0 | E3: 0.0099360819 | F3: FALSE | G3: FALSE | H3: TRUE
A4: a | B4: two_adjacent | C4: h1.5_vz-1.5_w2_d0.3 | D4: 0 | E4: 0.0099360819 | F4: FALSE | G4: FALSE | H4: TRUE
A5: a | B5: two_adjacent | C5: h3_vz0_w6_d0.11 | D5: 0 | E5: 0.0099360819 | F5: FALSE | G5: FALSE | H5: TRUE
A6: a2 | B6: one_out | C6: h1.5_vz-1.5_w2_d0.3 | D6: 0 | E6: 0.0099360819 | F6: FALSE | G6: FALSE | H6: TRUE
A7: a2 | B7: one_out | C7: h3_vz0_w6_d0.11 | D7: 0 | E7: 0.0099360819 | F7: FALSE | G7: FALSE | H7: TRUE
A8: a2 | B8: two_adjacent | C8: h1.5_vz-1.5_w2_d0.3 | D8: 0 | E8: 0.0099360819 | F8: FALSE | G8: FALSE | H8: TRUE
A9: a2 | B9: two_adjacent | C9: h3_vz0_w6_d0.11 | D9: 0 | E9: 0.0099360819 | F9: FALSE | G9: FALSE | H9: TRUE

Sheet Simulation Metadata
A1: source | B1: field | C1: value | D1: value_type
A2: Data/survivable_set_results.json | B2: note | C2: SIMULATION-ONLY PREDICTION (Study A/B). Mechanism and parachute action parameters are EST owner inputs (OQ-010); the bench/drop gates (Study C) must run before any survivable-set claim leaves this file. Preregistration: docs/specs/survivable-set/design.md + design-a2.md | D2: str
A3: Data/survivable_set_results.json | B3: preregistration.landing_criterion_bare | C3: [2.0, 29.999999999999996] | D3: str
A4: Data/survivable_set_results.json | B4: preregistration.landing_criterion_guarded_EST | C4: [2.5, 59.99999999999999] | D4: str
A5: Data/survivable_set_results.json | B5: preregistration.sensitivity.strict | C5: [1.5, 20.0] | D5: str
A6: Data/survivable_set_results.json | B6: preregistration.sensitivity.lenient | C6: [3.0, 45.0] | D6: str
A7: Data/survivable_set_results.json | B7: preregistration.mech_mass_g_EST | C7: 16 | D7: float
A8: Data/survivable_set_results.json | B8: preregistration.mech_mass_frac | C8: 0.11794191 | D8: float
A9: Data/survivable_set_results.json | B9: preregistration.mech_inertia_frac_EST | C9: 0.3 | D9: float
A10: Data/survivable_set_results.json | B10: preregistration.parachute_EST.terminal_m_s | C10: 1.8 | D10: float
A11: Data/survivable_set_results.json | B11: preregistration.parachute_EST.deploy_s | C11: 0.8 | D11: float
A12: Data/survivable_set_results.json | B12: preregistration.a2_yaw_drag_n_m_s2_EST | C12: 6e-06 | D12: float
A13: Data/survivable_set_results.json | B13: preregistration.descent_rate_m_s | C13: 1 | D13: float
A14: Data/survivable_set_results.json | B14: preregistration.init_tilt_max_deg | C14: 30 | D14: float
A15: Data/survivable_set_results.json | B15: preregistration.primary_cells | C15: ["h3_vz0_w6_d0.11", "h1.5_vz-1.5_w2_d0.3"] | D15: str
A16: Data/survivable_set_results.json | B16: preregistration.primary_classes | C16: ["one_out", "two_adjacent"] | D16: str
A17: Data/survivable_set_results.json | B17: preregistration.trials.exploratory | C17: 30 | D17: int
A18: Data/survivable_set_results.json | B18: preregistration.trials.primary | C18: 300 | D18: int
A19: Data/survivable_set_results.json | B19: preregistration.trials.parachute | C19: 2000 | D19: int
A20: Data/survivable_set_results.json | B20: preregistration.base_seed | C20: 20260916 | D20: int
A21: Data/survivable_set_results.json | B21: preregistration.scenario | C21: release_startup | D21: str
A22: Data/survivable_set_results.json | B22: preregistration.scenario_note | C22: All motors are off for detection+spool latency, then the controller engages: a RELEASE/STARTUP transient, NOT an in-flight failure in which healthy motors keep running until detection. Every rotor-out result here is conditional on that reading (critique C04). | D22: str
A23: Data/survivable_set_results.json | B23: preregistration.machinery_rev | C23: 2026-09-16: cascaded torque-priority allocation, balanced collective ceiling (0.9 airmode reserve in allocation mode), arrest-first descent; supersedes the single-pass pinv allocation of the first committed sweep — see design-a2.md | D23: str
A24: Data/survivable_set_results.json | B24: variant | C24: a | D24: str
A25: Data/survivable_set_results.json | B25: kill_criterion.mechanism_justified | C25: FALSE | D25: bool
A26: Data/survivable_set_results.json | B26: kill_criterion.verdict | C26: KILL: mechanism does not enlarge the survivable set beyond Monte Carlo uncertainty — redirect to the policy alone | D26: str
A27: Data/survivable_set_results_a2.json | B27: note | C27: SIMULATION-ONLY PREDICTION (Study A2/B). Mechanism and parachute action parameters are EST owner inputs (OQ-010); the bench/drop gates (Study C) must run before any survivable-set claim leaves this file. Preregistration: docs/specs/survivable-set/design.md + design-a2.md | D27: str
A28: Data/survivable_set_results_a2.json | B28: preregistration.landing_criterion_bare | C28: [2.0, 29.999999999999996] | D28: str
A29: Data/survivable_set_results_a2.json | B29: preregistration.landing_criterion_guarded_EST | C29: [2.5, 59.99999999999999] | D29: str
A30: Data/survivable_set_results_a2.json | B30: preregistration.sensitivity.strict | C30: [1.5, 20.0] | D30: str
A31: Data/survivable_set_results_a2.json | B31: preregistration.sensitivity.lenient | C31: [3.0, 45.0] | D31: str
A32: Data/survivable_set_results_a2.json | B32: preregistration.mech_mass_g_EST | C32: 16 | D32: float
A33: Data/survivable_set_results_a2.json | B33: preregistration.mech_mass_frac | C33: 0.11794191 | D33: float
A34: Data/survivable_set_results_a2.json | B34: preregistration.mech_inertia_frac_EST | C34: 0.3 | D34: float
A35: Data/survivable_set_results_a2.json | B35: preregistration.parachute_EST.terminal_m_s | C35: 1.8 | D35: float
A36: Data/survivable_set_results_a2.json | B36: preregistration.parachute_EST.deploy_s | C36: 0.8 | D36: float
A37: Data/survivable_set_results_a2.json | B37: preregistration.a2_yaw_drag_n_m_s2_EST | C37: 6e-06 | D37: float
A38: Data/survivable_set_results_a2.json | B38: preregistration.descent_rate_m_s | C38: 1 | D38: float
A39: Data/survivable_set_results_a2.json | B39: preregistration.init_tilt_max_deg | C39: 30 | D39: float
A40: Data/survivable_set_results_a2.json | B40: preregistration.primary_cells | C40: ["h3_vz0_w6_d0.11", "h1.5_vz-1.5_w2_d0.3"] | D40: str
A41: Data/survivable_set_results_a2.json | B41: preregistration.primary_classes | C41: ["one_out", "two_adjacent"] | D41: str
A42: Data/survivable_set_results_a2.json | B42: preregistration.trials.exploratory | C42: 30 | D42: int
A43: Data/survivable_set_results_a2.json | B43: preregistration.trials.primary | C43: 300 | D43: int
A44: Data/survivable_set_results_a2.json | B44: preregistration.trials.parachute | C44: 2000 | D44: int
A45: Data/survivable_set_results_a2.json | B45: preregistration.base_seed | C45: 20260916 | D45: int
A46: Data/survivable_set_results_a2.json | B46: preregistration.scenario | C46: release_startup | D46: str
A47: Data/survivable_set_results_a2.json | B47: preregistration.scenario_note | C47: All motors are off for detection+spool latency, then the controller engages: a RELEASE/STARTUP transient, NOT an in-flight failure in which healthy motors keep running until detection. Every rotor-out result here is conditional on that reading (critique C04). | D47: str
A48: Data/survivable_set_results_a2.json | B48: preregistration.machinery_rev | C48: 2026-09-16: cascaded torque-priority allocation, balanced collective ceiling (0.9 airmode reserve in allocation mode), arrest-first descent; supersedes the single-pass pinv allocation of the first committed sweep — see design-a2.md | D48: str
A49: Data/survivable_set_results_a2.json | B49: variant | C49: a2 | D49: str
A50: Data/survivable_set_results_a2.json | B50: kill_criterion.mechanism_justified | C50: FALSE | D50: bool
A51: Data/survivable_set_results_a2.json | B51: kill_criterion.verdict | C51: KILL: mechanism does not enlarge the survivable set beyond Monte Carlo uncertainty — redirect to the policy alone | D51: str
A52: Data/scenario-diagnostic/scenario_diagnostic.json | B52: study | C52: DR-SS-SCENARIO-01 | D52: str
A53: Data/scenario-diagnostic/scenario_diagnostic.json | B53: status | C53: EXPLORATORY DIAGNOSTIC — not a full-grid verdict | D53: str
A54: Data/scenario-diagnostic/scenario_diagnostic.json | B54: registration | C54: docs/specs/survivable-set/scenario-contract.md | D54: str
A55: Data/scenario-diagnostic/scenario_diagnostic.json | B55: note | C55: Simulation on the historical design profile under an idealized complete rotor effectiveness loss (R01). Not measured V995 performance. One frozen controller bundle across arms, so this does NOT estimate feedforward or drag effects. | D55: str
A56: Data/scenario-diagnostic/scenario_diagnostic.json | B56: commit | C56: a0b9aac6c532902701b8bca7dcc7706d30b494a2 | D56: str
A57: Data/scenario-diagnostic/scenario_diagnostic.json | B57: python | C57: 3.11.8 | D57: str
A58: Data/scenario-diagnostic/scenario_diagnostic.json | B58: numpy | C58: 2.1.1 | D58: str
A59: Data/scenario-diagnostic/scenario_diagnostic.json | B59: seconds | C59: 36.7 | D59: float
A60: Data/scenario-diagnostic/scenario_diagnostic.json | B60: design.arms | C60: ["release_startup", "in_flight_hold_matched", "in_flight_hold_immediate"] | D60: str
A61: Data/scenario-diagnostic/scenario_diagnostic.json | B61: design.classes | C61: ["one_out", "two_adjacent"] | D61: str
A62: Data/scenario-diagnostic/scenario_diagnostic.json | B62: design.cells | C62: ["h3_vz0_w6_d0.11", "h1.5_vz-1.5_w2_d0.3"] | D62: str
A63: Data/scenario-diagnostic/scenario_diagnostic.json | B63: design.packages | C63: ["mechanism", "realloc_only"] | D63: str
A64: Data/scenario-diagnostic/scenario_diagnostic.json | B64: design.pairs | C64: 12 | D64: int
A65: Data/scenario-diagnostic/scenario_diagnostic.json | B65: design.trajectories | C65: 288 | D65: int
A66: Data/scenario-diagnostic/scenario_diagnostic.json | B66: design.base_seed | C66: 20260925 | D66: int
A67: Data/scenario-diagnostic/scenario_diagnostic.json | B67: status_counts.contact | C67: 288 | D67: int
A68: Data/survivable_set_convergence.json | B68: max_impact_speed_delta_m_s | C68: 0.0043528248 | D68: float
A69: Data/survivable_set_convergence.json | B69: landed_agreement | C69: TRUE | D69: bool
A70: Data/survivable_set_convergence.json | B70: note | C70: Integrator diagnostic: production dt=5e-4 vs halved. Deltas small against the 0.5 m/s spacing of the criterion variants support the dt choice; a large delta would demand a smaller production step. | D70: str
A71: Data/monte_carlo_results.json | B71: scenario.as-toleranced_cg5mm.label | C71: as-toleranced_cg5mm | D71: str
A72: Data/monte_carlo_results.json | B72: scenario.as-toleranced_cg5mm.init_tilt_deg | C72: 60 | D72: float
A73: Data/monte_carlo_results.json | B73: scenario.as-toleranced_cg5mm.dispersions.mass_x | C73: [0.95, 1.1] | D73: str
A74: Data/monte_carlo_results.json | B74: scenario.as-toleranced_cg5mm.dispersions.inertia_x | C74: [0.85, 1.25] | D74: str
A75: Data/monte_carlo_results.json | B75: scenario.as-toleranced_cg5mm.dispersions.torque_x | C75: [0.85, 1.1] | D75: str
A76: Data/monte_carlo_results.json | B76: scenario.as-toleranced_cg5mm.dispersions.thrust_x | C76: [0.85, 1.05] | D76: str
A77: Data/monte_carlo_results.json | B77: scenario.as-toleranced_cg5mm.dispersions.latency_x | C77: [0.8, 1.5] | D77: str
A78: Data/monte_carlo_results.json | B78: scenario.as-toleranced_cg5mm.dispersions.cg_offset_max_m | C78: 0.005 | D78: float
A79: Data/monte_carlo_results.json | B79: scenario.as-toleranced_cg5mm.dispersions.torque_bias_max_frac | C79: 0.1 | D79: float
A80: Data/monte_carlo_results.json | B80: scenario.as-toleranced_cg5mm.dispersions.gyro_noise_rad_s | C80: 0.02 | D80: float
A81: Data/monte_carlo_results.json | B81: scenario.as-toleranced_cg5mm.dispersions.tilt_noise_deg | C81: 2 | D81: float
A82: Data/monte_carlo_results.json | B82: scenario.as-toleranced_cg5mm.dispersions.thrust_sag_x | C82: [0.9, 1.0] | D82: str
A83: Data/monte_carlo_results.json | B83: scenario.as-toleranced_cg5mm.dispersions.authority_model | C83: placeholder | D83: str
A84: Data/monte_carlo_results.json | B84: scenario.as-toleranced_cg5mm.dispersions.mixer_arm_m | D84: null
A85: Data/monte_carlo_results.json | B85: scenario.balance-controlled_cg1mm.label | C85: balance-controlled_cg1mm | D85: str
A86: Data/monte_carlo_results.json | B86: scenario.balance-controlled_cg1mm.init_tilt_deg | C86: 60 | D86: float
A87: Data/monte_carlo_results.json | B87: scenario.balance-controlled_cg1mm.dispersions.mass_x | C87: [0.95, 1.1] | D87: str
A88: Data/monte_carlo_results.json | B88: scenario.balance-controlled_cg1mm.dispersions.inertia_x | C88: [0.85, 1.25] | D88: str
A89: Data/monte_carlo_results.json | B89: scenario.balance-controlled_cg1mm.dispersions.torque_x | C89: [0.85, 1.1] | D89: str
A90: Data/monte_carlo_results.json | B90: scenario.balance-controlled_cg1mm.dispersions.thrust_x | C90: [0.85, 1.05] | D90: str
A91: Data/monte_carlo_results.json | B91: scenario.balance-controlled_cg1mm.dispersions.latency_x | C91: [0.8, 1.5] | D91: str
A92: Data/monte_carlo_results.json | B92: scenario.balance-controlled_cg1mm.dispersions.cg_offset_max_m | C92: 0.001 | D92: float
A93: Data/monte_carlo_results.json | B93: scenario.balance-controlled_cg1mm.dispersions.torque_bias_max_frac | C93: 0.1 | D93: float
A94: Data/monte_carlo_results.json | B94: scenario.balance-controlled_cg1mm.dispersions.gyro_noise_rad_s | C94: 0.02 | D94: float
A95: Data/monte_carlo_results.json | B95: scenario.balance-controlled_cg1mm.dispersions.tilt_noise_deg | C95: 2 | D95: float
A96: Data/monte_carlo_results.json | B96: scenario.balance-controlled_cg1mm.dispersions.thrust_sag_x | C96: [0.9, 1.0] | D96: str
A97: Data/monte_carlo_results.json | B97: scenario.balance-controlled_cg1mm.dispersions.authority_model | C97: placeholder | D97: str
A98: Data/monte_carlo_results.json | B98: scenario.balance-controlled_cg1mm.dispersions.mixer_arm_m | D98: null
A99: Data/monte_carlo_results.json | B99: scenario.as-toleranced_cg5mm_mixer-authority.label | C99: as-toleranced_cg5mm_mixer-authority | D99: str
A100: Data/monte_carlo_results.json | B100: scenario.as-toleranced_cg5mm_mixer-authority.init_tilt_deg | C100: 60 | D100: float
...

Sheet Simulation Parameters
A1: tier | B1: mass_kg | C1: inertia_lateral_kg_m2 | D1: inertia_yaw_factor | E1: max_torque_n_m | F1: max_thrust_n | G1: drag_coefficient | H1: projected_area_m2 | I1: detection_latency_s | J1: motor_start_latency_s | K1: gyro_limit_rad_s | L1: available_height_m | M1: arm_m | N1: yaw_torque_n_m | O1: yaw_drag_n_m_s2
A2: best | B2: 0.11796 | C2: 0.0002 | D2: 1.6 | E2: 0.006 | F2: 5 | G2: 1.3 | H2: 0.016 | I2: 0.02 | J2: 0.03 | K2: 34.906585 | L2: 3 | O2: 0
A3: nominal | B3: 0.12976 | C3: 0.00035 | D3: 1.6 | E3: 0.004 | F3: 4.2 | G3: 1 | H3: 0.012 | I3: 0.05 | J3: 0.06 | K3: 34.906585 | L3: 3 | O3: 0
A4: worst | B4: 0.155 | C4: 0.00055 | D4: 1.6 | E4: 0.0025 | F4: 3.5 | G4: 0.8 | H4: 0.008 | I4: 0.1 | J4: 0.12 | K4: 34.906585 | L4: 3 | O4: 0

Sheet Recovery Envelope Model
A1: name | B1: mass_kg | C1: inertia_kg_m2 | D1: initial_rate_rad_s | E1: initial_tilt_rad | F1: detection_latency_s | G1: motor_start_latency_s | H1: control_torque_n_m | I1: total_thrust_n | J1: battery_voltage_v | K1: reference_voltage_v | L1: drag_coefficient | M1: projected_area_m2 | N1: gyro_limit_rad_s | O1: gyro_margin_fraction | P1: available_height_m | Q1: result.name | R1: result.gyro_ok | S1: result.thrust_ok | T1: result.effective_control_torque_n_m | U1: result.effective_total_thrust_n | V1: result.attitude_arrest_s | W1: result.upright_rotation_s | X1: result.passive_time_s | Y1: result.vertical_arrest_s | Z1: result.minimum_height_m | AA1: result.available_height_m | AB1: result.testable_now
A2: best | B2: 0.11796 | C2: 0.0002 | D2: 2 | E2: 0.52359878 | F2: 0.02 | G2: 0.03 | H2: 0.006 | I2: 5 | J2: 8.4 | K2: 8.4 | L2: 1.3 | M2: 0.016 | N2: 34.906585 | O2: 0.8 | P2: 3 | Q2: best | R2: TRUE | S2: TRUE | T2: 0.006 | U2: 5 | V2: 0.066666667 | W2: 0.26422182 | X2: 0.38088849 | Y2: 0.108 | Z2: 0.88427091 | AA2: 3 | AB2: TRUE
A3: nominal | B3: 0.12976 | C3: 0.00035 | D3: 5 | E3: 1.0471976 | F3: 0.05 | G3: 0.06 | H3: 0.004 | I3: 4.2 | J3: 7.6 | K3: 8.4 | L3: 1 | M3: 0.012 | N3: 34.906585 | O3: 0.8 | P3: 3 | Q3: nominal | R3: TRUE | S3: TRUE | T3: 0.0036190476 | U3: 3.8 | V3: 0.48355263 | W3: 0.63647475 | X3: 1.2300274 | Y3: 0.4525 | Z3: 8.638546 | AA3: 3 | AB3: FALSE
A4: worst | B4: 0.155 | C4: 0.00055 | D4: 8 | E4: 1.5707963 | F4: 0.1 | G4: 0.12 | H4: 0.0025 | I4: 3.5 | J4: 7 | K4: 8.4 | L4: 0.8 | M4: 0.008 | N4: 34.906585 | O4: 0.8 | P4: 3 | Q4: worst | R4: TRUE | S4: TRUE | T4: 0.0020833333 | U4: 2.9166667 | V4: 2.112 | W4: 1.2879289 | X4: 3.6199289 | Y4: 1.6335 | Z4: 58.422447 | AA4: 3 | AB4: FALSE

Sheet Mass Budget
A1: id | B1: component | C1: best_g | D1: nominal_g | E1: worst_g | F1: basis | G1: source | H1: status
A2: EST-MASS-001 | B2: Flight controller | C2: 5.5 | D2: 5.5 | E2: 6.5 | F2: official product specification | G2: Holybro Kakute H7 Mini v1.5 | H2: CONFIRMED
A3: EST-MASS-002 | B3: 4-in-1 ESC | C3: 6.4 | D3: 6.4 | E3: 8 | F3: manufacturer specification; worst adds softmounts and capacitor; weigh on receipt | G3: Flywoo GOKU G45M 45A 2-6S AM32 | H3: CONFIRMED
A4: EST-MASS-003 | B4: Brushless motors | C4: 15.2 | D4: 15.2 | E4: 16.5 | F4: 3.8 g each catalog mass; weigh set | G4: Happymodel EX1103 11000KV | H4: BENCH_REQUIRED
A5: EST-MASS-004 | B5: Propeller flight set | C5: 3 | D5: 3.5 | E5: 4.5 | F5: 0.88 g each official mass; weigh set | G5: Gemfan Hurricane 2023-3 | H5: CONFIRMED
A6: EST-MASS-005 | B6: Flight battery | C6: 28 | D6: 29 | E6: 31 | F6: reseller specification 29 g +/-1 g | G6: GNB GNB5502S100AHV | H6: BENCH_REQUIRED
A7: EST-MASS-006 | B7: Control link receiver | C7: 0.46 | D7: 0.46 | E7: 1 | F7: official product specification | G7: BetaFPV ELRS Lite Flat Antenna V1.2 | H7: CONFIRMED
A8: EST-MASS-007 | B8: Buzzer and status LED | C8: 3 | D8: 3.3 | E8: 4.5 | F8: 2.7 g official buzzer plus LED/wire allowance | G8: VIFLY Finder Mini + WS2812 | H8: INFERRED
A9: EST-MASS-008 | B9: Vision processor and camera | C9: 19.8 | D9: 19.8 | E9: 21 | F9: official store weight rounded to 20 g | G9: Arduino Nicla Vision ABX00051 | H9: CONFIRMED
A10: EST-MASS-009 | B10: Optical flow and lidar | C10: 4.5 | D10: 4.5 | E10: 5 | F10: manufacturer specification | G10: MicoAir MTF-01 | H10: CONFIRMED
A11: EST-MASS-011 | B11: Wiring and connectors | C11: 3 | D11: 5.5 | E11: 8 | F11: estimated | G11: Planning assumption; weigh harness | H11: ASSUMED
A12: EST-MASS-012 | B12: Frame guards mounts and fasteners | C12: 35 | D12: 42.5 | E12: 50 | F12: estimated | G12: Replace with CAD mass model | H12: ASSUMED

Sheet Power Budget
A1: device | B1: rail | C1: nominal_ma | D1: worst_ma | E1: basis | F1: evidence_state | G1: source_url | H1: notes
A2: Arduino Nicla Vision | B2: 5V | C2: 105 | D2: 250 | E2: Official average image-capture current; worst is an engineering allowance with Wi-Fi/BLE disabled | F2: ASSUMED | G2: https://docs.arduino.cc/resources/datasheets/ABX00051-datasheet.pdf | H2: Measure inference peak current; add separate regulator if configuration exceeds allowance
A3: MicoAir MTF-01 | B3: 5V | C3: 100 | D3: 120 | E3: Manufacturer 500 mW at 5 V figure plus allowance | F3: CONFIRMED | G3: https://micoair.com/optical_range_sensor_mtf-01/ | H3: Input range 4.0-5.5 V
A4: BetaFPV ELRS Lite V1.2 | B4: 5V | C4: 50 | D4: 100 | E4: No official current figure located; conservative engineering allowance | F4: ASSUMED | G4: https://betafpv.com/collections/radio-controllers/products/elrs-lite-receiver | H4: Measure with telemetry active
A5: VIFLY Finder Mini + WS2812 | B5: 5V | C5: 60 | D5: 150 | E5: Charging/LED allowance; finder contains its own 40 mAh cell | F5: ASSUMED | G5: https://viflydrone.com/collections/all/products/vifly-finder-mini-fpv-racing-drone-buzzer | H5: Measure finder charging and maximum LED brightness

Sheet Estimates
A1: id | B1: parameter | C1: best | D1: nominal | E1: worst | F1: units | G1: basis | H1: source | I1: uncertainty_direction | J1: notes
A2: EST-MASS-001 | B2: Flight controller mass | C2: 5.5 | D2: 5.5 | E2: 6.5 | F2: g | G2: confirmed | H2: Holybro Kakute H7 Mini v1.5 official specification | I2: high_increases_risk | J2: Weigh delivered board with installed grommets
A3: EST-MASS-002 | B3: 4-in-1 ESC mass | C3: 6.4 | D3: 6.4 | E3: 8 | F3: g | G3: confirmed | H3: Flywoo GOKU G45M manufacturer specification | I3: high_increases_risk | J3: Weigh on receipt with softmounts and capacitor
A4: EST-MASS-003 | B4: Four motor mass | C4: 15.2 | D4: 15.2 | E4: 16.5 | F4: g | G4: bench_required | H4: Happymodel EX1103 11000KV catalog mass | I4: high_increases_risk | J4: Weigh all four delivered motors with final lead length
A5: EST-MASS-004 | B5: Propeller flight-set mass | C5: 3 | D5: 3.5 | E5: 4.5 | F5: g | G5: confirmed | H5: Gemfan Hurricane 2023-3 official 0.88 g each | I5: high_increases_risk | J5: Weigh balanced flight set
A6: EST-MASS-005 | B6: Flight battery mass | C6: 28 | D6: 29 | E6: 31 | F6: g | G6: bench_required | H6: GNB GNB5502S100AHV reseller specification | I6: high_increases_risk | J6: Weigh each pack and record capacity/sag test
A7: EST-MASS-006 | B7: Control-link receiver mass | C7: 0.46 | D7: 0.46 | E7: 1 | F7: g | G7: confirmed | H7: BetaFPV ELRS Lite Flat Antenna V1.2 official specification | I7: high_increases_risk | J7: Weigh with final leads
A8: EST-MASS-007 | B8: Buzzer and status LED mass | C8: 3 | D8: 3.3 | E8: 4.5 | F8: g | G8: inferred | H8: VIFLY Finder Mini 2.7 g plus WS2812 and wire allowance | I8: high_increases_risk | J8: Weigh completed status harness
A9: EST-MASS-008 | B9: Vision processor and camera mass | C9: 19.8 | D9: 19.8 | E9: 21 | F9: g | G9: confirmed | H9: Arduino Nicla Vision ABX00051 official store rounded weight | I9: high_increases_risk | J9: Weigh board with mounted headers and cable
A10: EST-MASS-009 | B10: Optical flow and lidar mass | C10: 4.5 | D10: 4.5 | E10: 5 | F10: g | G10: confirmed | H10: MicoAir MTF-01 manufacturer specification | I10: high_increases_risk | J10: Weigh with cable
A11: EST-MASS-010 | B11: External vision logging mass | C11: 0 | D11: 0 | E11: 0 | F11: g | G11: removed | H11: Nicla has no microSD socket | I11: high_increases_risk | J11: Stage 1 numeric events go to the flight controller over MAVLink; external SPI storage deferred
A12: EST-MASS-011 | B12: Wiring and connectors mass | C12: 3 | D12: 5.5 | E12: 8 | F12: g | G12: assumed | H12: Engineering allowance | I12: high_increases_risk | J12: Weigh completed harness
A13: EST-MASS-012 | B13: Frame guards mounts and fasteners mass | C13: 35 | D13: 42.5 | E13: 50 | F13: g | G13: assumed | H13: Replace with CAD mass model | I13: high_increases_risk | J13: Update after complete assembly mass properties
... A24: EST-GUARD-003 | B24: Repeated-event impact energy | C24: 0.02 | D24: 0.05 | E24: 0.1 | F24: J | G24: estimated | H24: Initial functional-event envelope | I24: high_increases_deflection | J24: Replace with trajectory measurements

Sheet Component Verification
A1: component | B1: claim | C1: required_value | D1: observed_value | E1: units | F1: evidence_state | G1: source_type | H1: source_url | I1: checked_date | J1: decision | K1: follow_up
A2: Holybro Kakute H7 Mini v1.5 | B2: ArduPilot support | C2: Official supported target | D2: KakuteH7Mini on ArduPilot 4.6.0 or later | F2: CONFIRMED | G2: manufacturer documentation | H2: https://docs.holybro.com/autopilot/kakute-h7-v1-v2-mini/kakute-h7-mini/supported-firmware | I2: 2026-06-21 | J2: PASS | K2: Install current stable ArduPilot 4.6 or later
A3: Holybro Kakute H7 Mini v1.5 | B3: UART capacity | C3: At least 5 full-duplex UARTs plus optional ESC telemetry | D3: UART1/2/3/4/6 full duplex; UART7 receive-only | E3: count | F3: CONFIRMED | G3: official pinout and ArduPilot mapping | H3: https://ardupilot.org/sub/docs/common-holybro-kakuteh7mini-v13.html | I3: 2026-06-21 | J3: PASS | K3: Confirm delivered board is v1.5 before soldering
A4: Holybro Kakute H7 Mini v1.5 | B4: Motor timer groups | C4: Four DShot outputs without mixed-rate collision | D4: M1/M4 group 1; M2/M3 group 2 | F4: CONFIRMED | G4: ArduPilot board documentation | H4: https://ardupilot.org/sub/docs/common-holybro-kakuteh7mini-v13.html | I4: 2026-06-21 | J4: PASS | K4: Configure all four motors to the same DShot rate
A5: Holybro Kakute H7 Mini v1.5 | B5: Physical mounting | C5: 20x20 stack compatible | D5: 20x20 mm; 3.6 mm holes with M3 and M2 grommets | E5: mm | F5: CONFIRMED | G5: manufacturer documentation | H5: https://docs.holybro.com/autopilot/kakute-h7-v1-v2-mini/kakute-h7-mini/overview | I5: 2026-06-21 | J5: PASS | K5: Order matching M2 grommets/standoffs and verify delivered fit
A6: Holybro Kakute H7 Mini v1.5 | B6: Peripheral rail | C6: At least 25 percent margin | D6: 2 A BEC specified; design uses conservative 1.5 A capacity | E6: A | F6: INFERRED | G6: manufacturer overview and pinout | H6: https://docs.holybro.com/autopilot/kakute-h7-v1-v2-mini/kakute-h7-mini/pinout | I6: 2026-06-21 | J6: PASS | K6: Measure rail voltage during peak Nicla load
A7: Flywoo GOKU G45M | B7: Electrical rating | C7: Per-motor peak 9.2 A + uncertainty within rating | D7: 45 A continuous; 50 A peak 10 s; per channel | E7: A | F7: CONFIRMED | G7: manufacturer specification | H7: https://flywoo.net/products/goku-g45m-32bit-128k-2-6s-45a-esc | I7: 2026-07-03 | J7: PASS | K7: Bench current/temperature at 2S remains required
A8: Flywoo GOKU G45M | B8: 2S voltage support | C8: Operates 7.0-8.4 V (2S LiHV under load) | D8: Flywoo lists 2-6S; some retailers list 3-6S | E8: S | F8: INFERRED | G8: manufacturer vs retailer listings disagree | H8: https://flywoo.net/products/goku-g45m-32bit-128k-2-6s-45a-esc | I8: 2026-07-03 | J8: PASS_WITH_CAVEAT | K8: Bench-verify spin-up and full-throttle at 7.0 V before the propulsion gate
A9: Flywoo GOKU G45M | B9: Mechanical mounting | C9: 20x20 stack compatible | D9: 20x20 mm M3; 33x30x6.1 mm; 6.4 g | F9: CONFIRMED | G9: manufacturer specification | H9: https://flywoo.net/products/goku-g45m-32bit-128k-2-6s-45a-esc | I9: 2026-07-03 | J9: PASS | K9: Confirm 8-pin connector pin order against Kakute before applying power
A10: Flywoo GOKU G45M | B10: Battery current telemetry | C10: Current sensor readable by ArduPilot | D10: AM32 telemetry + onboard current sensor | F10: CONFIRMED | G10: manufacturer and retailer specification | H10: https://www.rotorama.com/product/goku-g45m-32bit-2-6s-45a-esc-20x20 | I10: 2026-07-03 | J10: PASS_WITH_CAVEAT | K10: Calibrate BATT_AMP_PERVLT against bench meter
A11: Happymodel EX1103 11000KV | B11: Static thrust at 7.0 V | C11: At least 112.5 gf for full reserve | D11: 121.9 gf claimed at 7.4 V with 2023R | E11: gf | F11: BENCH_REQUIRED | G11: vendor-derived listing | H11: https://rcdrone.top/ko/products/happymodel-ex1103-brushless-motor | I11: 2026-06-21 | J11: OPEN | K11: Measure uncertainty-adjusted thrust at 8.4/7.6/7.0 V
A12: Happymodel EX1103 11000KV | B12: Peak current | C12: At most 10.4 A unconditional | D12: 9.2 A claimed at 7.4 V with 2023R | E12: A | F12: BENCH_REQUIRED | G12: vendor-derived listing | H12: https://rcdrone.top/ko/products/happymodel-ex1103-brushless-motor | I12: 2026-06-21 | J12: OPEN | K12: Measure current and winding temperature
A13: Gemfan Hurricane 2023-3 | B13: Geometry and mass | C13: 1.5 mm T-mount within 2-inch guard | D13: 52.17 mm disk; 2.3 inch pitch; 0.88 g each | F13: CONFIRMED | G13: manufacturer documentation | H13: https://www.gemfanhobby.com/2023-hurricane-pc-3-blade.html | I13: 2026-06-21 | J13: PASS | K13: Confirm EX1103 bell screw pattern and guard clearance
A14: Gemfan Hurricane 2023-3 | B14: Motor pairing | C14: Compatible with EX1103 | D14: Manufacturer recommends 1105-1108 motors | F14: BENCH_REQUIRED | G14: manufacturer documentation | H14: https://www.gemfanhobby.com/2023-hurricane-pc-3-blade.html | I14: 2026-06-21 | J14: OPEN | K14: Vendor propulsion test indicates use but exact delivered combination must be bench-tested
A15: GNB GNB5502S100AHV | B15: Pack identity | C15: 2S 550 mAh LiHV, XT30, about 29 g | D15: 7.6 V; 29 g +/-1 g; XT30 | F15: INFERRED | G15: specialist retailer listing | H15: https://www.drone-fpv-racer.com/en/2s-550mah-100c-gnb-lihv-battery-xt30-by-gaoneng-12372.html | I15: 2026-06-21 | J15: PASS_WITH_CAVEAT | K15: Verify label connector dimensions and mass on receipt
A16: GNB GNB5502S100AHV | B16: Continuous current | C16: At most 44 A for unconditional pass | D16: 55 A derived from claimed 100C | E16: A | F16: BENCH_REQUIRED | G16: retailer claim and calculation | H16: https://www.drone-fpv-racer.com/en/2s-550mah-100c-gnb-lihv-battery-xt30-by-gaoneng-12372.html | I16: 2026-06-21 | J16: OPEN | K16: Measure sag and temperature; C-rating is not accepted as proof
A17: BetaFPV ELRS Lite Flat V1.2 | B17: Power and mass | C17: 5 V receiver under 1 g | D17: 5 V; 0.46 g | F17: CONFIRMED | G17: manufacturer documentation | H17: https://betafpv.com/collections/radio-controllers/products/elrs-lite-receiver | I17: 2026-06-21 | J17: PASS | K17: Measure current and link quality with guards installed
A18: Arduino Nicla Vision ABX00051 | B18: Power and serial interface | C18: Compatible with Kakute 5 V and 3.3 V UART | D18: VIN 3.5-5.5 V; programmable VDDIO_EXT up to 3.3 V; one UART | F18: CONFIRMED | G18: manufacturer datasheet | H18: https://docs.arduino.cc/resources/datasheets/ABX00051-datasheet.pdf | I18: 2026-06-21 | J18: PASS | K18: Set VDDIO_EXT to 3.3 V and share ground
A19: Arduino Nicla Vision ABX00051 | B19: Image-capture current | C19: Fit conservative 1.5 A peripheral budget | D19: 105 mA average image capture | E19: mA | F19: CONFIRMED | G19: manufacturer datasheet | H19: https://docs.arduino.cc/resources/datasheets/ABX00051-datasheet.pdf | I19: 2026-06-21 | J19: PASS_WITH_CAVEAT | K19: Measure peak inference current with Wi-Fi/BLE disabled
A20: Arduino Nicla Vision ABX00051 | B20: Event latency | C20: At most 100 ms Stage 1 and 50 ms future recovery | D20: No application benchmark available | E20: ms | F20: BENCH_REQUIRED | G20: application-specific measurement | I20: 2026-06-21 | J20: OPEN | K20: Measure p95 sensor-event to MAVLink latency and effective FPS
A21: Arduino Nicla Vision ABX00051 | B21: Onboard microSD | C21: Required only for standalone continuous image storage | D21: No microSD socket | F21: BLOCKER | G21: manufacturer datasheet | H21: https://docs.arduino.cc/resources/datasheets/ABX00051-datasheet.pdf | I21: 2026-06-21 | J21: RESOLVED | K21: Remove card from Stage 1; log numeric events to FC over MAVLink
A22: MicoAir MTF-01 | B22: Combined flow and rangefinder interface | C22: One serial resource | D22: MAVLink1 over one UART; FLOW_TYPE=5 and RNGFND1_TYPE=10 | F22: CONFIRMED | G22: manufacturer and ArduPilot documentation | H22: https://ardupilot.org/copter/docs/common-mtf-01.html | I22: 2026-07-03 | J22: PASS | K22: Configure SERIAL4_PROTOCOL=1 with SERIAL4_OPTIONS=1024 at 115200 baud; set sensor mav_id=200 via MicoAssistant
A23: MicoAir MTF-01 | B23: Power and mass | C23: Fit 5 V budget and mass envelope | D23: 4.0-5.5 V; 500 mW at 5 V (~100 mA); 4.5 g | F23: CONFIRMED | G23: manufacturer documentation | H23: https://micoair.com/optical_range_sensor_mtf-01/ | I23: 2026-07-03 | J23: PASS | K23: 8 m range at 600 Lux derates to 5 m at 60 kLux; verify indoor cage lighting case
A24: MicoAir MTF-01 | B24: Availability | C24: Credible purchasable source | D24: In production; official store, Amazon, and resellers stocked | F24: CONFIRMED | G24: retail listings | H24: https://micoair.com/optical_range_sensor_mtf-01/ | I24: 2026-07-03 | J24: PASS | K24: Substituted for EOL Matek 3901-L0X on 2026-07-03
A25: VIFLY Finder Mini fmini01 | B25: Mass and function | C25: Self-powered finder under 3 g | D25: 2.7 g; 40 mAh cell; up to 7 hours | F25: CONFIRMED | G25: manufacturer store | H25: https://viflydrone.com/collections/all/products/vifly-finder-mini-fpv-racing-drone-buzzer | I25: 2026-06-21 | J25: PASS | K25: Verify buzzer control polarity and charging current

Sheet Hardware Inventory
A1: item | B1: category | C1: model_or_part | D1: revision | E1: quantity | F1: state | G1: label_or_drawing_ref | H1: calibration_record | I1: observer | J1: date | K1: notes
A2: V995 quadcopter | B2: test_article | C2: Veeniix V995 | D2: unknown | E2: 1 | F2: OWNER_IDENTIFIED | G2: P3 IMG_3883.HEIC; owner statement 2026-09-20 | H2: none | I2: owner | J2: 2026-09-20 | K2: ~50 g OWNER_ESTIMATE (battery inclusion unspecified); four guarded 3-blade rotors; two-wire motor leads (brushed inference, unconfirmed); board edge marking contains 'A20' and a date-like '23-05-06' (partial, obscured); CLK-marked pad group near switch end; photo shows canopy/foam removed - not the flight configuration
A3: V995 flight battery | B3: test_article | C3: 3.7 V 180 mAh (manufacturer FAQ) | D3: unknown | E3: 1 | F3: MANUFACTURER_SPECIFICATION | G3: S12 veeniix.com V995 page (indexed) | H3: none | I3: owner decision 2026-09-21 | J3: 2026-09-21 | K3: accepted for planning by owner; no label re-verification task; separate interface from charger input
A4: V995 charger | B4: test_article | C4: 5 V DC / 2 A adapter + supplied cable (manufacturer spec) | D4: unknown | E4: 1 | F4: MANUFACTURER_SPECIFICATION | G4: S12 | H4: none | I4: owner decision 2026-09-21 | J4: 2026-09-21 | K4: charger input is not the flight-battery interface; never a source for an accessory rail
A5: NAU7802 24-bit ADC STEMMA QT | B5: bench_adc | C5: Adafruit PID 4538 | D5: unknown (Rev C exposes A+B inputs; earlier A only) | E5: 1 | F5: PURCHASE_REPORTED | G5: P1/P2 purchase list (transcribed in the 2026-09-20 plan; personal details not copied) | H5: none | J5: 2026-09-20 | K5: confirm terminal labels on delivered board; one conversion chain even if two inputs
A6: QT Py RP2040 | B6: acquisition_mcu | C6: Adafruit PID 4900 | D6: unknown | E6: 1 | F6: PURCHASE_REPORTED | G6: P1/P2 | H6: none | J6: 2026-09-20 | K6: STEMMA connector = I2C1; SDA/SCL pads = I2C0 (S5); headers unassembled? - confirm
A7: INA260 V/I/P sensor | B7: bench_electrical | C7: Adafruit PID 4226 | D7: unknown | E7: 1 | F7: PURCHASE_REPORTED | G7: P1/P2 | H7: none | J7: 2026-09-20 | K7: default addr 0x40; Vin+/Vin- are shunt ends not battery +/-; 15 A chip rating does not rate the harness
A8: LIS3DH accelerometer | B8: motion | C8: Adafruit PID 2809 | D8: unknown | E8: 1 | F8: PURCHASE_REPORTED | G8: P1/P2 | H8: none | J8: 2026-09-20 | K8: specific force only - NOT a gyro; +/-2/4/8/16 g; addr 0x18 or 0x19
A9: IR break-beam pair 5 mm | B9: event_gate | C9: Adafruit PID 2168 | D9: unknown | E9: 1 | F9: PURCHASE_REPORTED | G9: P1/P2 | H9: none | J9: 2026-09-20 | K9: open-collector receiver; <2 ms response; coarse event timing only
A10: Load cell 1 kg four-wire | B10: force | C10: Adafruit PID 4540 | D10: unknown | E10: 1 | F10: PURCHASE_REPORTED | G10: P1/P2 | H10: none | J10: 2026-09-20 | K10: ~9.81 N nominal; ~29 g nominal body, 80 mm nominal length; bench apparatus not payload; recommended initial cell CONDITIONAL on load budget + resolution
A11: Load cell 5 kg four-wire | B11: force | C11: Adafruit PID 4541 | D11: unknown | E11: 1 | F11: PURCHASE_REPORTED | G11: P1/P2 | H11: none | J11: 2026-09-20 | K11: ~49.0 N nominal; 75 mm nominal length - not interchangeable mounting with the 1 kg body
A12: STEMMA QT / Qwiic JST SH 4-pin cable 100 mm | B12: cable | C12: Adafruit PID 4210 | D12: n/a | E12: 1 | F12: PURCHASE_REPORTED | G12: P1/P2 | H12: none | J12: 2026-09-20 | K12: one cable: QT Py STEMMA -> NAU7802 only
A13: Jumper wires F/F 20x75 mm | B13: cable | C13: Adafruit PID 1951 | D13: n/a | E13: 1 | F13: PURCHASE_REPORTED | G13: P1/P2 | H13: none | J13: 2026-09-20 | K13: logic only; never motor/battery current
A14: Jumper wires M/M 20x150 mm | B14: cable | C14: Adafruit PID 1957 | D14: n/a | E14: 1 | F14: PURCHASE_REPORTED | G14: P1/P2 | H14: none | J14: 2026-09-20 | K14: logic only; never motor/battery current
A15: USB data cable (QT Py) | B15: cable | C15: unknown | D15: n/a | E15: ? | F15: UNKNOWN | G15: not on P1/P2 | H15: none | K15: E5: confirm a data-capable USB-C cable is on hand
A16: Reference masses | B16: reference | C16: unknown | D16: n/a | E16: ? | F16: UNKNOWN | G16: not on P1/P2 | H16: none | K16: R3.4: needed for installed calibration; characterize or label results provisional
A17: Dimensional tools (caliper etc.) | B17: tool | C17: unknown | D17: n/a | E17: ? | F17: UNKNOWN | G17: not on P1/P2 | H17: none | K17: needed for cell body/hole inspection and rotor-center geometry
A18: Bench multimeter / current-limited supply | B18: instrument | C18: unknown | D18: n/a | E18: ? | F18: UNKNOWN | G18: not on P1/P2 | H18: none | K18: R2.1 dummy-load verification and INA260 reference points

Sheet Hardware Interfaces
A1: function | B1: resource_type | C1: serial | D1: pad | E1: resource_group | F1: protocol | G1: stage | H1: pad_exposed | I1: evidence_state | J1: source_url | K1: notes
A2: ELRS/CRSF receiver | B2: uart | C2: SERIAL6 | D2: UART6 | F2: CRSF | G2: STAGE_1 | H2: yes | I2: CONFIRMED | J2: https://ardupilot.org/sub/docs/common-holybro-kakuteh7mini-v13.html | K2: Full duplex RC and telemetry; SERIAL6_PROTOCOL=23
A3: MicoAir MTF-01 flow+lidar | B3: uart | C3: SERIAL4 | D3: UART4 | F3: MAVLINK1 | G3: STAGE_1 | H3: yes | I3: CONFIRMED | J3: https://ardupilot.org/copter/docs/common-mtf-01.html | K3: One UART carries both optical flow and rangefinder; SERIAL4_PROTOCOL=1 with SERIAL4_OPTIONS=1024; FLOW_TYPE=5 RNGFND1_TYPE=10; sensor mav_id=200 via MicoAssistant
A4: Nicla Vision MAVLink | B4: uart | C4: SERIAL2 | D4: UART2 | F4: MAVLINK2 | G4: STAGE_1 | H4: yes | I4: CONFIRMED | J4: https://docs.arduino.cc/resources/datasheets/ABX00051-datasheet.pdf | K4: Nicla exposes one level-translated UART; configure VDDIO_EXT=3.3 V and share ground
A5: GPS | B5: uart | C5: SERIAL3 | D5: UART3 | F5: GPS | G5: STAGE_2_RESERVED | H5: yes | I5: CONFIRMED | J5: https://ardupilot.org/sub/docs/common-holybro-kakuteh7mini-v13.html | K5: Reserved; UART3 is the ArduPilot default GPS port
A6: FPV/VTX control | B6: uart | C6: SERIAL1 | D6: UART1 | F6: VTX_CONTROL | G6: STAGE_2_RESERVED | H6: yes | I6: CONFIRMED | J6: https://ardupilot.org/sub/docs/common-holybro-kakuteh7mini-v13.html | K6: Reserved; default DJI/OSD serial allocation may be changed if needed
A7: ESC telemetry | B7: uart_rx | C7: SERIAL7 | D7: UART7_RX | F7: ESC_TELEMETRY | G7: OPTIONAL | H7: yes | I7: CONFIRMED | J7: https://ardupilot.org/sub/docs/common-holybro-kakuteh7mini-v13.html | K7: Receive-only; unnecessary when bidirectional DShot RPM telemetry is available
A8: Configuration/diagnostics | B8: usb | C8: SERIAL0 | D8: USB | F8: USB | G8: STAGE_1 | H8: yes | I8: CONFIRMED | J8: https://ardupilot.org/sub/docs/common-holybro-kakuteh7mini-v13.html | K8: Bench configuration and log download
A9: Motor 1 | B9: motor_output | D9: M1 | E9: PWM_GROUP_1 | F9: DSHOT | G9: STAGE_1 | H9: yes | I9: CONFIRMED | J9: https://ardupilot.org/sub/docs/common-holybro-kakuteh7mini-v13.html | K9: M1 and M4 share a timer group and must use the same output protocol/rate
A10: Motor 2 | B10: motor_output | D10: M2 | E10: PWM_GROUP_2 | F10: DSHOT | G10: STAGE_1 | H10: yes | I10: CONFIRMED | J10: https://ardupilot.org/sub/docs/common-holybro-kakuteh7mini-v13.html | K10: M2 and M3 share a timer group and must use the same output protocol/rate
A11: Motor 3 | B11: motor_output | D11: M3 | E11: PWM_GROUP_2 | F11: DSHOT | G11: STAGE_1 | H11: yes | I11: CONFIRMED | J11: https://ardupilot.org/sub/docs/common-holybro-kakuteh7mini-v13.html | K11: M2 and M3 share a timer group and must use the same output protocol/rate
A12: Motor 4 | B12: motor_output | D12: M4 | E12: PWM_GROUP_1 | F12: DSHOT | G12: STAGE_1 | H12: yes | I12: CONFIRMED | J12: https://ardupilot.org/sub/docs/common-holybro-kakuteh7mini-v13.html | K12: M1 and M4 share a timer group and must use the same output protocol/rate
A13: Status LED | B13: led_output | D13: LED | E13: PWM_GROUP_5 | F13: NEOPIXEL | G13: STAGE_1 | H13: yes | I13: CONFIRMED | J13: https://ardupilot.org/sub/docs/common-holybro-kakuteh7mini-v13.html | K13: Dedicated output 9; does not collide with motor timer groups
A14: Buzzer | B14: gpio | D14: BUZZER | F14: ACTIVE_LOW | G14: STAGE_1 | H14: yes | I14: CONFIRMED | J14: https://docs.holybro.com/autopilot/kakute-h7-v1-v2-mini/kakute-h7-mini/pinout | K14: Dedicated buzzer pads

Sheet Instrumentation
A1: measurement | B1: truth_source | C1: sample_rate | D1: resolution | E1: uncertainty | F1: synchronization | G1: calibration_method | H1: status
A2: Component and vehicle mass | B2: Calibrated digital scale | C2: N/A | D2: 0.1 g | E2: TBD | F2: Static measurement | G2: Certified check masses | H2: PENDING
A3: Center of gravity | B3: Balance fixture or multi-point scale | C3: N/A | D3: 1 mm target | E3: TBD | F3: Static measurement | G3: Known-mass fixture check | H3: PENDING
A4: Inertia | B4: Bifilar or trifilar pendulum | C4: 240 fps video or timer | D4: Timing dependent | E4: TBD | F4: Visible sync marker | G4: Known-body validation | H4: PENDING
A5: Thrust | B5: Load-cell thrust stand | C5: 1000 Hz target | D5: TBD | E5: TBD | F5: Hardware trigger and shared logger | G5: Known calibration weights | H5: PENDING
A6: Current and voltage | B6: Current shunt and power analyzer | C6: 1000 Hz target | D6: TBD | E6: TBD | F6: Shared logger | G6: Reference meter comparison | H6: PENDING
A7: Motor start response | B7: ESC RPM telemetry or optical tachometer | C7: 1000 Hz target | D7: 1 ms target | E7: TBD | F7: Hardware trigger plus sync LED | G7: Known-speed source or telemetry check | H7: PENDING
A8: Release trajectory | B8: Calibrated high-speed video with fiducials | C8: 240 fps minimum | D8: Pixel-scale dependent | E8: TBD | F8: Visible sync LED | G8: Calibration grid and scale bar | H8: PENDING
A9: Attitude and angular rate | B9: Onboard IMU plus external video | C9: IMU rate plus 240 fps minimum | D9: Sensor dependent | E9: TBD | F9: Sync event logged and visible | G9: Firmware configuration and video comparison | H9: PENDING
A10: Guard peak deflection | B10: Calibrated high-speed side video | C10: 1000 fps preferred | D10: 0.25 mm target | E10: TBD | F10: Visible sync LED | G10: Scale grid in impact plane | H10: PENDING
A11: Impact energy | B11: Measured mass and pre-impact velocity | C11: Video rate dependent | D11: Derived | E11: TBD | F11: Trajectory-aligned | G11: Propagated mass and velocity uncertainty | H11: PENDING
A12: Motor ESC and battery temperature | B12: Thermocouple or IR sensor | C12: 10 Hz minimum | D12: 1 C target | E12: TBD | F12: Test-log timestamp | G12: Reference temperature check | H12: PENDING

Sheet Requirements
A1: id | B1: requirement | C1: operator | D1: fixed_value | E1: units | F1: rationale | G1: verification | H1: status
A2: REQ-MASS-001 | B2: Provisional planning mass ceiling | C2: <= | D2: 200 | E2: g | F2: Temporary ceiling until CAD and BOM freeze | G2: Worst-case mass rollup | H2: PENDING
A3: REQ-MASS-002 | B3: Mass freeze abort threshold | C3: <= | D3: 225 | E3: g | F3: Preserves a buffer below the FAA 250 g threshold | G3: Frozen maximum mass check | H3: ACTIVE
A4: REQ-PROP-001 | B4: Static thrust-to-weight ratio | C4: >= | D4: 2 | E4: ratio | F4: Minimum static control authority | G4: Measured thrust divided by frozen maximum mass | H4: PENDING
A5: REQ-PROP-002 | B5: Propulsion acceptance test voltage | C5: = | D5: 7 | E5: V_at_ESC_input_under_load | F5: Verify thrust at the worst permitted loaded pack voltage | G5: Calibrated ESC-input voltage during thrust test | H5: ACTIVE
A6: REQ-IFACE-001 | B6: Duplicate assigned hardware resources | C6: = | D6: 0 | E6: count | F6: Prevent UART pad and output conflicts | G6: Automated hardware-interface validation | H6: ACTIVE
A7: REQ-PWR-001 | B7: Five-volt peripheral rail capacity margin | C7: >= | D7: 25 | E7: percent | F7: Prevent FC rail brownout during peak peripheral load | G7: Documented or measured peak load against conservative 1.5 A capacity | H7: PENDING
A8: REQ-GUARD-001 | B8: Minimum radial prop clearance | C8: >= | D8: 2 | E8: mm | F8: Prevent prop contact under nominal geometry | G8: Caliper inspection | H8: PENDING
A9: REQ-GUARD-002 | B9: Functional clearance-to-deflection safety factor | C9: >= | D9: 2 | E9: ratio | F9: Prevent prop contact during repeated elastic impacts | G9: Guard analysis plus impact test | H9: PENDING
A10: REQ-GUARD-003 | B10: Functional elastic stress safety factor | C10: >= | D10: 3 | E10: ratio | F10: Account for printed PETG variability in elastic events | G10: Linear analysis plus coupon data | H10: PENDING
A11: REQ-FLIGHT-001 | B11: Manual cage hover duration | C11: >= | D11: 30 | E11: s | F11: Prove stable baseline flight | G11: Cage hover test | H11: PENDING
A12: REQ-CLASS-001 | B12: Stage 1 false-positive 95 percent upper bound | C12: <= | D12: 1 | E12: percent | F12: Bound handling-event false activations | G12: At least 300 negative trials | H12: PENDING
A13: REQ-CLASS-002 | B13: Stage 1 release-event sensitivity | C13: >= | D13: 90 | E13: percent | F13: Detect controlled release events | G13: At least 100 positive trials | H13: PENDING
A14: REQ-CLASS-003 | B14: Live-recovery false-positive 95 percent upper bound | C14: <= | D14: 0.3 | E14: percent | F14: Reduce risk before powered release | G14: At least 1000 negative trials | H14: PENDING
A15: REQ-SAFE-001 | B15: Powered release safety approval | C15: = | D15: approved | E15: status | F15: Prevent powered release before safety gates pass | G15: Signed safety review | H15: PENDING
A16: REQ-EST-001 | B16: Initial angular rate | C16: <= | D16: 80 | E16: percent_of_verified_gyro_limit | F16: Maintain estimator margin | G16: External truth comparison plus firmware configuration | H16: PENDING
A17: REQ-VISION-001 | B17: Stage 1 sensor-event to MAVLink p95 latency | C17: <= | D17: 100 | E17: ms | F17: Keep release detection useful for log-only characterization | G17: Synchronized sensor event and MAVLink timestamp | H17: PENDING
A18: REQ-VISION-002 | B18: Future recovery sensor-event to MAVLink p95 latency | C18: <= | D18: 50 | E18: ms | F18: Limit uncommanded rotation before recovery response | G18: Synchronized sensor event and MAVLink timestamp | H18: DEFERRED

Sheet BOM
A1: Category | B1: Item | C1: Qty | D1: Locked Part | E1: Mass Best g | F1: Mass Nominal g | G1: Mass Worst g | H1: Mass Basis | I1: Evidence State | J1: Cost Best USD | K1: Cost Nominal USD | L1: Cost Worst USD | M1: Notes | N1: Selection Status | O1: Flying Hardware | P1: Primary Source
A2: Flight control | B2: Flight controller | C2: 1 | D2: Holybro Kakute H7 Mini v1.5 | E2: 5.5 | F2: 5.5 | G2: 6.5 | H2: official product specification | I2: CONFIRMED | J2: 55 | K2: 59 | L2: 75 | M2: ArduPilot 4.6+ target KakuteH7Mini; weigh on receipt. Exact v1.5 revision required. AVAILABILITY 2026-07-03: in stock at Holybro direct at $58.99 (v1.3 sold out); OQ-007 closed. | N2: LOCKED | O2: yes | P2: https://holybro.com/products/kakute-h7-mini
A3: Flight control | B3: 4-in-1 ESC | C3: 1 | D3: Flywoo GOKU G45M 45A 2-6S AM32 4-in-1 ESC | E3: 6.4 | F3: 6.4 | G3: 8 | H3: manufacturer specification; worst adds softmounts and required capacitor | I3: CONFIRMED | J3: 40 | K3: 45 | L3: 55 | M3: 45 A continuous and 50 A peak (10 s) per channel; AM32 with bidirectional DShot and current sensor. Verify 2S-LiHV operation on receipt (Flywoo says 2-6S; some retailers list 3-6S) and calibrate BATT_AMP_PERVLT. SUBSTITUTED 2026-07-03 for discontinued HGLRC XJB BS13A (OQ-008). | N3: LOCKED | O3: yes | P3: https://flywoo.net/products/goku-g45m-32bit-128k-2-6s-45a-esc
A4: Propulsion | B4: Brushless motors | C4: 4 | D4: Happymodel EX1103 11000KV | E4: 15.2 | F4: 15.2 | G4: 16.5 | H4: manufacturer-class listing; performance unverified | I4: BENCH_REQUIRED | J4: 30 | K4: 36 | L4: 44 | M4: 121.9 gf at 9.2 A is a vendor test at 7.4 V with a 2023R prop; verify exact delivered motor and bench at 7.0 V. | N4: LOCKED | O4: yes | P4: https://www.happymodel.cn/wp-content/uploads/2022/12/Bassline-SPI-ELRS-version-manual-.pdf
A5: Propulsion | B5: Propeller flight set | C5: 1 | D5: Gemfan Hurricane 2023-3 | E5: 3 | F5: 3.5 | G5: 4.5 | H5: official product specification | I5: CONFIRMED | J5: 4 | K5: 6 | L5: 10 | M5: 4 x 0.88 g catalog mass; 1.5 mm T-mount. EX1103 compatibility and thrust remain BENCH_REQUIRED. | N5: LOCKED | O5: yes | P5: https://www.gemfanhobby.com/2023-hurricane-pc-3-blade.html
A6: Power | B6: Flight battery | C6: 1 | D6: GNB GNB5502S100AHV 2S 550mAh 100C XT30 | E6: 28 | F6: 29 | G6: 31 | H6: reseller specification; C-rating unverified | I6: BENCH_REQUIRED | J6: 11 | K6: 14 | L6: 18 | M6: 7.6 V LiHV; 29 g +/-1 g; claimed 55 A continuous. Sag/thermal performance BENCH_REQUIRED; logistics UNVERIFIED. | N6: LOCKED | O6: yes | P6: https://www.drone-fpv-racer.com/en/2s-550mah-100c-gnb-lihv-battery-xt30-by-gaoneng-12372.html
A7: Control | B7: Control link receiver | C7: 1 | D7: BetaFPV ELRS Lite Flat Antenna V1.2 | E7: 0.46 | F7: 0.46 | G7: 1 | H7: official product specification | I7: CONFIRMED | J7: 10 | K7: 12 | L7: 16 | M7: 5 V ELRS/CRSF receiver on SERIAL6; verify link quality after installing guards. | N7: LOCKED | O7: yes | P7: https://betafpv.com/collections/radio-controllers/products/elrs-lite-receiver
A8: Control | B8: Buzzer and status LED | C8: 1 set | D8: VIFLY Finder Mini fmini01 + WS2812 | E8: 3 | F8: 3.3 | G8: 4.5 | H8: official buzzer specification plus LED allowance | I8: INFERRED | J8: 14 | K8: 18 | L8: 24 | M8: Finder is 2.7 g and self-powered; remaining 0.6 g is LED/wire allowance. | N8: LOCKED | O8: yes | P8: https://viflydrone.com/collections/all/products/vifly-finder-mini-fpv-racing-drone-buzzer
A9: Vision | B9: Vision processor and camera | C9: 1 | D9: Arduino Nicla Vision ABX00051 | E9: 19.8 | F9: 19.8 | G9: 21 | H9: official store weight rounded to 20 g | I9: CONFIRMED | J9: 68 | K9: 80 | L9: 115 | M9: 5 V VIN; 3.3 V translated UART; 105 mA average image capture. Latency/FPS BENCH_REQUIRED. PRICE 2026-07-03: official store $68.17. | N9: LOCKED | O9: yes | P9: https://docs.arduino.cc/resources/datasheets/ABX00051-datasheet.pdf
A10: Positioning | B10: Optical flow and lidar | C10: 1 | D10: MicoAir MTF-01 | E10: 4.5 | F10: 4.5 | G10: 5 | H10: manufacturer specification | I10: CONFIRMED | J10: 25 | K10: 30 | L10: 35 | M10: PMW3901 flow + 8 m ToF over one MAVLink UART at 4.0-5.5 V and ~100 mA (500 mW at 5 V); 100 Hz output. Set mav_id=200 via MicoAssistant. SUBSTITUTED 2026-07-03 for EOL Matek 3901-L0X (OQ-008). | N10: LOCKED | O10: yes | P10: https://micoair.com/optical_range_sensor_mtf-01/
A11: Vision | B11: Vision logging | C11: 0 | D11: No external storage in Stage 1 | H11: Nicla has no microSD socket | I11: BLOCKER | J11: 0 | K11: 0 | L11: 0 | M11: Removed from the flying BOM: send numeric event data to the FC over MAVLink; reconsider an SPI reader only if image-log testing proves necessary. | N11: REMOVED | O11: no | P11: https://docs.arduino.cc/resources/datasheets/ABX00051-datasheet.pdf
A12: Electrical | B12: Wiring and connectors | C12: 1 set | D12: XT30 + 18-26 AWG + JST-SH | E12: 3 | F12: 5.5 | G12: 8 | H12: engineering allowance | I12: ASSUMED | J12: 6 | K12: 8 | L12: 12 | M12: Battery pigtail 18-20 AWG (36.8 A transient); 26 AWG signal/5V runs. Weigh completed harness; include strain relief and Nicla header/cable. Interconnect documented in Engineering Data/wiring_harness.md (2026-07-15). | N12: LOCKED | O12: yes
A13: Mechanical | B13: Frame guards mounts and fasteners | C13: 1 set | D13: Printed nylon frame + stiff guards + steel M2 | E13: 35 | F13: 42.5 | G13: 50 | H13: engineering allowance | I13: ASSUMED | J13: 25 | K13: 40 | L13: 60 | M13: CAD/FEA/push testing required; guard deflection and stress remain BENCH_REQUIRED. | N13: LOCKED | O13: yes
A14: Support | B14: Battery charger | C14: 1 | D14: ToolkitRC M6AC | H14: non-flying selection | I14: INFERRED | J14: 45 | K14: 60 | L14: 80 | M14: Support equipment; verify LiHV 2S balance-charge support. | N14: PLANNED | O14: no
A15: Test equipment | B15: Test cage materials | C15: 1 | D15: PVC frame + net + padding | H15: non-flying design | I15: ASSUMED | J15: 25 | K15: 40 | L15: 60 | M15: Build before hover tests. | N15: PLANNED | O15: no
A16: Test equipment | B16: Release fixture materials | C16: 1 | D16: Tethered controlled-release rig | H16: non-flying design | I16: ASSUMED | J16: 12 | K16: 20 | L16: 35 | M16: No powered release before safety gate. | N16: PLANNED | O16: no
A17: Test equipment | B17: Thrust stand | C17: 1 | D17: DIY 1-2 kg load cell or used RCbenchmark 1520 | H17: non-flying design | I17: ASSUMED | J17: 30 | K17: 100 | L17: 165 | M17: Required for 8.4/7.6/7.0 V propulsion characterization. | N17: PLANNED | O17: no

Sheet Purchase Checklist
A1: priority | B1: category | C1: exact_part_or_sku | D1: order_qty | E1: flying_qty | F1: status | G1: required_accessories | H1: interface_check | I1: verify_on_receipt | J1: evidence_state | K1: source_url | L1: blocker_or_caveat
A2: 1 | B2: Flight controller | C2: Holybro Kakute H7 Mini v1.5 | D2: 1 | E2: 1 | F2: ORDER_READY | G2: M2 grommets/standoffs, JST-SH ESC cable | H2: Verify UART2/3/4/6, M1-M4, LED and buzzer pads | I2: Revision label, 5.5 g mass, hole fit, USB connection | J2: CONFIRMED | K2: https://holybro.com/products/kakute-h7-mini | L2: Must be v1.5 and use ArduPilot 4.6+; in stock at Holybro direct $58.99 (checked 2026-07-03)
A3: 1 | B3: ESC | C3: Flywoo GOKU G45M 45A 2-6S AM32 4-in-1 ESC | D3: 1 | E3: 1 | F3: ORDER_READY | G3: 8-pin JST-SH harness to FC, XT30 pigtail, included capacitor and softmounts | H3: Compare connector pin order with Kakute before power | I3: Exact model, 20x20 M3 holes, 6.4 g mass, no short circuits, current-sensor output present | J3: CONFIRMED | K3: https://flywoo.net/products/goku-g45m-32bit-128k-2-6s-45a-esc | L3: Bench-verify 2S-LiHV operation at 7.0 V (retailer listings disagree on 2S vs 3S minimum); substituted 2026-07-03 for discontinued HGLRC BS13A
A4: 1 | B4: Motors | C4: Happymodel EX1103 11000KV | D4: 6 | E4: 4 | F4: ORDER_READY | G4: correct motor screws, two spares | H4: Confirm 1.5 mm shaft/T-mount and lead reach | I4: 3.8 g each, shaft and bell dimensions, winding resistance | J4: BENCH_REQUIRED | K4: https://www.happymodel.cn/wp-content/uploads/2022/12/Bassline-SPI-ELRS-version-manual-.pdf | L4: Thrust/current remain bench-gated
A5: 1 | B5: Propellers | C5: Gemfan Hurricane 2023-3 CW/CCW sets | D5: 3 sets | E5: 1 set | F5: ORDER_READY | G5: spare sets | H5: Confirm T-mount screw pattern and guard clearance | I5: 0.88 g each, correct CW/CCW count, no warping | J5: CONFIRMED | K5: https://www.gemfanhobby.com/2023-hurricane-pc-3-blade.html | L5: No speculative fallback prop; mass freeze is primary shortfall response
A6: 1 | B6: Battery | C6: GNB GNB5502S100AHV 2S 550mAh LiHV XT30 | D6: 3 | E6: 1 | F6: ORDER_READY | G6: LiHV balance charger, LiPo bag, JST-XH balance compatibility | H6: XT30 polarity and charger LiHV mode | I6: 29 g +/-1 g, dimensions, cell voltage, internal resistance, damage | J6: BENCH_REQUIRED | K6: https://www.gaoneng.shop/products/gaoneng-gnb-lihv-2s-7.6v-550mah-100c-xt30-lipo-battery-long-type | L6: US logistics confirmed 2026-07-03 (RaceDayQuads/MyFPV/gaoneng.shop in stock); substitution reopens all power screens
A7: 2 | B7: Vision | C7: Arduino Nicla Vision ABX00051 | D7: 1 | E7: 1 | F7: ORDER_READY | G7: header/castellated wiring, 5 V and ground leads | H7: UART at 3.3 V VDDIO_EXT to Kakute UART2 | I7: Approx. 20 g, camera/IMU/ToF operation, 105 mA reference capture | J7: CONFIRMED | K7: https://docs.arduino.cc/resources/datasheets/ABX00051-datasheet.pdf | L7: No microSD socket; numeric Stage 1 logs go to FC
A8: 2 | B8: Positioning | C8: MicoAir MTF-01 | D8: 1 | E8: 1 | F8: ORDER_READY | G8: 4-wire 5 V UART cable | H8: One MAVLink UART to Kakute UART4 (SERIAL4_PROTOCOL=1 + SERIAL4_OPTIONS=1024) | I8: 4.5 g, flow and range initialization, mav_id=200 set via MicoAssistant | J8: CONFIRMED | K8: https://micoair.com/optical_range_sensor_mtf-01/ | L8: Substituted 2026-07-03 for EOL Matek 3901-L0X; in production and stocked
A9: 2 | B9: Receiver | C9: BetaFPV ELRS Lite Flat Antenna V1.2 | D9: 1 | E9: 1 | F9: ORDER_READY | G9: 5 V CRSF cable | H9: Full duplex CRSF on Kakute UART6 | I9: 0.46 g, correct version, bind and telemetry test | J9: CONFIRMED | K9: https://betafpv.com/collections/radio-controllers/products/elrs-lite-receiver | L9: Verify link after guard installation
A10: 2 | B10: Finder | C10: VIFLY Finder Mini fmini01 | D10: 1 | E10: 1 | F10: ORDER_READY | G10: wire kit | H10: Dedicated Kakute buzzer output | I10: 2.7 g, charge, manual disarm, battery-ejection alarm | J10: CONFIRMED | K10: https://viflydrone.com/collections/all/products/vifly-finder-mini-fpv-racing-drone-buzzer | L10: WS2812 LED is a separate allowance
A11: 3 | B11: Wiring | C11: XT30, 22 AWG power wire, 26 AWG signal wire, JST-SH/GH housings | D11: 1 lot | E11: 1 set | F11: ORDER_READY | G11: heat-shrink, strain relief, spare terminals | H11: Continuity and polarity map for every harness | I11: Finished harness mass and voltage drop | J11: ASSUMED | L11: Final mass remains an allowance until built
A12: 3 | B12: Fasteners | C12: M2 steel motor screws; M2 nylon standoffs; Kakute grommets | D12: 1 assortment | E12: 1 set | F12: ORDER_READY | G12: threadlocker appropriate for metal-to-metal only | H12: Verify screw depth cannot touch motor windings | I12: Finished installed mass and fit | J12: ASSUMED | L12: Do not assume generic M2.5 hardware fits
A13: 3 | B13: Thrust test | C13: 1-2 kg calibrated load cell, current/voltage logger, tachometer if available | D13: 1 rig | E13: 0 | F13: BUILD_REQUIRED | G13: calibration masses and guarded fixture | H13: Measure voltage at ESC input rather than supply setting | I13: Calibration residual and synchronized channels | J13: ASSUMED | L13: Must resolve 7.0 V thrust/current gates before mass freeze

Sheet FMEA
A1: id | B1: failure_mode | C1: effect | D1: severity_1_5 | E1: likelihood_1_5 | F1: detection_method | G1: mitigation | H1: owner | I1: residual_risk | J1: status
A2: FMEA-001 | B2: Premature release | C2: Uncontrolled powered drop | D2: 5 | E2: 2 | F2: Safety-pin inspection and release-state log | G2: Mechanical safety pin plus software inhibit | H2: Test director | I2: Medium | J2: PENDING
A3: FMEA-002 | B3: Release fails then releases unexpectedly | C3: Personnel exposure | D3: 5 | E3: 2 | F3: Release-state indication | G3: Disarm before approach and verify zero RPM | H3: Emergency-stop operator | I3: Low | J3: PENDING
A4: FMEA-003 | B4: Partial release or snag | C4: Asymmetric tumble or rig contact | D4: 4 | E4: 3 | F4: High-speed video and fixture inspection | G4: Breakaway interface and containment | H4: Fixture owner | I4: Medium | J4: PENDING
A5: FMEA-004 | B5: False recovery activation | C5: Unexpected motor spin | D5: 5 | E5: 2 | F5: Props-off trials and state logs | G5: Cage-mode interlock manual override and classifier gate | H5: Controls owner | I5: Low | J5: PENDING
A6: FMEA-005 | B6: Vehicle misses recovery | C6: Floor or cage impact | D6: 3 | E6: 4 | F6: External trajectory measurement | G6: Padded floor and replaceable guards | H6: Test director | I6: Medium | J6: PENDING
A7: FMEA-006 | B7: Battery ejects or is damaged | C7: Fire or electrical risk | D7: 5 | E7: 2 | F7: Positive-retention inspection and post-impact check | G7: Retention test quarantine and fire-response procedure | H7: Mechanical owner | I7: Medium | J7: PENDING
A8: FMEA-007 | B8: Communications loss | C8: Uncontrolled behavior | D8: 5 | E8: 2 | F8: Link-health log | G8: Flight-controller hold land or disarm response | H8: Controls owner | I8: Low | J8: PENDING
A9: FMEA-008 | B9: Thermal exceedance | C9: Motor ESC or battery failure | D9: 4 | E9: 3 | F9: Temperature monitoring | G9: Automatic test termination and cooldown limits | H9: Power owner | I9: Low | J9: PENDING
A10: FMEA-009 | B10: Emergency-stop failure | C10: Continued motor operation | D10: 5 | E10: 2 | F10: Pre-test functional check | G10: Independent secondary disarm method | H10: Emergency-stop operator | I10: Medium | J10: PENDING
A11: FMEA-010 | B11: Gyro saturation or estimator divergence | C11: Incorrect recovery command | D11: 5 | E11: 3 | F11: Rate-limit and estimator-health logs | G11: Reject recovery outside verified estimator envelope | H11: Controls owner | I11: Medium | J11: PENDING

Sheet CAD Parameters
A1: parameter | B1: value | C1: unit | D1: evidence_state | E1: source | F1: release_requirement
A2: motor_body_diameter | B2: 13.5 | C2: mm | D2: vendor_nominal | E2: https://www.happymodel.cn/index.php/2022/09/05/bassline-spare-part-ex1103-kv11000-brushless-motor/ | F2: Confirm delivered EX1103 KV11000 envelope and tolerance
A3: motor_body_length | B3: 15.5 | C3: mm | D3: vendor_nominal | E3: https://www.happymodel.cn/index.php/2022/09/05/bassline-spare-part-ex1103-kv11000-brushless-motor/ | F3: Confirm datum includes shaft and clearance required by mount
A4: motor_shaft_diameter | B4: 1.5 | C4: mm | D4: vendor_nominal | E4: https://www.happymodel.cn/index.php/2022/09/05/bassline-spare-part-ex1103-kv11000-brushless-motor/ | F4: Measure delivered shaft and mating hub fit
A5: prop_diameter | B5: 52.17 | C5: mm | D5: vendor_nominal | E5: https://www.gemfanhobby.com/2023-hurricane-pc-3-blade.html | F5: Add separately approved dynamic clearance and containment envelope
A6: prop_hub_bore | B6: 1.5 | C6: mm | D6: vendor_nominal | E6: https://www.gemfanhobby.com/2023-hurricane-pc-3-blade.html | F6: Confirm actual T-mount screw pattern and motor compatibility
A7: motor_mount_pitch_circle | C7: mm | D7: pending | E7: cad/bench/design-inputs.md | F7: Owner supplies dimensioned drawing or measured hole coordinates
A8: motor_mount_hole_diameter | C8: mm | D8: pending | E8: cad/bench/design-inputs.md | F8: Owner supplies thread size and fit with uncertainty
A9: motor_mount_thread_engagement | C9: mm | D9: pending | E9: cad/bench/design-inputs.md | F9: Owner confirms safe screw penetration and mounting plate stack
A10: prop_mount_screw_spacing | C10: mm | D10: pending | E10: cad/bench/design-inputs.md | F10: Owner supplies matching bell and prop hub drawing or inspection
A11: load_cell_mount_spacing | C11: mm | D11: pending | E11: Engineering Data/instrumentation.csv | F11: Select and identify calibrated load cell then record both end interfaces
A12: load_cell_capacity | C12: N | D12: pending | E12: Engineering Data/instrumentation.csv | F12: Owner selects overload capacity and source drawing
A13: stand_anchor_spacing | C13: mm | D13: pending | E13: Instrumentation/propulsion-bench-safety-checklist.md | F13: Measure actual bench mounting and document stability/load path
A14: stand_calibration_lever | C14: m | D14: pending | E14: cad/bench/design-inputs.md | F14: Calibrate perpendicular distance from pivot to calibration-force line
A15: authority_arm_measured | C15: m | D15: pending | E15: docs/specs/measured-authority-gate/evidence-contract.md | F15: Measure vehicle center-to-motor radius separately from stand calibration lever
A16: authority_arm_model | B16: 0.06 | C16: m | D16: model_assumption | E16: docs/specs/measured-authority-gate/design.md | F16: Planning only; cannot populate measured raw arm_m
A17: total_thrust_model | B17: 4.2 | C17: N | D17: model_assumption | E17: docs/specs/measured-authority-gate/design.md | F17: Planning only; cannot populate measured raw thrust_n
A18: acceptance_voltage | B18: 7 | C18: V | D18: protocol | E18: docs/specs/measured-authority-gate/design.md | F18: Measure under load with calibrated uncertainty
A19: collective_1 | B19: 0.25 | C19: 1 | D19: protocol | E19: docs/specs/measured-authority-gate/design.md | F19: Retain frozen grid
A20: collective_2 | B20: 0.375 | C20: 1 | D20: protocol | E20: docs/specs/measured-authority-gate/design.md | F20: Retain frozen grid
A21: collective_3 | B21: 0.5 | C21: 1 | D21: protocol | E21: docs/specs/measured-authority-gate/design.md | F21: Retain frozen grid
A22: collective_4 | B22: 0.625 | C22: 1 | D22: protocol | E22: docs/specs/measured-authority-gate/design.md | F22: Retain frozen grid
A23: collective_5 | B23: 0.75 | C23: 1 | D23: protocol | E23: docs/specs/measured-authority-gate/design.md | F23: Retain frozen grid
A24: authority_threshold | B24: 0.02 | C24: N*m | D24: protocol | E24: docs/specs/measured-authority-gate/design.md | F24: Uncertainty-adjusted empirical fifth percentile at every grid point
A25: thrust_expanded_uncertainty | C25: N | D25: pending | E25: docs/specs/measured-authority-gate/evidence-contract.md | F25: Reviewed calibration and uncertainty artifact required
A26: arm_expanded_uncertainty | C26: m | D26: pending | E26: docs/specs/measured-authority-gate/evidence-contract.md | F26: Reviewed geometry and uncertainty artifact required
A27: prop_hub_fit_tolerance | C27: mm | D27: pending | E27: cad/bench/design-inputs.md | F27: Owner chooses the bore-to-shaft fit tolerance with a stated design basis (fit class, retention method, vendor drawing); an unchosen tolerance is not 0.05 mm by default

Sheet CAD Input Requests
A1: parameter | B1: unit | C1: acquisition | D1: value | E1: status | F1: source | G1: required_evidence
A2: arm_expanded_uncertainty | B2: m | C2: measurement | E2: pending | F2: docs/specs/measured-authority-gate/evidence-contract.md | G2: Reviewed geometry and uncertainty artifact required
A3: authority_arm_measured | B3: m | C3: measurement | E3: pending | F3: docs/specs/measured-authority-gate/evidence-contract.md | G3: Measure vehicle center-to-motor radius separately from stand calibration lever
A4: stand_anchor_spacing | B4: mm | C4: measurement | E4: pending | F4: Instrumentation/propulsion-bench-safety-checklist.md | G4: Measure actual bench mounting and document stability/load path
A5: stand_calibration_lever | B5: m | C5: measurement | E5: pending | F5: cad/bench/design-inputs.md | G5: Calibrate perpendicular distance from pivot to calibration-force line
A6: thrust_expanded_uncertainty | B6: N | C6: measurement | E6: pending | F6: docs/specs/measured-authority-gate/evidence-contract.md | G6: Reviewed calibration and uncertainty artifact required
A7: prop_hub_fit_tolerance | B7: mm | C7: owner_decision | E7: pending | F7: cad/bench/design-inputs.md | G7: Owner chooses the bore-to-shaft fit tolerance with a stated design basis (fit class, retention method, vendor drawing); an unchosen tolerance is not 0.05 mm by default
A8: load_cell_capacity | B8: N | C8: vendor_drawing | E8: pending | F8: Engineering Data/instrumentation.csv | G8: Owner selects overload capacity and source drawing
A9: load_cell_mount_spacing | B9: mm | C9: vendor_drawing | E9: pending | F9: Engineering Data/instrumentation.csv | G9: Select and identify calibrated load cell then record both end interfaces
A10: motor_mount_hole_diameter | B10: mm | C10: vendor_drawing | E10: pending | F10: cad/bench/design-inputs.md | G10: Owner supplies thread size and fit with uncertainty
A11: motor_mount_pitch_circle | B11: mm | C11: vendor_drawing | E11: pending | F11: cad/bench/design-inputs.md | G11: Owner supplies dimensioned drawing or measured hole coordinates
A12: motor_mount_thread_engagement | B12: mm | C12: vendor_drawing | E12: pending | F12: cad/bench/design-inputs.md | G12: Owner confirms safe screw penetration and mounting plate stack
A13: prop_mount_screw_spacing | B13: mm | C13: vendor_drawing | E13: pending | F13: cad/bench/design-inputs.md | G13: Owner supplies matching bell and prop hub drawing or inspection

Sheet Wire Data
A1: WireID | B1: From | C1: FromPin | D1: To | E1: ToPin | F1: Diameter | G1: Gauge | H1: Insulation | I1: BendRadius | J1: Color
A2: W01 | B2: BATT | C2: + | D2: ESC | E2: B+ | F2: 2.4 | G2: 18 | I2: 12 | J2: red
A3: W02 | B3: BATT | C3: - | D3: ESC | E3: B- | F3: 2.4 | G3: 18 | I3: 12 | J3: black
A4: W03 | B4: MOTOR1 | C4: A | D4: ESC | E4: M1A | F4: 1 | G4: 28 | I4: 4 | J4: black
A5: W04 | B5: MOTOR1 | C5: B | D5: ESC | E5: M1B | F5: 1 | G5: 28 | I5: 4 | J5: black
A6: W05 | B6: MOTOR1 | C6: C | D6: ESC | E6: M1C | F6: 1 | G6: 28 | I6: 4 | J6: black
A7: W06 | B7: MOTOR2 | C7: A | D7: ESC | E7: M2A | F7: 1 | G7: 28 | I7: 4 | J7: black
A8: W07 | B8: MOTOR2 | C8: B | D8: ESC | E8: M2B | F8: 1 | G8: 28 | I8: 4 | J8: black
A9: W08 | B9: MOTOR2 | C9: C | D9: ESC | E9: M2C | F9: 1 | G9: 28 | I9: 4 | J9: black
A10: W09 | B10: MOTOR3 | C10: A | D10: ESC | E10: M3A | F10: 1 | G10: 28 | I10: 4 | J10: black
A11: W10 | B11: MOTOR3 | C11: B | D11: ESC | E11: M3B | F11: 1 | G11: 28 | I11: 4 | J11: black
A12: W11 | B12: MOTOR3 | C12: C | D12: ESC | E12: M3C | F12: 1 | G12: 28 | I12: 4 | J12: black
A13: W12 | B13: MOTOR4 | C13: A | D13: ESC | E13: M4A | F13: 1 | G13: 28 | I13: 4 | J13: black
... A40: W39 | B40: FC | C40: BZ- | D40: VIFLY | E40: BZ- | F40: 1 | G40: 28 | I40: 4 | J40: black

Sheet Interface Observations
A1: component | B1: revision | C1: feature | D1: datum | E1: reading_index | F1: value | G1: unit | H1: instrument | I1: instrument_resolution | J1: source_drawing_page | K1: observer | L1: date | M1: disposition | N1: notes

Sheet CAD Mass Template
A1: component | B1: mass_best_g | C1: mass_nominal_g | D1: mass_worst_g | E1: cg_x_mm | F1: cg_y_mm | G1: cg_z_mm | H1: Ixx_kg_m2 | I1: Iyy_kg_m2 | J1: Izz_kg_m2 | K1: Ixy_kg_m2 | L1: Ixz_kg_m2 | M1: Iyz_kg_m2 | N1: basis | O1: source | P1: status
A2: REPLACE_WITH_CAD_EXPORT | N2: estimated | O2: CAD model required | P2: PENDING

Sheet CS Dashboard
A1: Guarded Micro-UAV Component & Propulsion Study
A2: Initial source-backed selection screen | Component research + frame-integrated battery trade study
A4: Study metric | B4: Value | D4: Engineering recommendations
A5: Component candidates | B5: =COUNTA('CS Component Candidates'!B5:B100) -> 41 | D5: Start bench testing with EX1103 11000KV + 2023-3 + removable 2S 550-650 mAh pack. The modeled 450 mAh 75C pack clears static T/W but fails the catalog full-load discharge screen.
A6: Propulsion scenarios | B6: =COUNTA('CS Propulsion Study'!A5:A100) -> 12 | D6: Use a removable, centrally located pack for V1. Frame-integrated cells add uncertain mass, increase rotational inertia when distributed, and create charging, thermal, impact, and replacement hazards.
A7: Reference drones | B7: =COUNTA('CS Reference Drones'!A5:A100) -> 7 | D7: Prioritize AIO versus H7 FC trade testing: the AIO can save meaningful mass, but H7-class ArduPilot support/logging may be required for recovery research.
A8: Baseline base mass (g) | B8: ='CS Sources'!B9 -> 82.75 | D8: Do not select from estimated thrust cases until the exact motor-prop-voltage combination has measured thrust, current, RPM, transient response, and temperature data.
A9: Required static T/W | B9: ='CS Sources'!B10 -> 2.0 | D9: Static T/W is only a screen. Final selection must close recovery torque, motor-start latency, battery sag, gyro/estimator envelope, guard clearance, and thermal limits.
A10: Baseline scenario T/W | B10: ='CS Propulsion Study'!T5 -> 3.8222153
A11: Baseline est. flight time (min) | B11: ='CS Propulsion Study'!Z5 -> 2.2736842
A14: Scenario | B14: Static T/W | C14: Est. flight time (min)
A15: ='CS Propulsion Study'!A5 -> Baseline documented | B15: ='CS Propulsion Study'!T5 -> 3.8222153 | C15: ='CS Propulsion Study'!Z5 -> 2.2736842
A16: ='CS Propulsion Study'!A6 -> Middle-capacity candidate | B16: ='CS Propulsion Study'!T6 -> 3.72299 | C16: ='CS Propulsion Study'!Z6 -> 2.6938776
A17: ='CS Propulsion Study'!A7 -> Endurance/current candidate | B17: ='CS Propulsion Study'!T7 -> 3.5469557 | C17: ='CS Propulsion Study'!Z7 -> 3.0588235
A18: ='CS Propulsion Study'!A8 -> Heavy endurance | B18: ='CS Propulsion Study'!T8 -> 3.3750952 | C18: ='CS Propulsion Study'!Z8 -> 2.9714286
A19: ='CS Propulsion Study'!A9 -> Central integrated bay | B19: ='CS Propulsion Study'!T9 -> 3.6126547 | C19: ='CS Propulsion Study'!Z9 -> 2.5485149
A20: ='CS Propulsion Study'!A10 -> Split-arm battery concept | B20: ='CS Propulsion Study'!T10 -> 3.4935874 | C20: ='CS Propulsion Study'!Z10 -> 1.8
A21: ='CS Propulsion Study'!A11 -> Structural battery concept | B21: ='CS Propulsion Study'!T11 -> 3.2731422 | C21: ='CS Propulsion Study'!Z11 -> 1.9513043
A22: ='CS Propulsion Study'!A12 -> Lowest motor mass | B22: ='CS Propulsion Study'!T12 -> 3.3857316 | C22: ='CS Propulsion Study'!Z12 -> 2.4545455
A23: ='CS Propulsion Study'!A13 -> 1202.5 alternative | B23: ='CS Propulsion Study'!T13 -> 3.4686638 | C23: ='CS Propulsion Study'!Z13 -> 2.3736264
A24: ='CS Propulsion Study'!A14 -> Research-platform minimum | B24: ='CS Propulsion Study'!T14 -> 1.1701609 | C24: ='CS Propulsion Study'!Z14 -> 3.0545455
A25: ='CS Propulsion Study'!A15 -> Aquila endurance analog | B25: ='CS Propulsion Study'!T15 -> 2.7349092 | C25: ='CS Propulsion Study'!Z15 -> 5.0285714
A26: ='CS Propulsion Study'!A16 -> High-authority 3S | B26: ='CS Propulsion Study'!T16 -> 6.0818404 | C26: ='CS Propulsion Study'!Z16 -> 2.2956522
A30: Decision status: a removable central 2S pack is the defensible V1 architecture. Frame-integrated batteries remain a later research track after propulsion, mass properties, thermal behavior, crash protection, charging/balancing, and recovery dynamics are experimentally characterized.

Sheet CS Propulsion Study
A1: Motor–Propeller–Battery Estimate Study
A2: Formula-driven planning comparison. Only EX1103/2023 values use a published motor bench curve; all estimated cases require thrust-stand verification.
A4: Scenario | B4: Motor | C4: Propeller | D4: Battery | E4: Battery architecture | F4: Base mass excl. motor/prop/batt (g) | G4: Motor mass each (g) | H4: Prop set mass (g) | I4: Battery mass (g) | J4: Integration penalty (g) | K4: Total flying mass (g) | L4: Capacity (mAh) | M4: C rating | N4: Nominal V | O4: Energy (Wh) | P4: Usable fraction | Q4: Usable energy (Wh) | R4: Max thrust / motor (g) | S4: Total max thrust (g) | T4: Static T/W | U4: Max current / motor (A) | V4: Max system current (A) | W4: Battery continuous current (A) | X4: Discharge check | Y4: Estimated hover current (A) | Z4: Estimated flight time (min) | AA4: Notes
A5: Baseline documented | B5: EX1103 11000KV | C5: 2023-3 | D5: LAVA 450 2S | E5: Removable central pouch | F5: 82.75 | G5: 3.8 | H5: 3.52 | I5: 26.1 | J5: 0 | K5: =F5+4*G5+H5+I5+J5 -> 127.57 | L5: 450 | M5: 75 | N5: 7.6 | O5: =L5/1000*N5 -> 3.42 | P5: 0.8 | Q5: =O5*P5 -> 2.736 | R5: 121.9 | S5: =4*R5 -> 487.6 | T5: =S5/K5 -> 3.8222153 | U5: 9.2 | V5: =4*U5+0.5 -> 37.3 | W5: =L5/1000*M5 -> 33.75 | X5: =IF(W5>=V5,"PASS","FAIL") -> FAIL | Y5: 9.5 | Z5: =60*(L5/1000)*P5/Y5 -> 2.2736842 | AA5: Official motor curve; hover current estimated from curve
A6: Middle-capacity candidate | B6: EX1103 11000KV | C6: 2023-3 | D6: LAVA 550 2S | E6: Removable central pouch | F6: 82.75 | G6: 3.8 | H6: 3.52 | I6: 29.5 | J6: 0 | K6: =F6+4*G6+H6+I6+J6 -> 130.97 | L6: 550 | M6: 75 | N6: 7.6 | O6: =L6/1000*N6 -> 4.18 | P6: 0.8 | Q6: =O6*P6 -> 3.344 | R6: 121.9 | S6: =4*R6 -> 487.6 | T6: =S6/K6 -> 3.72299 | U6: 9.2 | V6: =4*U6+0.5 -> 37.3 | W6: =L6/1000*M6 -> 41.25 | X6: =IF(W6>=V6,"PASS","FAIL") -> PASS | Y6: 9.8 | Z6: =60*(L6/1000)*P6/Y6 -> 2.6938776 | AA6: Battery mass estimated; verify
A7: Endurance/current candidate | B7: EX1103 11000KV | C7: 2023-3 | D7: GNB 650 2S | E7: Removable central pouch | F7: 82.75 | G7: 3.8 | H7: 3.52 | I7: 36 | J7: 0 | K7: =F7+4*G7+H7+I7+J7 -> 137.47 | L7: 650 | M7: 120 | N7: 7.6 | O7: =L7/1000*N7 -> 4.94 | P7: 0.8 | Q7: =O7*P7 -> 3.952 | R7: 121.9 | S7: =4*R7 -> 487.6 | T7: =S7/K7 -> 3.5469557 | U7: 9.2 | V7: =4*U7+0.5 -> 37.3 | W7: =L7/1000*M7 -> 78 | X7: =IF(W7>=V7,"PASS","FAIL") -> PASS | Y7: 10.2 | Z7: =60*(L7/1000)*P7/Y7 -> 3.0588235 | AA7: Heavier but strong current headroom
A8: Heavy endurance | B8: EX1103 11000KV | C8: 2023-3 | D8: Tattu 650 2S | E8: Removable central pouch | F8: 82.75 | G8: 3.8 | H8: 3.52 | I8: 43 | J8: 0 | K8: =F8+4*G8+H8+I8+J8 -> 144.47 | L8: 650 | M8: 75 | N8: 7.4 | O8: =L8/1000*N8 -> 4.81 | P8: 0.8 | Q8: =O8*P8 -> 3.848 | R8: 121.9 | S8: =4*R8 -> 487.6 | T8: =S8/K8 -> 3.3750952 | U8: 9.2 | V8: =4*U8+0.5 -> 37.3 | W8: =L8/1000*M8 -> 48.75 | X8: =IF(W8>=V8,"PASS","FAIL") -> PASS | Y8: 10.5 | Z8: =60*(L8/1000)*P8/Y8 -> 2.9714286 | AA8: Heavy; recovery penalty
A9: Central integrated bay | B9: EX1103 11000KV | C9: 2023-3 | D9: LAVA 550 2S | E9: Semi-integrated protected central bay | F9: 82.75 | G9: 3.8 | H9: 3.52 | I9: 29.5 | J9: 4 | K9: =F9+4*G9+H9+I9+J9 -> 134.97 | L9: 550 | M9: 75 | N9: 7.6 | O9: =L9/1000*N9 -> 4.18 | P9: 0.78 | Q9: =O9*P9 -> 3.2604 | R9: 121.9 | S9: =4*R9 -> 487.6 | T9: =S9/K9 -> 3.6126547 | U9: 9.2 | V9: =4*U9+0.5 -> 37.3 | W9: =L9/1000*M9 -> 41.25 | X9: =IF(W9>=V9,"PASS","FAIL") -> PASS | Y9: 10.1 | Z9: =60*(L9/1000)*P9/Y9 -> 2.5485149 | AA9: Moderate integration penalty
A10: Split-arm battery concept | B10: EX1103 11000KV | C10: 2023-3 | D10: 2 x 1S 450 equivalent | E10: Split 2 x 1S cells in opposing arms, series wired | F10: 82.75 | G10: 3.8 | H10: 3.52 | I10: 26.1 | J10: 12 | K10: =F10+4*G10+H10+I10+J10 -> 139.57 | L10: 450 | M10: 75 | N10: 7.6 | O10: =L10/1000*N10 -> 3.42 | P10: 0.72 | Q10: =O10*P10 -> 2.4624 | R10: 121.9 | S10: =4*R10 -> 487.6 | T10: =S10/K10 -> 3.4935874 | U10: 9.2 | V10: =4*U10+0.5 -> 37.3 | W10: =L10/1000*M10 -> 33.75 | X10: =IF(W10>=V10,"PASS","FAIL") -> FAIL | Y10: 10.8 | Z10: =60*(L10/1000)*P10/Y10 -> 1.8 | AA10: Mass/inertia/wiring penalties; research only
A11: Structural battery concept | B11: EX1103 11000KV | C11: 2023-3 | D11: Custom embedded 2S 550 | E11: Four distributed/structural frame cells | F11: 82.75 | G11: 3.8 | H11: 3.52 | I11: 29.5 | J11: 18 | K11: =F11+4*G11+H11+I11+J11 -> 148.97 | L11: 550 | M11: 50 | N11: 7.6 | O11: =L11/1000*N11 -> 4.18 | P11: 0.68 | Q11: =O11*P11 -> 2.8424 | R11: 121.9 | S11: =4*R11 -> 487.6 | T11: =S11/K11 -> 3.2731422 | U11: 9.2 | V11: =4*U11+0.5 -> 37.3 | W11: =L11/1000*M11 -> 27.5 | X11: =IF(W11>=V11,"PASS","FAIL") -> FAIL | Y11: 11.5 | Z11: =60*(L11/1000)*P11/Y11 -> 1.9513043 | AA11: Highest uncertainty and safety risk
A12: Lowest motor mass | B12: BETAFPV 1103 11000KV | C12: Gemfan 2015-2 | D12: LAVA 450 2S | E12: Removable central pouch | F12: 82.75 | G12: 3.3 | H12: 2 | I12: 26.1 | J12: 0 | K12: =F12+4*G12+H12+I12+J12 -> 124.05 | L12: 450 | M12: 75 | N12: 7.6 | O12: =L12/1000*N12 -> 3.42 | P12: 0.8 | Q12: =O12*P12 -> 2.736 | R12: 105 | S12: =4*R12 -> 420 | T12: =S12/K12 -> 3.3857316 | U12: 8.5 | V12: =4*U12+0.5 -> 34.5 | W12: =L12/1000*M12 -> 33.75 | X12: =IF(W12>=V12,"PASS","FAIL") -> FAIL | Y12: 8.8 | Z12: =60*(L12/1000)*P12/Y12 -> 2.4545455 | AA12: Thrust/current estimated from similar 1103 platform
A13: 1202.5 alternative | B13: Flywoo ROBO 1202.5 11500KV | C13: 2023S-3 | D13: LAVA 450 2S | E13: Removable central pouch | F13: 82.75 | G13: 3.8 | H13: 2.8 | I13: 26.1 | J13: 0 | K13: =F13+4*G13+H13+I13+J13 -> 126.85 | L13: 450 | M13: 75 | N13: 7.6 | O13: =L13/1000*N13 -> 3.42 | P13: 0.8 | Q13: =O13*P13 -> 2.736 | R13: 110 | S13: =4*R13 -> 440 | T13: =S13/K13 -> 3.4686638 | U13: 8.8 | V13: =4*U13+0.5 -> 35.7 | W13: =L13/1000*M13 -> 33.75 | X13: =IF(W13>=V13,"PASS","FAIL") -> FAIL | Y13: 9.1 | Z13: =60*(L13/1000)*P13/Y13 -> 2.3736264 | AA13: Estimated; bench curve required
A14: Research-platform minimum | B14: Crazyflie 08028 10000KV | C14: 55 mm optimized | D14: 1S 350 | E14: Removable central pouch | F14: 82.75 | G14: 2.3 | H14: 1.5 | I14: 9.1 | J14: 0 | K14: =F14+4*G14+H14+I14+J14 -> 102.55 | L14: 350 | M14: 30 | N14: 3.7 | O14: =L14/1000*N14 -> 1.295 | P14: 0.8 | Q14: =O14*P14 -> 1.036 | R14: 30 | S14: =4*R14 -> 120 | T14: =S14/K14 -> 1.1701609 | U14: 3 | V14: =4*U14+0.5 -> 12.5 | W14: =L14/1000*M14 -> 10.5 | X14: =IF(W14>=V14,"PASS","FAIL") -> FAIL | Y14: 5.5 | Z14: =60*(L14/1000)*P14/Y14 -> 3.0545455 | AA14: Cannot meet 2:1 at project base mass
A15: Aquila endurance analog | B15: Aquila 1103 10500KV | C15: 2218-3 | D15: Aquila 1100 2S | E15: Removable central pouch | F15: 82.75 | G15: 3.5 | H15: 2.32 | I15: 54.5 | J15: 0 | K15: =F15+4*G15+H15+I15+J15 -> 153.57 | L15: 1100 | M15: 15 | N15: 7.6 | O15: =L15/1000*N15 -> 8.36 | P15: 0.8 | Q15: =O15*P15 -> 6.688 | R15: 105 | S15: =4*R15 -> 420 | T15: =S15/K15 -> 2.7349092 | U15: 8 | V15: =4*U15+0.5 -> 32.5 | W15: =L15/1000*M15 -> 16.5 | X15: =IF(W15>=V15,"PASS","FAIL") -> FAIL | Y15: 10.5 | Z15: =60*(L15/1000)*P15/Y15 -> 5.0285714 | AA15: Thrust/current estimated; low-C pack limits peaks
A16: High-authority 3S | B16: LAVA 1104 7200KV | C16: 2218-3 | D16: 3S 550 | E16: Removable central pouch | F16: 82.75 | G16: 5.3 | H16: 2.32 | I16: 45 | J16: 0 | K16: =F16+4*G16+H16+I16+J16 -> 151.27 | L16: 550 | M16: 75 | N16: 11.4 | O16: =L16/1000*N16 -> 6.27 | P16: 0.8 | Q16: =O16*P16 -> 5.016 | R16: 230 | S16: =4*R16 -> 920 | T16: =S16/K16 -> 6.0818404 | U16: 10.2 | V16: =4*U16+0.5 -> 41.3 | W16: =L16/1000*M16 -> 41.25 | X16: =IF(W16>=V16,"PASS","FAIL") -> FAIL | Y16: 11.5 | Z16: =60*(L16/1000)*P16/Y16 -> 2.2956522 | AA16: Outside baseline; high speed and impact energy

Sheet CS Component Candidates
A1: Drone Component Candidate Register
A2: Source-linked catalog research; 'Verify' and 'estimated' entries must be confirmed before selection.
A4: Category | B4: Product | C4: Function | D4: Mass (g) | E4: Dimensions | F4: Voltage | G4: Key specifications | H4: Engineering assessment | I4: Price | J4: Evidence basis | K4: Current disposition | L4: Source URL
A5: Flight Controller | B5: Holybro Kakute H7 Mini | C5: FC | D5: 5.5 | E5: 31 x 30 x 6 | F5: 2-6S | G5: STM32H743 480 MHz; ICM-42688-P; SPA06; 6 UART; 128 Mbit flash | H5: ArduPilot supported; strong logging/autonomy baseline | I5: $58.99 | J5: Datasheet | K5: Recommended baseline | L5: https://holybro.com/products/kakute-h7-mini
A6: Flight Controller | B6: Matek H743-MINI | C6: FC | D6: 7.0 | E6: 36 x 28 x 6.5 | F6: 2-8S | G6: STM32H743; dual IMU; DPS310; microSD; CAN; 5.5 UART | H6: ArduPilot target; strongest redundancy, slightly heavier | I6: Verify | J6: Datasheet | K6: Strong alternative | L6: https://www.mateksys.com/?portfolio=h743-mini
A7: Flight Controller/AIO | B7: BETAFPV F4 2-3S 20A AIO V1 | C7: FC + 4-in-1 ESC | D7: 5.58-5.92 | E7: 26 x 26 | F7: 2-3S | G7: STM32F405; ICM42688P/42605; barometer; 16 MB; 20A continuous | H7: Very low system mass; firmware/autonomy compatibility must be verified | I7: $54.99 | J7: Datasheet | K7: Mass-leading candidate | L7: https://betafpv.com/products/f4-2-3s-20a-aio-fc-v1
A8: Flight Controller/AIO | B8: BETAFPV F405 2-4S AIO V3 | C8: FC + 4-in-1 ESC | D8: Verify | E8: 26 x 26 | F8: 2-4S | G8: F405 AIO; 12A/20A variants | H8: Attractive packaging; exact variant and firmware support need verification | I8: Verify | J8: Partial datasheet | K8: Research candidate | L8: https://betafpv.com/products/f405-20a-aio-2-4s-brushless-flight-controllerblheli_s-v3
A9: Flight Controller/AIO | B9: Happymodel X12 Lite | C9: FC + 4-in-1 ESC + ELRS | D9: Verify | E9: Whoop AIO | F9: 2S | G9: F411; ICM42688P; 12A ESC; ELRS | H9: High integration; F411 resources and autonomy support are limiting | I9: Verify | J9: Reference platform | K9: Prototype-only candidate | L9: https://www.happymodel.cn/index.php/2023/03/21/bassline-digital-hd-2s-toothpick-fpv-drone-built-in-walksnail-or-hdzero-vtx/
A10: Flight Platform | B10: Crazyflie 2.1 Brushless | C10: Integrated platform | D10: 32-37 | E10: Platform | F10: 1S | G10: STM32F405; BMI088; BMP388; 5A ESCs; radio | H10: Excellent research ecosystem; limited payload/thrust for custom guarded frame | I10: Verify | J10: Datasheet | K10: Benchmark / research option | L10: https://www.bitcraze.io/products/crazyflie-2-1-brushless/
A11: Flight Controller | B11: SpeedyBee F405 Wing Mini | C11: Fixed-wing FC | D11: 5.5 | E11: Compact | F11: 2-6S | G11: F405; fixed-wing I/O | H11: Low mass but wrong control/output architecture for this quad | I11: Verify | J11: Datasheet | K11: Not recommended | L11: https://www.speedybee.com/speedybee-f405-wing-mini-fixed-wing-flight-controller/
A12: Motor | B12: Happymodel EX1103 11000KV | C12: Motor | D12: 3.8 each | E12: 11 x 3 stator | F12: 1-2S | G12: Official 2S/2023R curve: 121.9 g at 9.2 A max | H12: Best documented 2S candidate; curve supports auditable model | I12: Verify | J12: Bench curve | K12: Recommended baseline | L12: https://www.happymodel.cn/index.php/2022/09/05/bassline-spare-part-ex1103-kv11000-brushless-motor/
A13: Motor | B13: BETAFPV 1103 11000KV | C13: Motor | D13: 3.3 each | E13: 1103 | F13: 2S | G13: Recommended 40 mm 4-blade or 3020 2-blade | H13: Very light; thrust curve must be bench-tested | I13: $39.99/set | J13: Datasheet | K13: Strong lightweight candidate | L13: https://betafpv.com/products/1103-brushless-motors
A14: Motor | B14: BETAFPV 1103 8000KV | C14: Motor | D14: 3.8 each | E14: 1103 | F14: 3S | G14: Lower KV 3S variant | H14: Higher voltage alternative; guard/prop and risk implications | I14: $39.99/set | J14: Datasheet | K14: Alternative architecture | L14: https://betafpv.com/products/1103-brushless-motors
A15: Motor | B15: BETAFPV 1103 15000KV | C15: Motor | D15: 3.7 each | E15: 1103 | F15: 1S | G15: High-KV 1S variant | H15: Simpler battery but likely lower recovery authority at project mass | I15: $39.99/set | J15: Datasheet | K15: Benchmark only | L15: https://betafpv.com/products/1103-brushless-motors
... A45: Receiver | B45: RadioMaster XR1 | C45: ELRS receiver | D45: 1.0 excl. antenna | E45: 20 x 13 x 3 | F45: 5 V | G45: 100 mW telemetry | H45: Useful telemetry capability; larger than Lite receiver | I45: $11.99 | J45: Datasheet | K45: Alternative | L45: https://radiomasterrc.com/products/xr1-nano-multi-frequency-expresslrs-receiver

Sheet CS Reference Drones
A1: Comparable Small-Drone Benchmarks
A2: Observed combinations ground the estimated propulsion cases; they are not direct proof for this custom vehicle.
A4: Platform | B4: Flying mass | C4: Motor | D4: Propeller | E4: Battery | F4: Reported flight time | G4: Relevant performance | H4: Use in study | I4: Source URL
A5: Crazyflie 2.1 Brushless | B5: 34 g with legs; 37 g guards | C5: 08028 10000KV | D5: 55 mm optimized | E5: 1S 350 mAh, 9.1 g | F5: ~10 min | G5: Up to 30 g/motor; 40 g payload | H5: Research ecosystem and low-mass benchmark | I5: https://www.bitcraze.io/products/crazyflie-2-1-brushless/
A6: Happymodel Bassline 2S | B6: Verify | C6: EX1103 11000KV | D6: 2023 tri-blade | E6: 2S | F6: Verify | G6: Official motor curve reaches 121.9 g/motor | H6: Primary propulsion-performance analog | I6: https://www.happymodel.cn/index.php/2023/03/21/bassline-digital-hd-2s-toothpick-fpv-drone-built-in-walksnail-or-hdzero-vtx/
A7: BETAFPV Meteor85 2S | B7: Verify | C7: 1103 11000KV | D7: Gemfan 2015 2-blade | E7: 2S 300 mAh | F7: ~3 min | G7: Protected 2S whoop | H7: Low-mass removable-pack analog | I7: https://betafpv.com/products/beta85-pro2-whoop-quadcopter-2s
A8: BETAFPV Aquila20 | B8: 122-127 g takeoff | C8: 1103 10500KV | D8: Gemfan 2218 | E8: 2S 1100 mAh, 54.5 g | F8: ~10 min | G8: Large battery at modest mass | H8: Endurance analog; slower protected platform | I8: https://betafpv.com/collections/all-drone/products/aquila20-brushless-whoop-quadcopter
A9: BETAFPV Pavo20 Pro II | B9: 65.2 g PNP | C9: 1104 7200KV | D9: Gemfan 2218 | E9: 3S 550-class | F9: ~6.5 min | G9: Higher-power 3S protected platform | H9: High-authority alternative analog | I9: https://betafpv.com/collections/pavo-whoops/products/pavo20-pro-ii-brushless-whoop-quadcopter
A10: Happymodel Mobula8 O3 | B10: 82.5 g O3 version | C10: EX1103 11000KV | D10: 2-inch tri-blade | E10: 2S | F10: Verify | G10: Protected 2S digital platform | H10: Payload/mass analog | I10: https://www.happymodel.cn/index.php/2023/08/03/happymodel-mobula8-o3-and-o3-lite-tbs-version/
A11: BETAFPV Meteor85 (newer) | B11: Verify | C11: 1103 11000KV | D11: Gemfan 2015 | E11: 2S | F11: Verify | G11: Current protected 2S reference | H11: Confirms common motor/prop pairing | I11: https://betafpv.com/collections/best-sellers/products/meteor85-brushless-whoop-quadcopter-2022

Sheet CS Battery Architectures
A1: Frame-Integrated Battery Architecture Study
A2: Integration penalties are planning estimates and must be replaced by CAD, cell-abuse, thermal, and serviceability evidence.
A4: Architecture | B4: Net integration penalty (g) | C4: Usable energy fraction | D4: Design complexity | E4: Serviceability | F4: Thermal behavior | G4: Impact/fire risk | H4: Recovery/inertia effect | I4: Recommendation
A5: Removable central pouch | B5: 0 | C5: 0.80 | D5: Low | E5: Excellent | F5: Good | G5: Low | H5: Minimum inertia if centered; easiest recovery baseline | I5: Recommended V1
A6: Semi-integrated protected central bay | B6: 4 | C6: 0.78 | D6: Medium | E6: Good | F6: Good with venting | G6: Medium | H6: Still near CG; added enclosure mass | I6: Recommended later iteration
A7: Split 2 x 1S cells in opposing arms, series wired | B7: 12 | C7: 0.72 | D7: High | E7: Poor | F7: Uneven cooling/monitoring risk | G7: High | H7: Raises roll/pitch inertia and slows attitude arrest | I7: Research only; not V1
A8: Four distributed/structural frame cells | B8: 18 | C8: 0.68 | D8: Very high | E8: Very poor | F8: Highest thermal/impact complexity | G8: Very high | H8: Largest inertia penalty; uncertain load paths and cell abuse | I8: Deferred research concept
A10: Core conclusion: embedding cells away from the CG may improve packaging but increases inertia, slows attitude arrest, complicates charging/balancing, and makes crash-damaged cells harder to isolate. Keep the V1 pack removable and centered.

Sheet CS Sources
A1: Model Assumptions, Equations, and Limitations
A2: Yellow values are planning inputs. The workbook is a selection-screening tool, not a substitute for bench testing.
A4: Parameter | B4: Best / nominal / value | C4: Worst / range | D4: Units | E4: Basis | F4: Conservative direction | G4: Use | H4: Source / note
A5: Current project nominal mass | B5: 140.75 | D5: g | E5: Repository mass budget | F5: Higher is worse | G5: Derives non-propulsion base mass | H5: Engineering Data/estimates.csv
A6: Nominal motors in current budget | B6: 23 | D6: g/set | E6: Repository mass budget | F6: Higher is worse | G6: Removed from baseline | H6: Engineering Data/estimates.csv
A7: Nominal props in current budget | B7: 2.5 | D7: g/set | E7: Repository mass budget | F7: Higher is worse | G7: Removed from baseline | H7: Engineering Data/estimates.csv
A8: Nominal battery in current budget | B8: 32.5 | D8: g | E8: Repository mass budget | F8: Higher is worse | G8: Removed from baseline | H8: Engineering Data/estimates.csv
A9: Base aircraft excluding motors/props/battery | B9: 82.75 | D9: g | E9: Calculated | F9: Higher is worse | G9: Scenario base mass | H9: 140.75 - 23 - 2.5 - 32.5
A10: Static thrust-to-weight requirement | B10: 2.0 | D10: ratio | E10: Fixed requirement | F10: Lower is worse | G10: Initial propulsion screen | H10: Engineering Plan
A11: Avionics current allowance | B11: 0.5 | D11: A | E11: Estimated | F11: Higher is worse | G11: Maximum system current | H11: Replace with measurement
A12: Removable battery usable fraction | B12: 0.80 | D12: fraction | E12: Estimated | F12: Lower is worse | G12: Flight-time estimate | H12: Planning assumption
A13: Semi-integrated usable fraction | B13: 0.78 | D13: fraction | E13: Estimated | F13: Lower is worse | G13: Flight-time estimate | H13: Thermal/service allowance
A14: Split-arm usable fraction | B14: 0.72 | D14: fraction | E14: Estimated | F14: Lower is worse | G14: Flight-time estimate | H14: Balancing/wiring/thermal allowance
A15: Structural battery usable fraction | B15: 0.68 | D15: fraction | E15: Estimated | F15: Lower is worse | G15: Flight-time estimate | H15: Highest uncertainty/risk
A16: Total mass equation | B16: Base + 4*m_motor + m_prop_set + m_battery + integration penalty | E16: Calculated | G16: Propulsion Study | H16: Formula
A17: Battery energy equation | B17: capacity_Ah * nominal_voltage | D17: Wh | E17: Calculated | G17: Propulsion Study | H17: Formula
A18: Estimated flight time | B18: 60 * capacity_Ah * usable_fraction / hover_current | D18: min | E18: Calculated | G18: Propulsion Study | H18: Does not include reserve/aging beyond usable fraction
A19: Battery continuous current | B19: capacity_Ah * C_rating | D19: A | E19: Calculated | G19: Discharge screen | H19: C ratings may be optimistic
A20: Critical limitation | B20: Recovery torque, motor transient response, thermal performance, and estimator behavior are not proven by static catalog data. | E20: Engineering judgment | G20: Selection gate | H20: Measure on thrust stand and controlled test rig

Sheet CS Checks
A1: Workbook Verification Checks
A2: PASS means the screening workbook is internally consistent; it does not certify hardware.
A4: Check | B4: Formula / criterion | C4: Result | D4: Interpretation
A5: Candidate breadth | B5: At least 35 candidates | C5: =IF(COUNTA('CS Component Candidates'!B5:B100)>=35,"PASS","FAIL") -> PASS | D5: Wide initial option set
A6: Scenario breadth | B6: At least 10 scenarios | C6: =IF(COUNTA('CS Propulsion Study'!A5:A100)>=10,"PASS","FAIL") -> PASS | D6: Multiple architectures compared
A7: Baseline static T/W | B7: Baseline >= 2.0 | C7: =IF('CS Propulsion Study'!T5>=2,"PASS","FAIL") -> PASS | D7: Initial propulsion screen
A8: Baseline discharge | B8: Baseline pack continuous current >= estimated max | C8: ='CS Propulsion Study'!X5 -> FAIL | D8: Catalog C-rating screen only
A9: All source URLs populated | B9: No missing source cells | C9: =IF(COUNTBLANK('CS Component Candidates'!L5:L44)=0,"PASS","FAIL") -> PASS | D9: Sources auditable
A10: Frame battery warning present | B10: Architecture sheet populated | C10: =IF(COUNTA('CS Battery Architectures'!A5:A8)=4,"PASS","FAIL") -> PASS | D10: Integration alternatives explicit

Sheet Component Selection
A1: Original sheet | B1: Source row | C1: Source column A | D1: Source column B | E1: Source column C | F1: Source column D | G1: Source column E | H1: Source column F | I1: Source column G | J1: Source column H | K1: Source column I | L1: Source column J
A2: 00_Method_Envelope | B2: 1 | C2: MechAudit-style component selection — Guarded Micro-UAV (SelfStabilizingDrone)
A3: 00_Method_Envelope | B3: 2 | C3: Generated 2026-06-19 from 5 clustered deep-research streams vs primary/vendor sources.
A4: 00_Method_Envelope | B4: 4 | C4: DESIGN ENVELOPE
A5: 00_Method_Envelope | B5: 5 | C5: FAA sub-250g; planning mass target <=200g; hard abort ceiling 225g.
A6: 00_Method_Envelope | B6: 6 | C6: Power 2S LiPo; motors 1103-class ~11000KV; props 2.0-2.3"; static T/W >= 2.0.
A7: 00_Method_Envelope | B7: 7 | C7: Onboard vision/compute for release-event detection + self-stabilization recovery; ELRS 2.4GHz; printed PETG/nylon frame w/ prop guards.
A8: 00_Method_Envelope | B8: 9 | C8: KEY ENGINEERING SCREENS
A9: 00_Method_Envelope | B9: 10 | C9: Thrust-to-weight: T/W>=2.0 @200g AUW => >=400g total => >=100g/motor. EX1103 11000KV+Gemfan 2023R = 121.9g/motor (mfr, 2S WOT) => 4x=487.6g => T/W 2.44 @200g (3.6 @134g).
A10: 00_Method_Envelope | B10: 11 | C10: Battery current screen: 4-motor peak = 4 x 9.2A = 36.8A. Continuous capability = C-rating x capacity(Ah). 450mAh 75C = 33.75A => FAILS (matches prior screening). 550mAh 75C = 41.25A => passes. Use XT30 (BT2.0 limited ~9-30A).
A11: 00_Method_Envelope | B11: 13 | C11: CONFIDENCE LEGEND
A12: 00_Method_Envelope | B12: 14 | C12: confirmed (green) = from a cited primary/vendor source. inferred (orange) = estimated/derived; verify before purchase.
A13: 00_Method_Envelope | B13: 16 | C13: DECISIONS — Stage 1 status
... A18: 01_Stage1_Locked_BOM | B18: 1 | C18: STAGE 1 LOCKED BOM — autonomy fork resolved to the H7/F7 RESEARCH path (ArduPilot/PX4: logging, estimator access, failsafes) over the mass-minimal Betaflight AIO. The mass budget passes with wide margin, so the recovery-research benefits win. FPV + GPS deferred to Stage 2.
A19: 01_Stage1_Locked_BOM | B19: 2 | C19: Subsystem | D19: Locked part (Stage 1) | E19: Nominal mass (g) | F19: Price ~USD | G19: Why this / rejected alternative
A20: 01_Stage1_Locked_BOM | B20: 3 | C20: Flight controller | D20: Holybro Kakute H7 Mini (H743, 6 UART, baro) | E20: 5.5 | F20: 65 | G20: LOCKED H7 research path: ArduPilot/PX4, MAVLink companion link, blackbox logging, estimator access, failsafes. Rejected: Happymodel X12 AIO (lighter but Betaflight-only — no estimator/failsafe depth for recovery research).
A21: 01_Stage1_Locked_BOM | B21: 4 | C21: ESC (4-in-1) | D21: HGLRC 13A 2-3S BB2 (20x20) | E21: 3 | F21: 18 | G21: 20x20 matches the H7 FC mount; 13A/ch >> 9.2A/motor; 3g. Rejected: FD13A (16x16 — won't stack on 20x20); Tekko32 45-50A (over-spec, up to 15.6g). Upgrade: BLHeli_32/AM32 telemetry ESC if motor RPM/current logging wanted.
A22: 01_Stage1_Locked_BOM | B22: 5 | C22: Motors x4 | D22: Happymodel EX1103 11000KV | E22: 15.2 | F22: 36 | G22: Only motor with a published 2S+2023 thrust curve (121.9g/motor => 4x=488g). Rejected: <10000KV (fails T/W); T-Motor F1103 (+~5g, thrust table unconfirmed).
A23: 01_Stage1_Locked_BOM | B23: 6 | C23: Propellers (+spares) | D23: Gemfan Hurricane 2023-3 | E23: 3.5 | F23: 6 | G23: The exact prop behind the validated thrust figure (removes inference risk). Rejected: 2.5" pitch (more current draw); sub-2" (less thrust).
A24: 01_Stage1_Locked_BOM | B24: 7 | C24: Battery | D24: GNB 2S 550mAh 100C (XT30) | E24: 29 | F24: 14 | G24: 55A cont >> 36.8A 4-motor peak. Rejected: 450mAh 75C (33.75A FAILS the current screen — your prior failure); BT2.0 (connector-limited). Budget alt: BetaFPV LAVA 550 75C (41.25A).
A25: 01_Stage1_Locked_BOM | B25: 8 | C25: Vision / compute | D25: Arduino Nicla Vision (cam+IMU+ToF) | E25: 19.8 | F25: 90 | G25: Release detection = motion fusion; Nicla bundles camera+6-axis IMU+ToF in 20g, UART to FC. Rejected for Stage 1: Coral Micro (true NPU but mass unpublished); OAK-D-Lite (61g/5W).
A26: 01_Stage1_Locked_BOM | B26: 9 | C26: Positioning | D26: Matek 3901-L0X optical flow + lidar | E26: 2 | F26: 26 | G26: Flow + height in 2g, native ArduPilot — pairs with the H7 path for indoor position/alt hold. GPS deferred (outdoor only).
A27: 01_Stage1_Locked_BOM | B27: 10 | C27: Control link RX | D27: BetaFPV ELRS Lite (+ antenna) | E27: 0.46 | F27: 12 | G27: Lightest; the H7 FC has no onboard RX. Reliability upgrade: RadioMaster RP3 diversity (4.6g) if the guard shadows the antenna.
A28: 01_Stage1_Locked_BOM | B28: 11 | C28: Buzzer + LED | D28: VIFLY Finder Mini + WS2812 strip | E28: 3.3 | F28: 18 | G28: Self-powered finder survives LiPo ejection; WS2812 gives arming/orientation status (~0.5g).
A29: 01_Stage1_Locked_BOM | B29: 12 | C29: Wiring / connectors | D29: XT30 + 22/26AWG silicone + JST-SH | E29: 5.5 | F29: 8 | G29: XT30 for 36.8A peak headroom (BT2.0 connector-limited). Weigh the finished harness.
A30: 01_Stage1_Locked_BOM | B30: 13 | C30: Frame + guards + fasteners | D30: Printed nylon frame + stiff guards + steel M2 | E30: 42.5 | F30: 40 | G30: DESIGN WORK (your items 10/16/18). Guard ring must meet <=1.0mm deflection at the prop edge (SF>=2.0) — verify by FEA + static push test. Biggest single mass + the CAD-dependent unknown.
A31: 01_Stage1_Locked_BOM | B31: 14 | C31: Vision logging | D31: Samsung PRO Endurance 128GB microSD | E31: 0.4 | F31: 25 | G31: Endurance-class for continuous onboard logging (min V30/U3).
... A33: 01_Stage1_Locked_BOM | B33: 16 | C33: GPS | D33: DEFERRED (outdoor only) | E33: 0 | F33: 0 | G33: Indoor recovery uses optical flow. Outdoor add-on: Matek M10Q-5883 (8g).
A34: 01_Stage1_Locked_BOM | B34: 17 | C34: NOMINAL FLYING TOTAL (Stage 1, FPV/GPS deferred) | E34: 130.2 | F34: 358
A35: 01_Stage1_Locked_BOM | B35: 18 | C35: vs 200g target: 69.8g margin | vs 225g abort ceiling: 94.8g margin | T/W @ this AUW = 3.75 (>=2.0 required)
A36: 01_Stage1_Locked_BOM | B36: 19 | C36: Frame/guard mass (42.5g nominal) dominates and is the CAD-dependent unknown — even at worst-case (frame 50g, vision 25g) + Stage-2 FPV (~3.6g) the build stays well under the 225g ceiling. Support gear (non-flying, not in total): ToolkitRC M6AC charger ~$60; thrust stand (DIY 1-2kg load cell ~$30 or used RCbenchmark 1520 ~$165); PVC+net cage ~$40; tethered release fixture ~$20.
A37: 04_Motors | B37: 1 | C37: Motors (1103-class, 2S) — CRITICAL. Envelope: T/W>=2.0 needs >=100g/motor @200g AUW. EX1103 11000KV = 121.9g/motor (mfr, 2S+2023R).
A38: 04_Motors | B38: 2 | C38: rank | D38: part_model | E38: key_specs | F38: mass_g | G38: price_usd | H38: pros | I38: cons | J38: primary_source | K38: confidence | L38: rationale
A39: 04_Motors | B39: 3 | C39: 1 | D39: Happymodel EX1103 11000KV | E39: 9N12P, 1.5mm shaft, 1-2S; 121.9g @9.2A,68W on Gemfan 2023R (2S WOT) | F39: 3.8 | G39: 8-10 | H39: ONLY motor w/ published 2S+2" thrust curve; 4x=488g => T/W 2.44 @200g; proven; cheap | I39: Mfr test (not independent); 9.2A/motor => 36.8A pack peak | J39: happymodel.cn EX1103 KV11000 | K39: confirmed | L39: Only end-to-end documented 2S+2023 curve; clears envelope with real numbers. BASELINE.
A40: 04_Motors | B40: 4 | C40: 2 | D40: BetaFPV 1103 11000KV | E40: 1.5mm shaft, M1.6 on 8.5mm BC, 14mm, 2S, JST-1.25 | F40: 3.3-3.8 | G40: 9-11 | H40: Cleanest documented mount geometry for printed frame; explicit 2S targeting | I40: No thrust table published; thrust inferred from EX1103 | J40: betafpv.com 1103 | K40: confirmed/inferred | L40: Electrically same class; best mounting docs; infer thrust ~ EX1103.
A41: 04_Motors | B41: 5 | C41: 3 | D41: T-Motor F1103-II 11000KV | E41: 9N12P, step-shaft, NMB502Z bearing, 2-3S | F41: ~5.1 | G41: 13-16 | H41: Premium bearing + anti-disengage step shaft = durability for crash-prone guarded build | I41: Heaviest (~+5g AUW); thrust table not accessible; priciest | J41: getfpv.com t-motor-f1103 | K41: confirmed/inferred | L41: Durability pick; demoted on weight + unconfirmed thrust.
A42: 04_Motors | B42: 6 | C42: 4 | D42: iFlight XING-E Nano 1103 10000KV | E42: 1.5mm shaft, 2-3S, rated 1.2-2.5" props | F42: ~3.6 | G42: 10-13 | H42: Lightest confirmed mass; explicitly 2" on 2S; reputable | I42: 10000KV < baseline => slightly less thrust; no 2S+2" table | J42: amazon iFlight 1103 | K42: confirmed/inferred | L42: Strong light pick; 10000KV under baseline so below 11000KV trio.
A43: 04_Motors | B43: 7 | C43: 5 | D43: Flywoo NIN 1103 V2 10500KV | E43: 1.5mm shaft, 2S; 7650/10500KV options | F43: ~3.5 | G43: 11-13 | H43: Light; 10500KV near baseline; good build rep | I43: Specs from search summary only (page 403); no thrust table | J43: getfpv.com flywoo-nin-1103 | K43: inferred | L43: Viable near-baseline alt; mid-rank for unconfirmed specs.
A44: 04_Motors | B44: 8 | C44: 6 | D44: Happymodel EX1103 8000KV | E44: 9N12P, 1.5mm shaft, 2-3S | F44: 3.7 | G44: 8-10 | H44: Same proven body; better for 2.5" / lower current / longer 2S flight | I44: 8000KV on 2"/2S underspins => likely <100g/motor; better on 3S | J44: happymodel.cn EX1103 6/8/12k | K44: confirmed | L44: Completeness; KV too low for 2S+2" T/W>=2 unless prop grows.
A45: 04_Motors | B45: 9 | C45: 7 | D45: RCInPower GTS V3 (no 1103) | E45: GTS V3 line is 1002/1003-class, NOT 1103 | F45: - | G45: - | H45: Excellent bearings/build IF a 1003 substitution acceptable | I45: Not a 1103; off-spec | J45: racedayquads RCInPower GTS V3 | K45: confirmed | L45: Recorded only to note RCInPower has no 1103 in this line.
A46: 04_Motors | B46: 10 | C46: 8 | D46: Emax TH1103 7000KV | E46: 1.5mm shaft, Tinyhawk-class | F46: ~3.5 | G46: 7-9 | H46: Cheap, available | I46: 7000KV = 1S/light-2S whoop motor; won't reach T/W 2 on 2S+2" | J46: racedayquads emax-th1103 | K46: confirmed | L46: Lowest; KV far under baseline, fails thrust target.
A47: 05_Propellers | B47: 1 | C47: Propellers 2.0-2.3" — CRITICAL. Gemfan 2023-3 is the prop behind the validated EX1103 thrust figure.
A48: 05_Propellers | B48: 2 | C48: rank | D48: part_model | E48: key_specs | F48: mass_g | G48: price_usd | H48: pros | I48: cons | J48: primary_source | K48: confidence | L48: rationale
A49: 05_Propellers | B49: 3 | C49: 1 | D49: Gemfan Hurricane 2023-3 | E49: 2.0"D x 2.3" pitch, 3-blade, PC, 1.5mm bore, 3-hole T-mount, 52.2mm disk | F49: 0.88 | G49: ~3/set | H49: THE prop in the EX1103 121.9g data point => removes thrust-inference risk; correct 1.5mm bore | I49: 3-hole hub must match bell; PC less flexible in crash | J49: flywoo/getfpv 2023-3 | K49: confirmed | L49: Specifying it collapses all thrust uncertainty. BASELINE.
A50: 05_Propellers | B50: 4 | C50: 2 | D50: HQProp T2X2.3X3 | E50: 2.0"D x 2.3" pitch, 3-blade, PC, 1.5mm T-mount, ~10mm hub | F50: ~0.75-0.85 | G50: ~3/set | H50: Exact 2.3" pitch baseline; HQ Durable PC tolerates guard strikes; lightest | I50: No 1103+2S curve; exact 2.3 mass interpolated | J50: hqprop.com T2X2X3 | K50: confirmed/inferred | L50: Closest direct match to 2.3" baseline w/ durable PC.
